Workbook
Name CT: Settings!$B$5
Name QMAX: Settings!$B$7
Name TOL: Settings!$B$8
Name WT: Settings!$B$6
Name YT: Settings!$B$4

Sheet Guide
A1: KRGI ACADEMIC AUDIT FRAMEWORK (NBA Tier-I aligned)
A2: Group: K. Ramakrishnan Group of Institutions - KRCT, KRCE, MKCE. Scope: every department of all three institutes.
A4: 1. Audit cycles
A5: Mid-Semester audit: cross-department WITHIN the same institute (e.g., KRCT ECE auditors audit KRCT CSE). Scope = metrics marked 'Yes' in the Mid-Sem column (mainly Plan/Do/Check process metrics).
A6: End-Semester audit: CROSS-INSTITUTIONAL (auditors from KRCT/KRCE/MKCE audit a different institute). Scope = all metrics, C1 to C9.
A7: Auditors are drawn from the pooled list on 'Auditor Pool' (two per department: one senior + one with 3-5 years' experience, nominated by Head-IQAC). The deployment rule is checked automatically on 'Audit Allocation' and on each 'Dept Audit' sheet.
A9: 2. Two-stage method
A10: Stage A - Digital audit: the department uploads proof for every metric to its Drive evidence folder and pastes the link in column P, fills the claimed value / self-score (column O) and evidence status (Q). Auditors do a desk review and enter the audited value / score (R).
A11: Stage B - Physical audit (one day): auditors visit the department to validate the claims. Column V flags 'Mandatory' checks (evidence not complete, or claim exceeds audited value by more than the tolerance in Settings). Other metrics are sampled. The validated value goes in X; the final score uses the physical result wherever it was Partially Verified / Not Verified.
A13: 3. Grading (thresholds editable on 'Settings')
A14: Y : more than 75% | C : 60% to 75% | W : 40% to below 60% | D : below 40%
A15: Grades are computed for every metric, sub-criterion, criterion and the overall department score.
... A32: Example (quantitative): 4.6 Placement, Benchmark 80, Claimed 72, Audited 68 -> Digital 85% (Y); physical audit finds offer letters for 60 -> Partially Verified, validated 60 -> Final 75% (C).

Sheet KRGI Dashboard
A1: KRGI ACADEMIC AUDIT DASHBOARD - ALL DEPARTMENTS (KRCT + KRCE + MKCE)
A2: Enter validated % per criterion from each department's 'Criterion Summary' (column G), or link with IMPORTRANGE. Grades and counts are automatic.
A4: Institute | B4: Cycle | C4: Departments audited | D4: Average overall % | E4: Grade
A5: KRCT | B5: Mid-Semester | C5: =COUNTIFS($A$14:$A$200,A5,$B$14:$B$200,B5,$M$14:$M$200,"<>") -> 0 | D5: =IF(C5=0,"",AVERAGEIFS($M$14:$M$200,$A$14:$A$200,A5,$B$14:$B$200,B5)) | E5: =IF(D5="","",IF(D5>YT,"Y",IF(D5>=CT,"C",IF(D5>=WT,"W","D"))))
A6: KRCT | B6: End-Semester | C6: =COUNTIFS($A$14:$A$200,A6,$B$14:$B$200,B6,$M$14:$M$200,"<>") -> 0 | D6: =IF(C6=0,"",AVERAGEIFS($M$14:$M$200,$A$14:$A$200,A6,$B$14:$B$200,B6)) | E6: =IF(D6="","",IF(D6>YT,"Y",IF(D6>=CT,"C",IF(D6>=WT,"W","D"))))
A7: KRCE | B7: Mid-Semester | C7: =COUNTIFS($A$14:$A$200,A7,$B$14:$B$200,B7,$M$14:$M$200,"<>") -> 0 | D7: =IF(C7=0,"",AVERAGEIFS($M$14:$M$200,$A$14:$A$200,A7,$B$14:$B$200,B7)) | E7: =IF(D7="","",IF(D7>YT,"Y",IF(D7>=CT,"C",IF(D7>=WT,"W","D"))))
A8: KRCE | B8: End-Semester | C8: =COUNTIFS($A$14:$A$200,A8,$B$14:$B$200,B8,$M$14:$M$200,"<>") -> 0 | D8: =IF(C8=0,"",AVERAGEIFS($M$14:$M$200,$A$14:$A$200,A8,$B$14:$B$200,B8)) | E8: =IF(D8="","",IF(D8>YT,"Y",IF(D8>=CT,"C",IF(D8>=WT,"W","D"))))
A9: MKCE | B9: Mid-Semester | C9: =COUNTIFS($A$14:$A$200,A9,$B$14:$B$200,B9,$M$14:$M$200,"<>") -> 0 | D9: =IF(C9=0,"",AVERAGEIFS($M$14:$M$200,$A$14:$A$200,A9,$B$14:$B$200,B9)) | E9: =IF(D9="","",IF(D9>YT,"Y",IF(D9>=CT,"C",IF(D9>=WT,"W","D"))))
A10: MKCE | B10: End-Semester | C10: =COUNTIFS($A$14:$A$200,A10,$B$14:$B$200,B10,$M$14:$M$200,"<>") -> 0 | D10: =IF(C10=0,"",AVERAGEIFS($M$14:$M$200,$A$14:$A$200,A10,$B$14:$B$200,B10)) | E10: =IF(D10="","",IF(D10>YT,"Y",IF(D10>=CT,"C",IF(D10>=WT,"W","D"))))
A13: Institute | B13: Department | C13: Cycle | D13: C1 | E13: C2 | F13: C3 | G13: C4 | H13: C5 | I13: C6 | J13: C7 | K13: C8 | L13: C9 | M13: Overall % | N13: Overall grade | O13: Criteria at Y | P13: Criteria at C | Q13: Criteria at W | R13: Criteria at D | S13: Audit status | T13: Link to department audit file
A14: KRCT | B14: AI&DS | C14: Mid-Semester | N14: =IF(M14="","",IF(M14>YT,"Y",IF(M14>=CT,"C",IF(M14>=WT,"W","D")))) | O14: =COUNTIF(D14:L14,">"&YT) -> 0 | P14: =COUNTIFS(D14:L14,">="&CT,D14:L14,"<="&YT) -> 0 | Q14: =COUNTIFS(D14:L14,">="&WT,D14:L14,"<"&CT) -> 0 | R14: =COUNTIF(D14:L14,"<"&WT) -> 0
A15: KRCT | B15: AI&ML | C15: Mid-Semester | N15: =IF(M15="","",IF(M15>YT,"Y",IF(M15>=CT,"C",IF(M15>=WT,"W","D")))) | O15: =COUNTIF(D15:L15,">"&YT) -> 0 | P15: =COUNTIFS(D15:L15,">="&CT,D15:L15,"<="&YT) -> 0 | Q15: =COUNTIFS(D15:L15,">="&WT,D15:L15,"<"&CT) -> 0 | R15: =COUNTIF(D15:L15,"<"&WT) -> 0
A16: KRCT | B16: IT | C16: Mid-Semester | N16: =IF(M16="","",IF(M16>YT,"Y",IF(M16>=CT,"C",IF(M16>=WT,"W","D")))) | O16: =COUNTIF(D16:L16,">"&YT) -> 0 | P16: =COUNTIFS(D16:L16,">="&CT,D16:L16,"<="&YT) -> 0 | Q16: =COUNTIFS(D16:L16,">="&WT,D16:L16,"<"&CT) -> 0 | R16: =COUNTIF(D16:L16,"<"&WT) -> 0
A17: KRCT | B17: CSE | C17: Mid-Semester | N17: =IF(M17="","",IF(M17>YT,"Y",IF(M17>=CT,"C",IF(M17>=WT,"W","D")))) | O17: =COUNTIF(D17:L17,">"&YT) -> 0 | P17: =COUNTIFS(D17:L17,">="&CT,D17:L17,"<="&YT) -> 0 | Q17: =COUNTIFS(D17:L17,">="&WT,D17:L17,"<"&CT) -> 0 | R17: =COUNTIF(D17:L17,"<"&WT) -> 0
A18: KRCT | B18: ECE | C18: Mid-Semester | N18: =IF(M18="","",IF(M18>YT,"Y",IF(M18>=CT,"C",IF(M18>=WT,"W","D")))) | O18: =COUNTIF(D18:L18,">"&YT) -> 0 | P18: =COUNTIFS(D18:L18,">="&CT,D18:L18,"<="&YT) -> 0 | Q18: =COUNTIFS(D18:L18,">="&WT,D18:L18,"<"&CT) -> 0 | R18: =COUNTIF(D18:L18,"<"&WT) -> 0
A19: KRCT | B19: EEE | C19: Mid-Semester | N19: =IF(M19="","",IF(M19>YT,"Y",IF(M19>=CT,"C",IF(M19>=WT,"W","D")))) | O19: =COUNTIF(D19:L19,">"&YT) -> 0 | P19: =COUNTIFS(D19:L19,">="&CT,D19:L19,"<="&YT) -> 0 | Q19: =COUNTIFS(D19:L19,">="&WT,D19:L19,"<"&CT) -> 0 | R19: =COUNTIF(D19:L19,"<"&WT) -> 0
A20: KRCT | B20: MECH | C20: Mid-Semester | N20: =IF(M20="","",IF(M20>YT,"Y",IF(M20>=CT,"C",IF(M20>=WT,"W","D")))) | O20: =COUNTIF(D20:L20,">"&YT) -> 0 | P20: =COUNTIFS(D20:L20,">="&CT,D20:L20,"<="&YT) -> 0 | Q20: =COUNTIFS(D20:L20,">="&WT,D20:L20,"<"&CT) -> 0 | R20: =COUNTIF(D20:L20,"<"&WT) -> 0
A21: KRCT | B21: CIVIL | C21: Mid-Semester | N21: =IF(M21="","",IF(M21>YT,"Y",IF(M21>=CT,"C",IF(M21>=WT,"W","D")))) | O21: =COUNTIF(D21:L21,">"&YT) -> 0 | P21: =COUNTIFS(D21:L21,">="&CT,D21:L21,"<="&YT) -> 0 | Q21: =COUNTIFS(D21:L21,">="&WT,D21:L21,"<"&CT) -> 0 | R21: =COUNTIF(D21:L21,"<"&WT) -> 0
A22: KRCT | B22: S&H | C22: Mid-Semester | N22: =IF(M22="","",IF(M22>YT,"Y",IF(M22>=CT,"C",IF(M22>=WT,"W","D")))) | O22: =COUNTIF(D22:L22,">"&YT) -> 0 | P22: =COUNTIFS(D22:L22,">="&CT,D22:L22,"<="&YT) -> 0 | Q22: =COUNTIFS(D22:L22,">="&WT,D22:L22,"<"&CT) -> 0 | R22: =COUNTIF(D22:L22,"<"&WT) -> 0
A23: KRCE | B23: AI&DS | C23: Mid-Semester | N23: =IF(M23="","",IF(M23>YT,"Y",IF(M23>=CT,"C",IF(M23>=WT,"W","D")))) | O23: =COUNTIF(D23:L23,">"&YT) -> 0 | P23: =COUNTIFS(D23:L23,">="&CT,D23:L23,"<="&YT) -> 0 | Q23: =COUNTIFS(D23:L23,">="&WT,D23:L23,"<"&CT) -> 0 | R23: =COUNTIF(D23:L23,"<"&WT) -> 0
A24: KRCE | B24: AI&ML | C24: Mid-Semester | N24: =IF(M24="","",IF(M24>YT,"Y",IF(M24>=CT,"C",IF(M24>=WT,"W","D")))) | O24: =COUNTIF(D24:L24,">"&YT) -> 0 | P24: =COUNTIFS(D24:L24,">="&CT,D24:L24,"<="&YT) -> 0 | Q24: =COUNTIFS(D24:L24,">="&WT,D24:L24,"<"&CT) -> 0 | R24: =COUNTIF(D24:L24,"<"&WT) -> 0
A25: KRCE | B25: IT | C25: Mid-Semester | N25: =IF(M25="","",IF(M25>YT,"Y",IF(M25>=CT,"C",IF(M25>=WT,"W","D")))) | O25: =COUNTIF(D25:L25,">"&YT) -> 0 | P25: =COUNTIFS(D25:L25,">="&CT,D25:L25,"<="&YT) -> 0 | Q25: =COUNTIFS(D25:L25,">="&WT,D25:L25,"<"&CT) -> 0 | R25: =COUNTIF(D25:L25,"<"&WT) -> 0
... A73: MKCE | B73: CSE (CS) | C73: End-Semester | N73: =IF(M73="","",IF(M73>YT,"Y",IF(M73>=CT,"C",IF(M73>=WT,"W","D")))) | O73: =COUNTIF(D73:L73,">"&YT) -> 0 | P73: =COUNTIFS(D73:L73,">="&CT,D73:L73,"<="&YT) -> 0 | Q73: =COUNTIFS(D73:L73,">="&WT,D73:L73,"<"&CT) -> 0 | R73: =COUNTIF(D73:L73,"<"&WT) -> 0

Sheet All Criteria
A1: ALL CRITERIA C1-C9 - QUANTITATIVE METRICS (1000 marks)
A2: Combined view: values come automatically from the C1-C9 Validation Rubrics and Quantitative tabs. Enter Benchmark, Validated value, Items checked, Valid items and Auditor remarks in the Cn Validation Rubrics tabs.
A4: Code | B4: Metric | C4: How to measure | D4: Unit | E4: Max marks | F4: Benchmark | G4: Validated value | H4: Marks obtained | I4: Percentage | J4: Grade | K4: Y | L4: C | M4: W | N4: D | O4: Items checked | P4: Valid items | Q4: Sample validity % | R4: Auditor remarks
A5: C1 | B5: CRITERION 1 - OUTCOME-BASED CURRICULUM
A6: 1.1 | B6: Vision, Mission and PEOs | E6: #REF! | F6: #REF! | G6: #REF! | H6: =IF(COUNT(H7:H14)=0,"",SUM(H7:H14)) | I6: =IF(H6="","",ROUND(H6/E6*100,2)) | J6: =IF(I6="","",IF(I6>YT*100,"Y",IF(I6>=CT*100,"C",IF(I6>=WT*100,"W","D")))) | K6: =SUM(K7:K14) -> #VALUE! | L6: =SUM(L7:L14) -> #VALUE! | M6: =SUM(M7:M14) -> #VALUE! | N6: =SUM(N7:N14) -> #VALUE! | O6: =IF(COUNT(O7:O14)=0,"",SUM(O7:O14)) | P6: =IF(COUNT(P7:P14)=0,"",SUM(P7:P14)) | Q6: =IF(N(O6)=0,"",ROUND(N(P6)/O6*100,2))
A7: 1.1.a | B7: Approval of Vision & Mission (1.1.1) | C7: Approvals obtained (IQAC, DAB, GB) / Approvals required | D7: % | E7: #REF! | F7: #REF! | G7: #REF! | H7: =IF(OR(G7="",F7="",F7=0),"",ROUND(E7*MIN(G7/F7,1),2)) -> #VALUE! | I7: =IF(H7="","",ROUND(H7/E7*100,2)) -> #VALUE! | J7: =IF(I7="","",IF(I7>YT*100,"Y",IF(I7>=CT*100,"C",IF(I7>=WT*100,"W","D")))) -> #VALUE! | K7: =IF($J7="Y",1,"") -> #VALUE! | L7: =IF($J7="C",1,"") -> #VALUE! | M7: =IF($J7="W",1,"") -> #VALUE! | N7: =IF($J7="D",1,"") -> #VALUE! | O7: =IF('C1 Validation Rubrics'!M9="","",'C1 Validation Rubrics'!M9) | P7: =IF('C1 Validation Rubrics'!N9="","",'C1 Validation Rubrics'!N9) | Q7: =IF(N(O7)=0,"",ROUND(N(P7)/O7*100,2)) | R7: =IF('C1 Validation Rubrics'!O9="","",'C1 Validation Rubrics'!O9)
A8: 1.1.b | B8: Quality of PEOs (1.1.2) | C8: PEOs meeting criteria (specific, measurable, 3-5 yrs after graduation) / PEOs defined | D8: % | E8: #REF! | F8: #REF! | G8: #REF! | H8: =IF(OR(G8="",F8="",F8=0),"",ROUND(E8*MIN(G8/F8,1),2)) -> #VALUE! | I8: =IF(H8="","",ROUND(H8/E8*100,2)) -> #VALUE! | J8: =IF(I8="","",IF(I8>YT*100,"Y",IF(I8>=CT*100,"C",IF(I8>=WT*100,"W","D")))) -> #VALUE! | K8: =IF($J8="Y",1,"") -> #VALUE! | L8: =IF($J8="C",1,"") -> #VALUE! | M8: =IF($J8="W",1,"") -> #VALUE! | N8: =IF($J8="D",1,"") -> #VALUE! | O8: =IF('C1 Validation Rubrics'!M10="","",'C1 Validation Rubrics'!M10) | P8: =IF('C1 Validation Rubrics'!N10="","",'C1 Validation Rubrics'!N10) | Q8: =IF(N(O8)=0,"",ROUND(N(P8)/O8*100,2)) | R8: =IF('C1 Validation Rubrics'!O10="","",'C1 Validation Rubrics'!O10)
A9: 1.1.c | B9: Stakeholder categories consulted (1.1.3) | C9: Categories consulted (students, alumni, employers, parents, faculty, industry) / 6 | D9: % | E9: #REF! | F9: #REF! | G9: #REF! | H9: =IF(OR(G9="",F9="",F9=0),"",ROUND(E9*MIN(G9/F9,1),2)) -> #VALUE! | I9: =IF(H9="","",ROUND(H9/E9*100,2)) -> #VALUE! | J9: =IF(I9="","",IF(I9>YT*100,"Y",IF(I9>=CT*100,"C",IF(I9>=WT*100,"W","D")))) -> #VALUE! | K9: =IF($J9="Y",1,"") -> #VALUE! | L9: =IF($J9="C",1,"") -> #VALUE! | M9: =IF($J9="W",1,"") -> #VALUE! | N9: =IF($J9="D",1,"") -> #VALUE! | O9: =IF('C1 Validation Rubrics'!M11="","",'C1 Validation Rubrics'!M11) | P9: =IF('C1 Validation Rubrics'!N11="","",'C1 Validation Rubrics'!N11) | Q9: =IF(N(O9)=0,"",ROUND(N(P9)/O9*100,2)) | R9: =IF('C1 Validation Rubrics'!O11="","",'C1 Validation Rubrics'!O11)
A10: 1.1.d | B10: Stakeholder survey responses (1.1.3) | C10: Survey responses received / Target responses | D10: % | E10: #REF! | F10: #REF! | G10: #REF! | H10: =IF(OR(G10="",F10="",F10=0),"",ROUND(E10*MIN(G10/F10,1),2)) -> #VALUE! | I10: =IF(H10="","",ROUND(H10/E10*100,2)) -> #VALUE! | J10: =IF(I10="","",IF(I10>YT*100,"Y",IF(I10>=CT*100,"C",IF(I10>=WT*100,"W","D")))) -> #VALUE! | K10: =IF($J10="Y",1,"") -> #VALUE! | L10: =IF($J10="C",1,"") -> #VALUE! | M10: =IF($J10="W",1,"") -> #VALUE! | N10: =IF($J10="D",1,"") -> #VALUE! | O10: =IF('C1 Validation Rubrics'!M12="","",'C1 Validation Rubrics'!M12) | P10: =IF('C1 Validation Rubrics'!N12="","",'C1 Validation Rubrics'!N12) | Q10: =IF(N(O10)=0,"",ROUND(N(P10)/O10*100,2)) | R10: =IF('C1 Validation Rubrics'!O12="","",'C1 Validation Rubrics'!O12)
A11: 1.1.e | B11: Dissemination points (1.1.4) | C11: Places displayed (website, dept, labs, classrooms, course files, handbook) / Required places | D11: % | E11: #REF! | F11: #REF! | G11: #REF! | H11: =IF(OR(G11="",F11="",F11=0),"",ROUND(E11*MIN(G11/F11,1),2)) -> #VALUE! | I11: =IF(H11="","",ROUND(H11/E11*100,2)) -> #VALUE! | J11: =IF(I11="","",IF(I11>YT*100,"Y",IF(I11>=CT*100,"C",IF(I11>=WT*100,"W","D")))) -> #VALUE! | K11: =IF($J11="Y",1,"") -> #VALUE! | L11: =IF($J11="C",1,"") -> #VALUE! | M11: =IF($J11="W",1,"") -> #VALUE! | N11: =IF($J11="D",1,"") -> #VALUE! | O11: =IF('C1 Validation Rubrics'!M13="","",'C1 Validation Rubrics'!M13) | P11: =IF('C1 Validation Rubrics'!N13="","",'C1 Validation Rubrics'!N13) | Q11: =IF(N(O11)=0,"",ROUND(N(P11)/O11*100,2)) | R11: =IF('C1 Validation Rubrics'!O13="","",'C1 Validation Rubrics'!O13)
A12: 1.1.f | B12: Stakeholder awareness (1.1.4) | C12: Sampled students able to state V/M/PEOs / Students sampled | D12: % | E12: #REF! | F12: #REF! | G12: #REF! | H12: =IF(OR(G12="",F12="",F12=0),"",ROUND(E12*MIN(G12/F12,1),2)) -> #VALUE! | I12: =IF(H12="","",ROUND(H12/E12*100,2)) -> #VALUE! | J12: =IF(I12="","",IF(I12>YT*100,"Y",IF(I12>=CT*100,"C",IF(I12>=WT*100,"W","D")))) -> #VALUE! | K12: =IF($J12="Y",1,"") -> #VALUE! | L12: =IF($J12="C",1,"") -> #VALUE! | M12: =IF($J12="W",1,"") -> #VALUE! | N12: =IF($J12="D",1,"") -> #VALUE! | O12: =IF('C1 Validation Rubrics'!M14="","",'C1 Validation Rubrics'!M14) | P12: =IF('C1 Validation Rubrics'!N14="","",'C1 Validation Rubrics'!N14) | Q12: =IF(N(O12)=0,"",ROUND(N(P12)/O12*100,2)) | R12: =IF('C1 Validation Rubrics'!O14="","",'C1 Validation Rubrics'!O14)
A13: 1.1.g | B13: PEO-Mission mapping completeness (1.1.5) | C13: Mapping cells filled with justification / Total mapping cells | D13: % | E13: #REF! | F13: #REF! | G13: #REF! | H13: =IF(OR(G13="",F13="",F13=0),"",ROUND(E13*MIN(G13/F13,1),2)) -> #VALUE! | I13: =IF(H13="","",ROUND(H13/E13*100,2)) -> #VALUE! | J13: =IF(I13="","",IF(I13>YT*100,"Y",IF(I13>=CT*100,"C",IF(I13>=WT*100,"W","D")))) -> #VALUE! | K13: =IF($J13="Y",1,"") -> #VALUE! | L13: =IF($J13="C",1,"") -> #VALUE! | M13: =IF($J13="W",1,"") -> #VALUE! | N13: =IF($J13="D",1,"") -> #VALUE! | O13: =IF('C1 Validation Rubrics'!M15="","",'C1 Validation Rubrics'!M15) | P13: =IF('C1 Validation Rubrics'!N15="","",'C1 Validation Rubrics'!N15) | Q13: =IF(N(O13)=0,"",ROUND(N(P13)/O13*100,2)) | R13: =IF('C1 Validation Rubrics'!O15="","",'C1 Validation Rubrics'!O15)
A14: 1.1.h | B14: PEO-Mission correlation strength (1.1.5) | C14: PEOs with strong (3) correlation to at least one mission element / PEOs defined | D14: % | E14: #REF! | F14: #REF! | G14: #REF! | H14: =IF(OR(G14="",F14="",F14=0),"",ROUND(E14*MIN(G14/F14,1),2)) -> #VALUE! | I14: =IF(H14="","",ROUND(H14/E14*100,2)) -> #VALUE! | J14: =IF(I14="","",IF(I14>YT*100,"Y",IF(I14>=CT*100,"C",IF(I14>=WT*100,"W","D")))) -> #VALUE! | K14: =IF($J14="Y",1,"") -> #VALUE! | L14: =IF($J14="C",1,"") -> #VALUE! | M14: =IF($J14="W",1,"") -> #VALUE! | N14: =IF($J14="D",1,"") -> #VALUE! | O14: =IF('C1 Validation Rubrics'!M16="","",'C1 Validation Rubrics'!M16) | P14: =IF('C1 Validation Rubrics'!N16="","",'C1 Validation Rubrics'!N16) | Q14: =IF(N(O14)=0,"",ROUND(N(P14)/O14*100,2)) | R14: =IF('C1 Validation Rubrics'!O16="","",'C1 Validation Rubrics'!O16)
A15: 1.2 | B15: Curriculum structure and features | E15: #REF! | F15: #REF! | G15: #REF! | H15: =IF(COUNT(H16:H22)=0,"",SUM(H16:H22)) | I15: =IF(H15="","",ROUND(H15/E15*100,2)) | J15: =IF(I15="","",IF(I15>YT*100,"Y",IF(I15>=CT*100,"C",IF(I15>=WT*100,"W","D")))) | K15: =SUM(K16:K22) -> #VALUE! | L15: =SUM(L16:L22) -> #VALUE! | M15: =SUM(M16:M22) -> #VALUE! | N15: =SUM(N16:N22) -> #VALUE! | O15: =IF(COUNT(O16:O22)=0,"",SUM(O16:O22)) | P15: =IF(COUNT(P16:P22)=0,"",SUM(P16:P22)) | Q15: =IF(N(O15)=0,"",ROUND(N(P15)/O15*100,2))
A16: 1.2.a | B16: Curriculum feedback collected and analysed (1.2.1) | C16: Stakeholder categories with feedback analysed / 4 (students, alumni, employers, faculty) | D16: % | E16: #REF! | F16: #REF! | G16: #REF! | H16: =IF(OR(G16="",F16="",F16=0),"",ROUND(E16*MIN(G16/F16,1),2)) -> #VALUE! | I16: =IF(H16="","",ROUND(H16/E16*100,2)) -> #VALUE! | J16: =IF(I16="","",IF(I16>YT*100,"Y",IF(I16>=CT*100,"C",IF(I16>=WT*100,"W","D")))) -> #VALUE! | K16: =IF($J16="Y",1,"") -> #VALUE! | L16: =IF($J16="C",1,"") -> #VALUE! | M16: =IF($J16="W",1,"") -> #VALUE! | N16: =IF($J16="D",1,"") -> #VALUE! | O16: =IF('C1 Validation Rubrics'!M18="","",'C1 Validation Rubrics'!M18) | P16: =IF('C1 Validation Rubrics'!N18="","",'C1 Validation Rubrics'!N18) | Q16: =IF(N(O16)=0,"",ROUND(N(P16)/O16*100,2)) | R16: =IF('C1 Validation Rubrics'!O18="","",'C1 Validation Rubrics'!O18)
A17: 1.2.b | B17: Curriculum gaps addressed (1.2.1) | C17: Gaps closed through BoS revision or content beyond syllabus / Gaps identified | D17: % | E17: #REF! | F17: #REF! | G17: #REF! | H17: =IF(OR(G17="",F17="",F17=0),"",ROUND(E17*MIN(G17/F17,1),2)) -> #VALUE! | I17: =IF(H17="","",ROUND(H17/E17*100,2)) -> #VALUE! | J17: =IF(I17="","",IF(I17>YT*100,"Y",IF(I17>=CT*100,"C",IF(I17>=WT*100,"W","D")))) -> #VALUE! | K17: =IF($J17="Y",1,"") -> #VALUE! | L17: =IF($J17="C",1,"") -> #VALUE! | M17: =IF($J17="W",1,"") -> #VALUE! | N17: =IF($J17="D",1,"") -> #VALUE! | O17: =IF('C1 Validation Rubrics'!M19="","",'C1 Validation Rubrics'!M19) | P17: =IF('C1 Validation Rubrics'!N19="","",'C1 Validation Rubrics'!N19) | Q17: =IF(N(O17)=0,"",ROUND(N(P17)/O17*100,2)) | R17: =IF('C1 Validation Rubrics'!O19="","",'C1 Validation Rubrics'!O19)
A18: 1.2.c | B18: Complete syllabi (1.2.2) | C18: Courses with complete syllabus (COs, content, hours, references) / Courses in curriculum | D18: % | E18: #REF! | F18: #REF! | G18: #REF! | H18: =IF(OR(G18="",F18="",F18=0),"",ROUND(E18*MIN(G18/F18,1),2)) -> #VALUE! | I18: =IF(H18="","",ROUND(H18/E18*100,2)) -> #VALUE! | J18: =IF(I18="","",IF(I18>YT*100,"Y",IF(I18>=CT*100,"C",IF(I18>=WT*100,"W","D")))) -> #VALUE! | K18: =IF($J18="Y",1,"") -> #VALUE! | L18: =IF($J18="C",1,"") -> #VALUE! | M18: =IF($J18="W",1,"") -> #VALUE! | N18: =IF($J18="D",1,"") -> #VALUE! | O18: =IF('C1 Validation Rubrics'!M20="","",'C1 Validation Rubrics'!M20) | P18: =IF('C1 Validation Rubrics'!N20="","",'C1 Validation Rubrics'!N20) | Q18: =IF(N(O18)=0,"",ROUND(N(P18)/O18*100,2)) | R18: =IF('C1 Validation Rubrics'!O20="","",'C1 Validation Rubrics'!O20)
A19: 1.2.d | B19: Credit compliance (1.2.2) | C19: Semesters with credits within university/AICTE norms / Total semesters | D19: % | E19: #REF! | F19: #REF! | G19: #REF! | H19: =IF(OR(G19="",F19="",F19=0),"",ROUND(E19*MIN(G19/F19,1),2)) -> #VALUE! | I19: =IF(H19="","",ROUND(H19/E19*100,2)) -> #VALUE! | J19: =IF(I19="","",IF(I19>YT*100,"Y",IF(I19>=CT*100,"C",IF(I19>=WT*100,"W","D")))) -> #VALUE! | K19: =IF($J19="Y",1,"") -> #VALUE! | L19: =IF($J19="C",1,"") -> #VALUE! | M19: =IF($J19="W",1,"") -> #VALUE! | N19: =IF($J19="D",1,"") -> #VALUE! | O19: =IF('C1 Validation Rubrics'!M21="","",'C1 Validation Rubrics'!M21) | P19: =IF('C1 Validation Rubrics'!N21="","",'C1 Validation Rubrics'!N21) | Q19: =IF(N(O19)=0,"",ROUND(N(P19)/O19*100,2)) | R19: =IF('C1 Validation Rubrics'!O21="","",'C1 Validation Rubrics'!O21)
A20: 1.2.e | B20: Curriculum components within AICTE range (1.2.3) | C20: Categories within range (BS, ES, HSS, PC, PE, OE, Project) / 7 | D20: % | E20: #REF! | F20: #REF! | G20: #REF! | H20: =IF(OR(G20="",F20="",F20=0),"",ROUND(E20*MIN(G20/F20,1),2)) -> #VALUE! | I20: =IF(H20="","",ROUND(H20/E20*100,2)) -> #VALUE! | J20: =IF(I20="","",IF(I20>YT*100,"Y",IF(I20>=CT*100,"C",IF(I20>=WT*100,"W","D")))) -> #VALUE! | K20: =IF($J20="Y",1,"") -> #VALUE! | L20: =IF($J20="C",1,"") -> #VALUE! | M20: =IF($J20="W",1,"") -> #VALUE! | N20: =IF($J20="D",1,"") -> #VALUE! | O20: =IF('C1 Validation Rubrics'!M22="","",'C1 Validation Rubrics'!M22) | P20: =IF('C1 Validation Rubrics'!N22="","",'C1 Validation Rubrics'!N22) | Q20: =IF(N(O20)=0,"",ROUND(N(P20)/O20*100,2)) | R20: =IF('C1 Validation Rubrics'!O22="","",'C1 Validation Rubrics'!O22)
A21: 1.2.f | B21: Interdisciplinary / honours / minor options (1.2.4) | C21: Number of options offered | D21: No. | E21: #REF! | F21: #REF! | G21: #REF! | H21: =IF(OR(G21="",F21="",F21=0),"",ROUND(E21*MIN(G21/F21,1),2)) -> #VALUE! | I21: =IF(H21="","",ROUND(H21/E21*100,2)) -> #VALUE! | J21: =IF(I21="","",IF(I21>YT*100,"Y",IF(I21>=CT*100,"C",IF(I21>=WT*100,"W","D")))) -> #VALUE! | K21: =IF($J21="Y",1,"") -> #VALUE! | L21: =IF($J21="C",1,"") -> #VALUE! | M21: =IF($J21="W",1,"") -> #VALUE! | N21: =IF($J21="D",1,"") -> #VALUE! | O21: =IF('C1 Validation Rubrics'!M23="","",'C1 Validation Rubrics'!M23) | P21: =IF('C1 Validation Rubrics'!N23="","",'C1 Validation Rubrics'!N23) | Q21: =IF(N(O21)=0,"",ROUND(N(P21)/O21*100,2)) | R21: =IF('C1 Validation Rubrics'!O23="","",'C1 Validation Rubrics'!O23)
A22: 1.2.g | B22: Academic Bank of Credits registration (1.2.4) | C22: Students with ABC ID / Students on roll | D22: % | E22: #REF! | F22: #REF! | G22: #REF! | H22: =IF(OR(G22="",F22="",F22=0),"",ROUND(E22*MIN(G22/F22,1),2)) -> #VALUE! | I22: =IF(H22="","",ROUND(H22/E22*100,2)) -> #VALUE! | J22: =IF(I22="","",IF(I22>YT*100,"Y",IF(I22>=CT*100,"C",IF(I22>=WT*100,"W","D")))) -> #VALUE! | K22: =IF($J22="Y",1,"") -> #VALUE! | L22: =IF($J22="C",1,"") -> #VALUE! | M22: =IF($J22="W",1,"") -> #VALUE! | N22: =IF($J22="D",1,"") -> #VALUE! | O22: =IF('C1 Validation Rubrics'!M24="","",'C1 Validation Rubrics'!M24) | P22: =IF('C1 Validation Rubrics'!N24="","",'C1 Validation Rubrics'!N24) | Q22: =IF(N(O22)=0,"",ROUND(N(P22)/O22*100,2)) | R22: =IF('C1 Validation Rubrics'!O24="","",'C1 Validation Rubrics'!O24)
A23: 1.3 | B23: Mapping of POs and PSOs | E23: #REF! | F23: #REF! | G23: #REF! | H23: =IF(COUNT(H24:H26)=0,"",SUM(H24:H26)) | I23: =IF(H23="","",ROUND(H23/E23*100,2)) | J23: =IF(I23="","",IF(I23>YT*100,"Y",IF(I23>=CT*100,"C",IF(I23>=WT*100,"W","D")))) | K23: =SUM(K24:K26) -> #VALUE! | L23: =SUM(L24:L26) -> #VALUE! | M23: =SUM(M24:M26) -> #VALUE! | N23: =SUM(N24:N26) -> #VALUE! | O23: =IF(COUNT(O24:O26)=0,"",SUM(O24:O26)) | P23: =IF(COUNT(P24:P26)=0,"",SUM(P24:P26)) | Q23: =IF(N(O23)=0,"",ROUND(N(P23)/O23*100,2))
A24: 1.3.a | B24: PSOs defined and approved (1.3.1) | C24: PSOs approved by BoS/DAB / PSOs defined | D24: % | E24: #REF! | F24: #REF! | G24: #REF! | H24: =IF(OR(G24="",F24="",F24=0),"",ROUND(E24*MIN(G24/F24,1),2)) -> #VALUE! | I24: =IF(H24="","",ROUND(H24/E24*100,2)) -> #VALUE! | J24: =IF(I24="","",IF(I24>YT*100,"Y",IF(I24>=CT*100,"C",IF(I24>=WT*100,"W","D")))) -> #VALUE! | K24: =IF($J24="Y",1,"") -> #VALUE! | L24: =IF($J24="C",1,"") -> #VALUE! | M24: =IF($J24="W",1,"") -> #VALUE! | N24: =IF($J24="D",1,"") -> #VALUE! | O24: =IF('C1 Validation Rubrics'!M26="","",'C1 Validation Rubrics'!M26) | P24: =IF('C1 Validation Rubrics'!N26="","",'C1 Validation Rubrics'!N26) | Q24: =IF(N(O24)=0,"",ROUND(N(P24)/O24*100,2)) | R24: =IF('C1 Validation Rubrics'!O26="","",'C1 Validation Rubrics'!O26)
A25: 1.3.b | B25: Courses mapped to POs/PSOs (1.3.2) | C25: Courses with PO/PSO mapping / Courses in curriculum | D25: % | E25: #REF! | F25: #REF! | G25: #REF! | H25: =IF(OR(G25="",F25="",F25=0),"",ROUND(E25*MIN(G25/F25,1),2)) -> #VALUE! | I25: =IF(H25="","",ROUND(H25/E25*100,2)) -> #VALUE! | J25: =IF(I25="","",IF(I25>YT*100,"Y",IF(I25>=CT*100,"C",IF(I25>=WT*100,"W","D")))) -> #VALUE! | K25: =IF($J25="Y",1,"") -> #VALUE! | L25: =IF($J25="C",1,"") -> #VALUE! | M25: =IF($J25="W",1,"") -> #VALUE! | N25: =IF($J25="D",1,"") -> #VALUE! | O25: =IF('C1 Validation Rubrics'!M27="","",'C1 Validation Rubrics'!M27) | P25: =IF('C1 Validation Rubrics'!N27="","",'C1 Validation Rubrics'!N27) | Q25: =IF(N(O25)=0,"",ROUND(N(P25)/O25*100,2)) | R25: =IF('C1 Validation Rubrics'!O27="","",'C1 Validation Rubrics'!O27)
A26: 1.3.c | B26: Justified mappings (1.3.2) | C26: Mapped courses with written justification / Mapped courses | D26: % | E26: #REF! | F26: #REF! | G26: #REF! | H26: =IF(OR(G26="",F26="",F26=0),"",ROUND(E26*MIN(G26/F26,1),2)) -> #VALUE! | I26: =IF(H26="","",ROUND(H26/E26*100,2)) -> #VALUE! | J26: =IF(I26="","",IF(I26>YT*100,"Y",IF(I26>=CT*100,"C",IF(I26>=WT*100,"W","D")))) -> #VALUE! | K26: =IF($J26="Y",1,"") -> #VALUE! | L26: =IF($J26="C",1,"") -> #VALUE! | M26: =IF($J26="W",1,"") -> #VALUE! | N26: =IF($J26="D",1,"") -> #VALUE! | O26: =IF('C1 Validation Rubrics'!M28="","",'C1 Validation Rubrics'!M28) | P26: =IF('C1 Validation Rubrics'!N28="","",'C1 Validation Rubrics'!N28) | Q26: =IF(N(O26)=0,"",ROUND(N(P26)/O26*100,2)) | R26: =IF('C1 Validation Rubrics'!O28="","",'C1 Validation Rubrics'!O28)
A27: 1.4 | B27: Course Outcomes and Course Articulation Matrix | E27: #REF! | F27: #REF! | G27: #REF! | H27: =IF(COUNT(H28:H32)=0,"",SUM(H28:H32)) | I27: =IF(H27="","",ROUND(H27/E27*100,2)) | J27: =IF(I27="","",IF(I27>YT*100,"Y",IF(I27>=CT*100,"C",IF(I27>=WT*100,"W","D")))) | K27: =SUM(K28:K32) -> #VALUE! | L27: =SUM(L28:L32) -> #VALUE! | M27: =SUM(M28:M32) -> #VALUE! | N27: =SUM(N28:N32) -> #VALUE! | O27: =IF(COUNT(O28:O32)=0,"",SUM(O28:O32)) | P27: =IF(COUNT(P28:P32)=0,"",SUM(P28:P32)) | Q27: =IF(N(O27)=0,"",ROUND(N(P27)/O27*100,2))
A28: 1.4.a | B28: Courses with COs defined (1.4.1) | C28: Courses with COs / Courses offered | D28: % | E28: #REF! | F28: #REF! | G28: #REF! | H28: =IF(OR(G28="",F28="",F28=0),"",ROUND(E28*MIN(G28/F28,1),2)) -> #VALUE! | I28: =IF(H28="","",ROUND(H28/E28*100,2)) -> #VALUE! | J28: =IF(I28="","",IF(I28>YT*100,"Y",IF(I28>=CT*100,"C",IF(I28>=WT*100,"W","D")))) -> #VALUE! | K28: =IF($J28="Y",1,"") -> #VALUE! | L28: =IF($J28="C",1,"") -> #VALUE! | M28: =IF($J28="W",1,"") -> #VALUE! | N28: =IF($J28="D",1,"") -> #VALUE! | O28: =IF('C1 Validation Rubrics'!M30="","",'C1 Validation Rubrics'!M30) | P28: =IF('C1 Validation Rubrics'!N30="","",'C1 Validation Rubrics'!N30) | Q28: =IF(N(O28)=0,"",ROUND(N(P28)/O28*100,2)) | R28: =IF('C1 Validation Rubrics'!O30="","",'C1 Validation Rubrics'!O30)
A29: 1.4.b | B29: Measurable COs (1.4.1) | C29: COs with action verb and Bloom's level / Total COs | D29: % | E29: #REF! | F29: #REF! | G29: #REF! | H29: =IF(OR(G29="",F29="",F29=0),"",ROUND(E29*MIN(G29/F29,1),2)) -> #VALUE! | I29: =IF(H29="","",ROUND(H29/E29*100,2)) -> #VALUE! | J29: =IF(I29="","",IF(I29>YT*100,"Y",IF(I29>=CT*100,"C",IF(I29>=WT*100,"W","D")))) -> #VALUE! | K29: =IF($J29="Y",1,"") -> #VALUE! | L29: =IF($J29="C",1,"") -> #VALUE! | M29: =IF($J29="W",1,"") -> #VALUE! | N29: =IF($J29="D",1,"") -> #VALUE! | O29: =IF('C1 Validation Rubrics'!M31="","",'C1 Validation Rubrics'!M31) | P29: =IF('C1 Validation Rubrics'!N31="","",'C1 Validation Rubrics'!N31) | Q29: =IF(N(O29)=0,"",ROUND(N(P29)/O29*100,2)) | R29: =IF('C1 Validation Rubrics'!O31="","",'C1 Validation Rubrics'!O31)
A30: 1.4.c | B30: Higher-order COs (1.4.1) | C30: Courses with at least one CO at Apply level or above / Courses offered | D30: % | E30: #REF! | F30: #REF! | G30: #REF! | H30: =IF(OR(G30="",F30="",F30=0),"",ROUND(E30*MIN(G30/F30,1),2)) -> #VALUE! | I30: =IF(H30="","",ROUND(H30/E30*100,2)) -> #VALUE! | J30: =IF(I30="","",IF(I30>YT*100,"Y",IF(I30>=CT*100,"C",IF(I30>=WT*100,"W","D")))) -> #VALUE! | K30: =IF($J30="Y",1,"") -> #VALUE! | L30: =IF($J30="C",1,"") -> #VALUE! | M30: =IF($J30="W",1,"") -> #VALUE! | N30: =IF($J30="D",1,"") -> #VALUE! | O30: =IF('C1 Validation Rubrics'!M32="","",'C1 Validation Rubrics'!M32) | P30: =IF('C1 Validation Rubrics'!N32="","",'C1 Validation Rubrics'!N32) | Q30: =IF(N(O30)=0,"",ROUND(N(P30)/O30*100,2)) | R30: =IF('C1 Validation Rubrics'!O32="","",'C1 Validation Rubrics'!O32)
A31: 1.4.d | B31: Course Articulation Matrix prepared (1.4.2) | C31: Courses with CAM / Courses offered | D31: % | E31: #REF! | F31: #REF! | G31: #REF! | H31: =IF(OR(G31="",F31="",F31=0),"",ROUND(E31*MIN(G31/F31,1),2)) -> #VALUE! | I31: =IF(H31="","",ROUND(H31/E31*100,2)) -> #VALUE! | J31: =IF(I31="","",IF(I31>YT*100,"Y",IF(I31>=CT*100,"C",IF(I31>=WT*100,"W","D")))) -> #VALUE! | K31: =IF($J31="Y",1,"") -> #VALUE! | L31: =IF($J31="C",1,"") -> #VALUE! | M31: =IF($J31="W",1,"") -> #VALUE! | N31: =IF($J31="D",1,"") -> #VALUE! | O31: =IF('C1 Validation Rubrics'!M33="","",'C1 Validation Rubrics'!M33) | P31: =IF('C1 Validation Rubrics'!N33="","",'C1 Validation Rubrics'!N33) | Q31: =IF(N(O31)=0,"",ROUND(N(P31)/O31*100,2)) | R31: =IF('C1 Validation Rubrics'!O33="","",'C1 Validation Rubrics'!O33)
A32: 1.4.e | B32: CAM correlations justified (1.4.2) | C32: CAMs with justification for each correlation / CAMs prepared | D32: % | E32: #REF! | F32: #REF! | G32: #REF! | H32: =IF(OR(G32="",F32="",F32=0),"",ROUND(E32*MIN(G32/F32,1),2)) -> #VALUE! | I32: =IF(H32="","",ROUND(H32/E32*100,2)) -> #VALUE! | J32: =IF(I32="","",IF(I32>YT*100,"Y",IF(I32>=CT*100,"C",IF(I32>=WT*100,"W","D")))) -> #VALUE! | K32: =IF($J32="Y",1,"") -> #VALUE! | L32: =IF($J32="C",1,"") -> #VALUE! | M32: =IF($J32="W",1,"") -> #VALUE! | N32: =IF($J32="D",1,"") -> #VALUE! | O32: =IF('C1 Validation Rubrics'!M34="","",'C1 Validation Rubrics'!M34) | P32: =IF('C1 Validation Rubrics'!N34="","",'C1 Validation Rubrics'!N34) | Q32: =IF(N(O32)=0,"",ROUND(N(P32)/O32*100,2)) | R32: =IF('C1 Validation Rubrics'!O34="","",'C1 Validation Rubrics'!O34)
A33: 1.5 | B33: Programme Articulation Matrix | E33: #REF! | F33: #REF! | G33: #REF! | H33: =IF(COUNT(H34:H35)=0,"",SUM(H34:H35)) | I33: =IF(H33="","",ROUND(H33/E33*100,2)) | J33: =IF(I33="","",IF(I33>YT*100,"Y",IF(I33>=CT*100,"C",IF(I33>=WT*100,"W","D")))) | K33: =SUM(K34:K35) -> #VALUE! | L33: =SUM(L34:L35) -> #VALUE! | M33: =SUM(M34:M35) -> #VALUE! | N33: =SUM(N34:N35) -> #VALUE! | O33: =IF(COUNT(O34:O35)=0,"",SUM(O34:O35)) | P33: =IF(COUNT(P34:P35)=0,"",SUM(P34:P35)) | Q33: =IF(N(O33)=0,"",ROUND(N(P33)/O33*100,2))
A34: 1.5.a | B34: PAM derived from CAMs | C34: POs/PSOs with PAM value computed from CAMs / Total POs + PSOs | D34: % | E34: #REF! | F34: #REF! | G34: #REF! | H34: =IF(OR(G34="",F34="",F34=0),"",ROUND(E34*MIN(G34/F34,1),2)) -> #VALUE! | I34: =IF(H34="","",ROUND(H34/E34*100,2)) -> #VALUE! | J34: =IF(I34="","",IF(I34>YT*100,"Y",IF(I34>=CT*100,"C",IF(I34>=WT*100,"W","D")))) -> #VALUE! | K34: =IF($J34="Y",1,"") -> #VALUE! | L34: =IF($J34="C",1,"") -> #VALUE! | M34: =IF($J34="W",1,"") -> #VALUE! | N34: =IF($J34="D",1,"") -> #VALUE! | O34: =IF('C1 Validation Rubrics'!M36="","",'C1 Validation Rubrics'!M36) | P34: =IF('C1 Validation Rubrics'!N36="","",'C1 Validation Rubrics'!N36) | Q34: =IF(N(O34)=0,"",ROUND(N(P34)/O34*100,2)) | R34: =IF('C1 Validation Rubrics'!O36="","",'C1 Validation Rubrics'!O36)
A35: 1.5.b | B35: PO/PSO coverage | C35: POs/PSOs addressed by at least N courses / Total POs + PSOs | D35: % | E35: #REF! | F35: #REF! | G35: #REF! | H35: =IF(OR(G35="",F35="",F35=0),"",ROUND(E35*MIN(G35/F35,1),2)) -> #VALUE! | I35: =IF(H35="","",ROUND(H35/E35*100,2)) -> #VALUE! | J35: =IF(I35="","",IF(I35>YT*100,"Y",IF(I35>=CT*100,"C",IF(I35>=WT*100,"W","D")))) -> #VALUE! | K35: =IF($J35="Y",1,"") -> #VALUE! | L35: =IF($J35="C",1,"") -> #VALUE! | M35: =IF($J35="W",1,"") -> #VALUE! | N35: =IF($J35="D",1,"") -> #VALUE! | O35: =IF('C1 Validation Rubrics'!M37="","",'C1 Validation Rubrics'!M37) | P35: =IF('C1 Validation Rubrics'!N37="","",'C1 Validation Rubrics'!N37) | Q35: =IF(N(O35)=0,"",ROUND(N(P35)/O35*100,2)) | R35: =IF('C1 Validation Rubrics'!O37="","",'C1 Validation Rubrics'!O37)
A36: C1 | B36: CRITERION 1 TOTAL | E36: #REF! | F36: #REF! | G36: #REF! | H36: =IF(COUNT(H6,H15,H23,H27,H33)=0,"",N(H6)+N(H15)+N(H23)+N(H27)+N(H33)) | I36: =IF(H36="","",ROUND(H36/E36*100,2)) | J36: =IF(I36="","",IF(I36>YT*100,"Y",IF(I36>=CT*100,"C",IF(I36>=WT*100,"W","D")))) | K36: =N(K6)+N(K15)+N(K23)+N(K27)+N(K33) -> #VALUE! | L36: =N(L6)+N(L15)+N(L23)+N(L27)+N(L33) -> #VALUE! | M36: =N(M6)+N(M15)+N(M23)+N(M27)+N(M33) -> #VALUE! | N36: =N(N6)+N(N15)+N(N23)+N(N27)+N(N33) -> #VALUE! | O36: =IF(COUNT(O6,O15,O23,O27,O33)=0,"",N(O6)+N(O15)+N(O23)+N(O27)+N(O33)) | P36: =IF(COUNT(P6,P15,P23,P27,P33)=0,"",N(P6)+N(P15)+N(P23)+N(P27)+N(P33)) | Q36: =IF(N(O36)=0,"",ROUND(N(P36)/O36*100,2))
A37: C2 | B37: CRITERION 2 - OUTCOME-BASED TEACHING LEARNING
A38: 2.1 | B38: Quality of teaching-learning processes | E38: #REF! | F38: =IF('C2 Validation Rubrics'!R8="","",'C2 Validation Rubrics'!R8) | G38: =IF('C2 Validation Rubrics'!S8="","",'C2 Validation Rubrics'!S8) | H38: =IF(COUNT(H39:H43)=0,"",SUM(H39:H43)) | I38: =IF(H38="","",ROUND(H38/E38*100,2)) | J38: =IF(I38="","",IF(I38>YT*100,"Y",IF(I38>=CT*100,"C",IF(I38>=WT*100,"W","D")))) | K38: =SUM(K39:K43) -> #VALUE! | L38: =SUM(L39:L43) -> #VALUE! | M38: =SUM(M39:M43) -> #VALUE! | N38: =SUM(N39:N43) -> #VALUE! | O38: =IF(COUNT(O39:O43)=0,"",SUM(O39:O43)) | P38: =IF(COUNT(P39:P43)=0,"",SUM(P39:P43)) | Q38: =IF(N(O38)=0,"",ROUND(N(P38)/O38*100,2))
A39: 2.1.a | B39: Course files complete before semester start | C39: Courses with lesson plan + COs + CAM uploaded / Courses offered | D39: % | E39: #REF! | F39: =IF('C2 Validation Rubrics'!R9="","",'C2 Validation Rubrics'!R9) -> 3 | G39: =IF('C2 Validation Rubrics'!S9="","",'C2 Validation Rubrics'!S9) -> 2 | H39: =IF(OR(G39="",F39="",F39=0),"",ROUND(E39*MIN(G39/F39,1),2)) -> #VALUE! | I39: =IF(H39="","",ROUND(H39/E39*100,2)) -> #VALUE! | J39: =IF(I39="","",IF(I39>YT*100,"Y",IF(I39>=CT*100,"C",IF(I39>=WT*100,"W","D")))) -> #VALUE! | K39: =IF($J39="Y",1,"") -> #VALUE! | L39: =IF($J39="C",1,"") -> #VALUE! | M39: =IF($J39="W",1,"") -> #VALUE! | N39: =IF($J39="D",1,"") -> #VALUE! | O39: =IF('C2 Validation Rubrics'!M9="","",'C2 Validation Rubrics'!M9) | P39: =IF('C2 Validation Rubrics'!N9="","",'C2 Validation Rubrics'!N9) | Q39: =IF(N(O39)=0,"",ROUND(N(P39)/O39*100,2)) | R39: =IF('C2 Validation Rubrics'!O9="","",'C2 Validation Rubrics'!O9)
A40: 2.1.b | B40: Syllabus coverage as per lesson plan | C40: Topics covered / Topics planned to audit date | D40: % | E40: #REF! | F40: =IF('C2 Validation Rubrics'!R10="","",'C2 Validation Rubrics'!R10) | G40: =IF('C2 Validation Rubrics'!S10="","",'C2 Validation Rubrics'!S10) | H40: =IF(OR(G40="",F40="",F40=0),"",ROUND(E40*MIN(G40/F40,1),2)) | I40: =IF(H40="","",ROUND(H40/E40*100,2)) | J40: =IF(I40="","",IF(I40>YT*100,"Y",IF(I40>=CT*100,"C",IF(I40>=WT*100,"W","D")))) | K40: =IF($J40="Y",1,"") | L40: =IF($J40="C",1,"") | M40: =IF($J40="W",1,"") | N40: =IF($J40="D",1,"") | O40: =IF('C2 Validation Rubrics'!M10="","",'C2 Validation Rubrics'!M10) | P40: =IF('C2 Validation Rubrics'!N10="","",'C2 Validation Rubrics'!N10) | Q40: =IF(N(O40)=0,"",ROUND(N(P40)/O40*100,2)) | R40: =IF('C2 Validation Rubrics'!O10="","",'C2 Validation Rubrics'!O10)
A41: 2.1.c | B41: Classes conducted vs scheduled | C41: Hours conducted / Hours timetabled | D41: % | E41: #REF! | F41: =IF('C2 Validation Rubrics'!R11="","",'C2 Validation Rubrics'!R11) | G41: =IF('C2 Validation Rubrics'!S11="","",'C2 Validation Rubrics'!S11) | H41: =IF(OR(G41="",F41="",F41=0),"",ROUND(E41*MIN(G41/F41,1),2)) | I41: =IF(H41="","",ROUND(H41/E41*100,2)) | J41: =IF(I41="","",IF(I41>YT*100,"Y",IF(I41>=CT*100,"C",IF(I41>=WT*100,"W","D")))) | K41: =IF($J41="Y",1,"") | L41: =IF($J41="C",1,"") | M41: =IF($J41="W",1,"") | N41: =IF($J41="D",1,"") | O41: =IF('C2 Validation Rubrics'!M11="","",'C2 Validation Rubrics'!M11) | P41: =IF('C2 Validation Rubrics'!N11="","",'C2 Validation Rubrics'!N11) | Q41: =IF(N(O41)=0,"",ROUND(N(P41)/O41*100,2)) | R41: =IF('C2 Validation Rubrics'!O11="","",'C2 Validation Rubrics'!O11)
A42: 2.1.d | B42: Courses using active learning / ICT | C42: Courses with documented active-learning or ICT sessions / Courses offered | D42: % | E42: #REF! | F42: =IF('C2 Validation Rubrics'!R12="","",'C2 Validation Rubrics'!R12) | G42: =IF('C2 Validation Rubrics'!S12="","",'C2 Validation Rubrics'!S12) | H42: =IF(OR(G42="",F42="",F42=0),"",ROUND(E42*MIN(G42/F42,1),2)) | I42: =IF(H42="","",ROUND(H42/E42*100,2)) | J42: =IF(I42="","",IF(I42>YT*100,"Y",IF(I42>=CT*100,"C",IF(I42>=WT*100,"W","D")))) | K42: =IF($J42="Y",1,"") | L42: =IF($J42="C",1,"") | M42: =IF($J42="W",1,"") | N42: =IF($J42="D",1,"") | O42: =IF('C2 Validation Rubrics'!M12="","",'C2 Validation Rubrics'!M12) | P42: =IF('C2 Validation Rubrics'!N12="","",'C2 Validation Rubrics'!N12) | Q42: =IF(N(O42)=0,"",ROUND(N(P42)/O42*100,2)) | R42: =IF('C2 Validation Rubrics'!O12="","",'C2 Validation Rubrics'!O12)
A43: 2.1.e | B43: Student feedback on teaching | C43: Dept average feedback score / Max of scale (e.g. 5) | D43: % | E43: #REF! | F43: =IF('C2 Validation Rubrics'!R13="","",'C2 Validation Rubrics'!R13) | G43: =IF('C2 Validation Rubrics'!S13="","",'C2 Validation Rubrics'!S13) | H43: =IF(OR(G43="",F43="",F43=0),"",ROUND(E43*MIN(G43/F43,1),2)) | I43: =IF(H43="","",ROUND(H43/E43*100,2)) | J43: =IF(I43="","",IF(I43>YT*100,"Y",IF(I43>=CT*100,"C",IF(I43>=WT*100,"W","D")))) | K43: =IF($J43="Y",1,"") | L43: =IF($J43="C",1,"") | M43: =IF($J43="W",1,"") | N43: =IF($J43="D",1,"") | O43: =IF('C2 Validation Rubrics'!M13="","",'C2 Validation Rubrics'!M13) | P43: =IF('C2 Validation Rubrics'!N13="","",'C2 Validation Rubrics'!N13) | Q43: =IF(N(O43)=0,"",ROUND(N(P43)/O43*100,2)) | R43: =IF('C2 Validation Rubrics'!O13="","",'C2 Validation Rubrics'!O13)
A44: 2.2 | B44: Quality of capstone project | E44: #REF! | F44: =IF('C2 Validation Rubrics'!R14="","",'C2 Validation Rubrics'!R14) | G44: =IF('C2 Validation Rubrics'!S14="","",'C2 Validation Rubrics'!S14) | H44: =IF(COUNT(H45:H49)=0,"",SUM(H45:H49)) | I44: =IF(H44="","",ROUND(H44/E44*100,2)) | J44: =IF(I44="","",IF(I44>YT*100,"Y",IF(I44>=CT*100,"C",IF(I44>=WT*100,"W","D")))) | K44: =SUM(K45:K49) -> 0 | L44: =SUM(L45:L49) -> 0 | M44: =SUM(M45:M49) -> 0 | N44: =SUM(N45:N49) -> 0 | O44: =IF(COUNT(O45:O49)=0,"",SUM(O45:O49)) | P44: =IF(COUNT(P45:P49)=0,"",SUM(P45:P49)) | Q44: =IF(N(O44)=0,"",ROUND(N(P44)/O44*100,2))
A45: 2.2.a | B45: Projects mapped to POs/PSOs | C45: Projects with PO/PSO mapping / Total projects | D45: % | E45: #REF! | F45: =IF('C2 Validation Rubrics'!R15="","",'C2 Validation Rubrics'!R15) | G45: =IF('C2 Validation Rubrics'!S15="","",'C2 Validation Rubrics'!S15) | H45: =IF(OR(G45="",F45="",F45=0),"",ROUND(E45*MIN(G45/F45,1),2)) | I45: =IF(H45="","",ROUND(H45/E45*100,2)) | J45: =IF(I45="","",IF(I45>YT*100,"Y",IF(I45>=CT*100,"C",IF(I45>=WT*100,"W","D")))) | K45: =IF($J45="Y",1,"") | L45: =IF($J45="C",1,"") | M45: =IF($J45="W",1,"") | N45: =IF($J45="D",1,"") | O45: =IF('C2 Validation Rubrics'!M15="","",'C2 Validation Rubrics'!M15) | P45: =IF('C2 Validation Rubrics'!N15="","",'C2 Validation Rubrics'!N15) | Q45: =IF(N(O45)=0,"",ROUND(N(P45)/O45*100,2)) | R45: =IF('C2 Validation Rubrics'!O15="","",'C2 Validation Rubrics'!O15)
A46: 2.2.b | B46: Industry / research-linked projects | C46: Industry-sponsored or research-linked projects / Total projects | D46: % | E46: #REF! | F46: =IF('C2 Validation Rubrics'!R16="","",'C2 Validation Rubrics'!R16) | G46: =IF('C2 Validation Rubrics'!S16="","",'C2 Validation Rubrics'!S16) | H46: =IF(OR(G46="",F46="",F46=0),"",ROUND(E46*MIN(G46/F46,1),2)) | I46: =IF(H46="","",ROUND(H46/E46*100,2)) | J46: =IF(I46="","",IF(I46>YT*100,"Y",IF(I46>=CT*100,"C",IF(I46>=WT*100,"W","D")))) | K46: =IF($J46="Y",1,"") | L46: =IF($J46="C",1,"") | M46: =IF($J46="W",1,"") | N46: =IF($J46="D",1,"") | O46: =IF('C2 Validation Rubrics'!M16="","",'C2 Validation Rubrics'!M16) | P46: =IF('C2 Validation Rubrics'!N16="","",'C2 Validation Rubrics'!N16) | Q46: =IF(N(O46)=0,"",ROUND(N(P46)/O46*100,2)) | R46: =IF('C2 Validation Rubrics'!O16="","",'C2 Validation Rubrics'!O16)
A47: 2.2.c | B47: Projects with tangible outcome | C47: Projects with paper, patent, prototype or award / Total projects | D47: % | E47: #REF! | F47: =IF('C2 Validation Rubrics'!R17="","",'C2 Validation Rubrics'!R17) | G47: =IF('C2 Validation Rubrics'!S17="","",'C2 Validation Rubrics'!S17) | H47: =IF(OR(G47="",F47="",F47=0),"",ROUND(E47*MIN(G47/F47,1),2)) | I47: =IF(H47="","",ROUND(H47/E47*100,2)) | J47: =IF(I47="","",IF(I47>YT*100,"Y",IF(I47>=CT*100,"C",IF(I47>=WT*100,"W","D")))) | K47: =IF($J47="Y",1,"") | L47: =IF($J47="C",1,"") | M47: =IF($J47="W",1,"") | N47: =IF($J47="D",1,"") | O47: =IF('C2 Validation Rubrics'!M17="","",'C2 Validation Rubrics'!M17) | P47: =IF('C2 Validation Rubrics'!N17="","",'C2 Validation Rubrics'!N17) | Q47: =IF(N(O47)=0,"",ROUND(N(P47)/O47*100,2)) | R47: =IF('C2 Validation Rubrics'!O17="","",'C2 Validation Rubrics'!O17)
A48: 2.2.d | B48: Rubric-based reviews on schedule | C48: Projects with >=3 rubric-scored reviews / Total projects | D48: % | E48: #REF! | F48: =IF('C2 Validation Rubrics'!R18="","",'C2 Validation Rubrics'!R18) | G48: =IF('C2 Validation Rubrics'!S18="","",'C2 Validation Rubrics'!S18) | H48: =IF(OR(G48="",F48="",F48=0),"",ROUND(E48*MIN(G48/F48,1),2)) | I48: =IF(H48="","",ROUND(H48/E48*100,2)) | J48: =IF(I48="","",IF(I48>YT*100,"Y",IF(I48>=CT*100,"C",IF(I48>=WT*100,"W","D")))) | K48: =IF($J48="Y",1,"") | L48: =IF($J48="C",1,"") | M48: =IF($J48="W",1,"") | N48: =IF($J48="D",1,"") | O48: =IF('C2 Validation Rubrics'!M18="","",'C2 Validation Rubrics'!M18) | P48: =IF('C2 Validation Rubrics'!N18="","",'C2 Validation Rubrics'!N18) | Q48: =IF(N(O48)=0,"",ROUND(N(P48)/O48*100,2)) | R48: =IF('C2 Validation Rubrics'!O18="","",'C2 Validation Rubrics'!O18)
A49: 2.2.e | B49: Interdisciplinary / SDG-linked projects | C49: Projects tagged interdisciplinary or to an SDG / Total projects | D49: % | E49: #REF! | F49: =IF('C2 Validation Rubrics'!R19="","",'C2 Validation Rubrics'!R19) | G49: =IF('C2 Validation Rubrics'!S19="","",'C2 Validation Rubrics'!S19) | H49: =IF(OR(G49="",F49="",F49=0),"",ROUND(E49*MIN(G49/F49,1),2)) | I49: =IF(H49="","",ROUND(H49/E49*100,2)) | J49: =IF(I49="","",IF(I49>YT*100,"Y",IF(I49>=CT*100,"C",IF(I49>=WT*100,"W","D")))) | K49: =IF($J49="Y",1,"") | L49: =IF($J49="C",1,"") | M49: =IF($J49="W",1,"") | N49: =IF($J49="D",1,"") | O49: =IF('C2 Validation Rubrics'!M19="","",'C2 Validation Rubrics'!M19) | P49: =IF('C2 Validation Rubrics'!N19="","",'C2 Validation Rubrics'!N19) | Q49: =IF(N(O49)=0,"",ROUND(N(P49)/O49*100,2)) | R49: =IF('C2 Validation Rubrics'!O19="","",'C2 Validation Rubrics'!O19)
A50: 2.3 | B50: Internship and industrial training | E50: #REF! | F50: =IF('C2 Validation Rubrics'!R20="","",'C2 Validation Rubrics'!R20) | G50: =IF('C2 Validation Rubrics'!S20="","",'C2 Validation Rubrics'!S20) | H50: =IF(COUNT(H51:H53)=0,"",SUM(H51:H53)) | I50: =IF(H50="","",ROUND(H50/E50*100,2)) | J50: =IF(I50="","",IF(I50>YT*100,"Y",IF(I50>=CT*100,"C",IF(I50>=WT*100,"W","D")))) | K50: =SUM(K51:K53) -> #VALUE! | L50: =SUM(L51:L53) -> #VALUE! | M50: =SUM(M51:M53) -> #VALUE! | N50: =SUM(N51:N53) -> #VALUE! | O50: =IF(COUNT(O51:O53)=0,"",SUM(O51:O53)) | P50: =IF(COUNT(P51:P53)=0,"",SUM(P51:P53)) | Q50: =IF(N(O50)=0,"",ROUND(N(P50)/O50*100,2))
A51: 2.3.a | B51: Internship completion | C51: Eligible students completing required internship / Eligible students | D51: % | E51: #REF! | F51: =IF('C2 Validation Rubrics'!R21="","",'C2 Validation Rubrics'!R21) | G51: =IF('C2 Validation Rubrics'!S21="","",'C2 Validation Rubrics'!S21) | H51: =IF(OR(G51="",F51="",F51=0),"",ROUND(E51*MIN(G51/F51,1),2)) | I51: =IF(H51="","",ROUND(H51/E51*100,2)) | J51: =IF(I51="","",IF(I51>YT*100,"Y",IF(I51>=CT*100,"C",IF(I51>=WT*100,"W","D")))) | K51: =IF($J51="Y",1,"") | L51: =IF($J51="C",1,"") | M51: =IF($J51="W",1,"") | N51: =IF($J51="D",1,"") | O51: =IF('C2 Validation Rubrics'!M21="","",'C2 Validation Rubrics'!M21) | P51: =IF('C2 Validation Rubrics'!N21="","",'C2 Validation Rubrics'!N21) | Q51: =IF(N(O51)=0,"",ROUND(N(P51)/O51*100,2)) | R51: =IF('C2 Validation Rubrics'!O21="","",'C2 Validation Rubrics'!O21)
A52: 2.3.b | B52: Quality of internship host | C52: Internships at industry or R&D organisations / Total internships | D52: % | E52: #REF! | F52: =IF('C2 Validation Rubrics'!R22="","",'C2 Validation Rubrics'!R22) | G52: =IF('C2 Validation Rubrics'!S22="","",'C2 Validation Rubrics'!S22) | H52: =IF(OR(G52="",F52="",F52=0),"",ROUND(E52*MIN(G52/F52,1),2)) | I52: =IF(H52="","",ROUND(H52/E52*100,2)) | J52: =IF(I52="","",IF(I52>YT*100,"Y",IF(I52>=CT*100,"C",IF(I52>=WT*100,"W","D")))) | K52: =IF($J52="Y",1,"") | L52: =IF($J52="C",1,"") | M52: =IF($J52="W",1,"") | N52: =IF($J52="D",1,"") | O52: =IF('C2 Validation Rubrics'!M22="","",'C2 Validation Rubrics'!M22) | P52: =IF('C2 Validation Rubrics'!N22="","",'C2 Validation Rubrics'!N22) | Q52: =IF(N(O52)=0,"",ROUND(N(P52)/O52*100,2)) | R52: =IF('C2 Validation Rubrics'!O22="","",'C2 Validation Rubrics'!O22)
A53: 2.3.c | B53: Internship to stipend / PPO | C53: Internships with stipend or pre-placement offer / Total internships | D53: % | E53: #REF! | F53: =IF('C2 Validation Rubrics'!R23="","",'C2 Validation Rubrics'!R23) -> 2 | G53: =IF('C2 Validation Rubrics'!S23="","",'C2 Validation Rubrics'!S23) -> 1 | H53: =IF(OR(G53="",F53="",F53=0),"",ROUND(E53*MIN(G53/F53,1),2)) -> #VALUE! | I53: =IF(H53="","",ROUND(H53/E53*100,2)) -> #VALUE! | J53: =IF(I53="","",IF(I53>YT*100,"Y",IF(I53>=CT*100,"C",IF(I53>=WT*100,"W","D")))) -> #VALUE! | K53: =IF($J53="Y",1,"") -> #VALUE! | L53: =IF($J53="C",1,"") -> #VALUE! | M53: =IF($J53="W",1,"") -> #VALUE! | N53: =IF($J53="D",1,"") -> #VALUE! | O53: =IF('C2 Validation Rubrics'!M23="","",'C2 Validation Rubrics'!M23) | P53: =IF('C2 Validation Rubrics'!N23="","",'C2 Validation Rubrics'!N23) | Q53: =IF(N(O53)=0,"",ROUND(N(P53)/O53*100,2)) | R53: =IF('C2 Validation Rubrics'!O23="","",'C2 Validation Rubrics'!O23)
A54: 2.4 | B54: Seminar and mini/micro projects | E54: #REF! | F54: =IF('C2 Validation Rubrics'!R24="","",'C2 Validation Rubrics'!R24) | G54: =IF('C2 Validation Rubrics'!S24="","",'C2 Validation Rubrics'!S24) | H54: =IF(COUNT(H55:H57)=0,"",SUM(H55:H57)) | I54: =IF(H54="","",ROUND(H54/E54*100,2)) | J54: =IF(I54="","",IF(I54>YT*100,"Y",IF(I54>=CT*100,"C",IF(I54>=WT*100,"W","D")))) | K54: =SUM(K55:K57) -> 0 | L54: =SUM(L55:L57) -> 0 | M54: =SUM(M55:M57) -> 0 | N54: =SUM(N55:N57) -> 0 | O54: =IF(COUNT(O55:O57)=0,"",SUM(O55:O57)) | P54: =IF(COUNT(P55:P57)=0,"",SUM(P55:P57)) | Q54: =IF(N(O54)=0,"",ROUND(N(P54)/O54*100,2))
A55: 2.4.a | B55: Seminar participation | C55: Students who presented a seminar / Students on roll (relevant years) | D55: % | E55: #REF! | F55: =IF('C2 Validation Rubrics'!R25="","",'C2 Validation Rubrics'!R25) | G55: =IF('C2 Validation Rubrics'!S25="","",'C2 Validation Rubrics'!S25) | H55: =IF(OR(G55="",F55="",F55=0),"",ROUND(E55*MIN(G55/F55,1),2)) | I55: =IF(H55="","",ROUND(H55/E55*100,2)) | J55: =IF(I55="","",IF(I55>YT*100,"Y",IF(I55>=CT*100,"C",IF(I55>=WT*100,"W","D")))) | K55: =IF($J55="Y",1,"") | L55: =IF($J55="C",1,"") | M55: =IF($J55="W",1,"") | N55: =IF($J55="D",1,"") | O55: =IF('C2 Validation Rubrics'!M25="","",'C2 Validation Rubrics'!M25) | P55: =IF('C2 Validation Rubrics'!N25="","",'C2 Validation Rubrics'!N25) | Q55: =IF(N(O55)=0,"",ROUND(N(P55)/O55*100,2)) | R55: =IF('C2 Validation Rubrics'!O25="","",'C2 Validation Rubrics'!O25)
A56: 2.4.b | B56: Mini/micro-project completion | C56: Students completing a mini-project / Students on roll | D56: % | E56: #REF! | F56: =IF('C2 Validation Rubrics'!R26="","",'C2 Validation Rubrics'!R26) | G56: =IF('C2 Validation Rubrics'!S26="","",'C2 Validation Rubrics'!S26) | H56: =IF(OR(G56="",F56="",F56=0),"",ROUND(E56*MIN(G56/F56,1),2)) | I56: =IF(H56="","",ROUND(H56/E56*100,2)) | J56: =IF(I56="","",IF(I56>YT*100,"Y",IF(I56>=CT*100,"C",IF(I56>=WT*100,"W","D")))) | K56: =IF($J56="Y",1,"") | L56: =IF($J56="C",1,"") | M56: =IF($J56="W",1,"") | N56: =IF($J56="D",1,"") | O56: =IF('C2 Validation Rubrics'!M26="","",'C2 Validation Rubrics'!M26) | P56: =IF('C2 Validation Rubrics'!N26="","",'C2 Validation Rubrics'!N26) | Q56: =IF(N(O56)=0,"",ROUND(N(P56)/O56*100,2)) | R56: =IF('C2 Validation Rubrics'!O26="","",'C2 Validation Rubrics'!O26)
A57: 2.4.c | B57: Rubric-evaluated mini-projects | C57: Mini-projects evaluated by rubric / Total mini-projects | D57: % | E57: #REF! | F57: =IF('C2 Validation Rubrics'!R27="","",'C2 Validation Rubrics'!R27) | G57: =IF('C2 Validation Rubrics'!S27="","",'C2 Validation Rubrics'!S27) | H57: =IF(OR(G57="",F57="",F57=0),"",ROUND(E57*MIN(G57/F57,1),2)) | I57: =IF(H57="","",ROUND(H57/E57*100,2)) | J57: =IF(I57="","",IF(I57>YT*100,"Y",IF(I57>=CT*100,"C",IF(I57>=WT*100,"W","D")))) | K57: =IF($J57="Y",1,"") | L57: =IF($J57="C",1,"") | M57: =IF($J57="W",1,"") | N57: =IF($J57="D",1,"") | O57: =IF('C2 Validation Rubrics'!M27="","",'C2 Validation Rubrics'!M27) | P57: =IF('C2 Validation Rubrics'!N27="","",'C2 Validation Rubrics'!N27) | Q57: =IF(N(O57)=0,"",ROUND(N(P57)/O57*100,2)) | R57: =IF('C2 Validation Rubrics'!O27="","",'C2 Validation Rubrics'!O27)
A58: 2.5 | B58: Case studies and real-life examples | E58: #REF! | F58: =IF('C2 Validation Rubrics'!R28="","",'C2 Validation Rubrics'!R28) | G58: =IF('C2 Validation Rubrics'!S28="","",'C2 Validation Rubrics'!S28) | H58: =IF(COUNT(H59:H61)=0,"",SUM(H59:H61)) | I58: =IF(H58="","",ROUND(H58/E58*100,2)) | J58: =IF(I58="","",IF(I58>YT*100,"Y",IF(I58>=CT*100,"C",IF(I58>=WT*100,"W","D")))) | K58: =SUM(K59:K61) -> 0 | L58: =SUM(L59:L61) -> 0 | M58: =SUM(M59:M61) -> 0 | N58: =SUM(N59:N61) -> 0 | O58: =IF(COUNT(O59:O61)=0,"",SUM(O59:O61)) | P58: =IF(COUNT(P59:P61)=0,"",SUM(P59:P61)) | Q58: =IF(N(O58)=0,"",ROUND(N(P58)/O58*100,2))
A59: 2.5.a | B59: Courses using case studies | C59: Theory courses with >= N documented case studies / Theory courses | D59: % | E59: #REF! | F59: =IF('C2 Validation Rubrics'!R29="","",'C2 Validation Rubrics'!R29) | G59: =IF('C2 Validation Rubrics'!S29="","",'C2 Validation Rubrics'!S29) | H59: =IF(OR(G59="",F59="",F59=0),"",ROUND(E59*MIN(G59/F59,1),2)) | I59: =IF(H59="","",ROUND(H59/E59*100,2)) | J59: =IF(I59="","",IF(I59>YT*100,"Y",IF(I59>=CT*100,"C",IF(I59>=WT*100,"W","D")))) | K59: =IF($J59="Y",1,"") | L59: =IF($J59="C",1,"") | M59: =IF($J59="W",1,"") | N59: =IF($J59="D",1,"") | O59: =IF('C2 Validation Rubrics'!M29="","",'C2 Validation Rubrics'!M29) | P59: =IF('C2 Validation Rubrics'!N29="","",'C2 Validation Rubrics'!N29) | Q59: =IF(N(O59)=0,"",ROUND(N(P59)/O59*100,2)) | R59: =IF('C2 Validation Rubrics'!O29="","",'C2 Validation Rubrics'!O29)
A60: 2.5.b | B60: Case-based assessment | C60: Courses with case-based questions in internal assessment / Theory courses | D60: % | E60: #REF! | F60: =IF('C2 Validation Rubrics'!R30="","",'C2 Validation Rubrics'!R30) | G60: =IF('C2 Validation Rubrics'!S30="","",'C2 Validation Rubrics'!S30) | H60: =IF(OR(G60="",F60="",F60=0),"",ROUND(E60*MIN(G60/F60,1),2)) | I60: =IF(H60="","",ROUND(H60/E60*100,2)) | J60: =IF(I60="","",IF(I60>YT*100,"Y",IF(I60>=CT*100,"C",IF(I60>=WT*100,"W","D")))) | K60: =IF($J60="Y",1,"") | L60: =IF($J60="C",1,"") | M60: =IF($J60="W",1,"") | N60: =IF($J60="D",1,"") | O60: =IF('C2 Validation Rubrics'!M30="","",'C2 Validation Rubrics'!M30) | P60: =IF('C2 Validation Rubrics'!N30="","",'C2 Validation Rubrics'!N30) | Q60: =IF(N(O60)=0,"",ROUND(N(P60)/O60*100,2)) | R60: =IF('C2 Validation Rubrics'!O30="","",'C2 Validation Rubrics'!O30)
A61: 2.5.c | B61: Industry-led case sessions | C61: Number of industry-expert case sessions held | D61: No. | E61: #REF! | F61: =IF('C2 Validation Rubrics'!R31="","",'C2 Validation Rubrics'!R31) | G61: =IF('C2 Validation Rubrics'!S31="","",'C2 Validation Rubrics'!S31) | H61: =IF(OR(G61="",F61="",F61=0),"",ROUND(E61*MIN(G61/F61,1),2)) | I61: =IF(H61="","",ROUND(H61/E61*100,2)) | J61: =IF(I61="","",IF(I61>YT*100,"Y",IF(I61>=CT*100,"C",IF(I61>=WT*100,"W","D")))) | K61: =IF($J61="Y",1,"") | L61: =IF($J61="C",1,"") | M61: =IF($J61="W",1,"") | N61: =IF($J61="D",1,"") | O61: =IF('C2 Validation Rubrics'!M31="","",'C2 Validation Rubrics'!M31) | P61: =IF('C2 Validation Rubrics'!N31="","",'C2 Validation Rubrics'!N31) | Q61: =IF(N(O61)=0,"",ROUND(N(P61)/O61*100,2)) | R61: =IF('C2 Validation Rubrics'!O31="","",'C2 Validation Rubrics'!O31)
A62: 2.6 | B62: MOOC / SWAYAM / NPTEL / self-learning | E62: #REF! | F62: =IF('C2 Validation Rubrics'!R32="","",'C2 Validation Rubrics'!R32) | G62: =IF('C2 Validation Rubrics'!S32="","",'C2 Validation Rubrics'!S32) | H62: =IF(COUNT(H63:H65)=0,"",SUM(H63:H65)) | I62: =IF(H62="","",ROUND(H62/E62*100,2)) | J62: =IF(I62="","",IF(I62>YT*100,"Y",IF(I62>=CT*100,"C",IF(I62>=WT*100,"W","D")))) | K62: =SUM(K63:K65) -> 0 | L62: =SUM(L63:L65) -> 0 | M62: =SUM(M63:M65) -> 0 | N62: =SUM(N63:N65) -> 0 | O62: =IF(COUNT(O63:O65)=0,"",SUM(O63:O65)) | P62: =IF(COUNT(P63:P65)=0,"",SUM(P63:P65)) | Q62: =IF(N(O62)=0,"",ROUND(N(P62)/O62*100,2))
A63: 2.6.a | B63: MOOC certification | C63: Students with >=1 MOOC certificate in period / Students on roll | D63: % | E63: #REF! | F63: =IF('C2 Validation Rubrics'!R33="","",'C2 Validation Rubrics'!R33) | G63: =IF('C2 Validation Rubrics'!S33="","",'C2 Validation Rubrics'!S33) | H63: =IF(OR(G63="",F63="",F63=0),"",ROUND(E63*MIN(G63/F63,1),2)) | I63: =IF(H63="","",ROUND(H63/E63*100,2)) | J63: =IF(I63="","",IF(I63>YT*100,"Y",IF(I63>=CT*100,"C",IF(I63>=WT*100,"W","D")))) | K63: =IF($J63="Y",1,"") | L63: =IF($J63="C",1,"") | M63: =IF($J63="W",1,"") | N63: =IF($J63="D",1,"") | O63: =IF('C2 Validation Rubrics'!M33="","",'C2 Validation Rubrics'!M33) | P63: =IF('C2 Validation Rubrics'!N33="","",'C2 Validation Rubrics'!N33) | Q63: =IF(N(O63)=0,"",ROUND(N(P63)/O63*100,2)) | R63: =IF('C2 Validation Rubrics'!O33="","",'C2 Validation Rubrics'!O33)
A64: 2.6.b | B64: Credit transfer via MOOC | C64: Credits earned via MOOC / Credits eligible for transfer | D64: % | E64: #REF! | F64: =IF('C2 Validation Rubrics'!R34="","",'C2 Validation Rubrics'!R34) | G64: =IF('C2 Validation Rubrics'!S34="","",'C2 Validation Rubrics'!S34) | H64: =IF(OR(G64="",F64="",F64=0),"",ROUND(E64*MIN(G64/F64,1),2)) | I64: =IF(H64="","",ROUND(H64/E64*100,2)) | J64: =IF(I64="","",IF(I64>YT*100,"Y",IF(I64>=CT*100,"C",IF(I64>=WT*100,"W","D")))) | K64: =IF($J64="Y",1,"") | L64: =IF($J64="C",1,"") | M64: =IF($J64="W",1,"") | N64: =IF($J64="D",1,"") | O64: =IF('C2 Validation Rubrics'!M34="","",'C2 Validation Rubrics'!M34) | P64: =IF('C2 Validation Rubrics'!N34="","",'C2 Validation Rubrics'!N34) | Q64: =IF(N(O64)=0,"",ROUND(N(P64)/O64*100,2)) | R64: =IF('C2 Validation Rubrics'!O34="","",'C2 Validation Rubrics'!O34)
A65: 2.6.c | B65: High-performance MOOC certificates | C65: Elite / Silver / Gold or topper certificates / Total certificates | D65: % | E65: #REF! | F65: =IF('C2 Validation Rubrics'!R35="","",'C2 Validation Rubrics'!R35) | G65: =IF('C2 Validation Rubrics'!S35="","",'C2 Validation Rubrics'!S35) | H65: =IF(OR(G65="",F65="",F65=0),"",ROUND(E65*MIN(G65/F65,1),2)) | I65: =IF(H65="","",ROUND(H65/E65*100,2)) | J65: =IF(I65="","",IF(I65>YT*100,"Y",IF(I65>=CT*100,"C",IF(I65>=WT*100,"W","D")))) | K65: =IF($J65="Y",1,"") | L65: =IF($J65="C",1,"") | M65: =IF($J65="W",1,"") | N65: =IF($J65="D",1,"") | O65: =IF('C2 Validation Rubrics'!M35="","",'C2 Validation Rubrics'!M35) | P65: =IF('C2 Validation Rubrics'!N35="","",'C2 Validation Rubrics'!N35) | Q65: =IF(N(O65)=0,"",ROUND(N(P65)/O65*100,2)) | R65: =IF('C2 Validation Rubrics'!O35="","",'C2 Validation Rubrics'!O35)
A66: 2.7 | B66: Complex engineering problems with SDGs | E66: #REF! | F66: =IF('C2 Validation Rubrics'!R36="","",'C2 Validation Rubrics'!R36) | G66: =IF('C2 Validation Rubrics'!S36="","",'C2 Validation Rubrics'!S36) | H66: =IF(COUNT(H67:H70)=0,"",SUM(H67:H70)) | I66: =IF(H66="","",ROUND(H66/E66*100,2)) | J66: =IF(I66="","",IF(I66>YT*100,"Y",IF(I66>=CT*100,"C",IF(I66>=WT*100,"W","D")))) | K66: =SUM(K67:K70) -> 0 | L66: =SUM(L67:L70) -> 0 | M66: =SUM(M67:M70) -> 0 | N66: =SUM(N67:N70) -> 0 | O66: =IF(COUNT(O67:O70)=0,"",SUM(O67:O70)) | P66: =IF(COUNT(P67:P70)=0,"",SUM(P67:P70)) | Q66: =IF(N(O66)=0,"",ROUND(N(P66)/O66*100,2))
A67: 2.7.a | B67: Courses with complex engineering problems | C67: Courses with >=1 complex-problem task meeting NBA complexity attributes / Core courses | D67: % | E67: #REF! | F67: =IF('C2 Validation Rubrics'!R37="","",'C2 Validation Rubrics'!R37) | G67: =IF('C2 Validation Rubrics'!S37="","",'C2 Validation Rubrics'!S37) | H67: =IF(OR(G67="",F67="",F67=0),"",ROUND(E67*MIN(G67/F67,1),2)) | I67: =IF(H67="","",ROUND(H67/E67*100,2)) | J67: =IF(I67="","",IF(I67>YT*100,"Y",IF(I67>=CT*100,"C",IF(I67>=WT*100,"W","D")))) | K67: =IF($J67="Y",1,"") | L67: =IF($J67="C",1,"") | M67: =IF($J67="W",1,"") | N67: =IF($J67="D",1,"") | O67: =IF('C2 Validation Rubrics'!M37="","",'C2 Validation Rubrics'!M37) | P67: =IF('C2 Validation Rubrics'!N37="","",'C2 Validation Rubrics'!N37) | Q67: =IF(N(O67)=0,"",ROUND(N(P67)/O67*100,2)) | R67: =IF('C2 Validation Rubrics'!O37="","",'C2 Validation Rubrics'!O37)
A68: 2.7.b | B68: Student coverage | C68: Students who attempted complex-problem tasks / Students on roll | D68: % | E68: #REF! | F68: =IF('C2 Validation Rubrics'!R38="","",'C2 Validation Rubrics'!R38) | G68: =IF('C2 Validation Rubrics'!S38="","",'C2 Validation Rubrics'!S38) | H68: =IF(OR(G68="",F68="",F68=0),"",ROUND(E68*MIN(G68/F68,1),2)) | I68: =IF(H68="","",ROUND(H68/E68*100,2)) | J68: =IF(I68="","",IF(I68>YT*100,"Y",IF(I68>=CT*100,"C",IF(I68>=WT*100,"W","D")))) | K68: =IF($J68="Y",1,"") | L68: =IF($J68="C",1,"") | M68: =IF($J68="W",1,"") | N68: =IF($J68="D",1,"") | O68: =IF('C2 Validation Rubrics'!M38="","",'C2 Validation Rubrics'!M38) | P68: =IF('C2 Validation Rubrics'!N38="","",'C2 Validation Rubrics'!N38) | Q68: =IF(N(O68)=0,"",ROUND(N(P68)/O68*100,2)) | R68: =IF('C2 Validation Rubrics'!O38="","",'C2 Validation Rubrics'!O38)
A69: 2.7.c | B69: SDG linkage | C69: Complex-problem tasks mapped to SDGs / Total complex-problem tasks | D69: % | E69: #REF! | F69: =IF('C2 Validation Rubrics'!R39="","",'C2 Validation Rubrics'!R39) | G69: =IF('C2 Validation Rubrics'!S39="","",'C2 Validation Rubrics'!S39) | H69: =IF(OR(G69="",F69="",F69=0),"",ROUND(E69*MIN(G69/F69,1),2)) | I69: =IF(H69="","",ROUND(H69/E69*100,2)) | J69: =IF(I69="","",IF(I69>YT*100,"Y",IF(I69>=CT*100,"C",IF(I69>=WT*100,"W","D")))) | K69: =IF($J69="Y",1,"") | L69: =IF($J69="C",1,"") | M69: =IF($J69="W",1,"") | N69: =IF($J69="D",1,"") | O69: =IF('C2 Validation Rubrics'!M39="","",'C2 Validation Rubrics'!M39) | P69: =IF('C2 Validation Rubrics'!N39="","",'C2 Validation Rubrics'!N39) | Q69: =IF(N(O69)=0,"",ROUND(N(P69)/O69*100,2)) | R69: =IF('C2 Validation Rubrics'!O39="","",'C2 Validation Rubrics'!O39)
A70: 2.7.d | B70: Solution quality | C70: Average rubric score of solutions / Max rubric score | D70: % | E70: #REF! | F70: =IF('C2 Validation Rubrics'!R40="","",'C2 Validation Rubrics'!R40) | G70: =IF('C2 Validation Rubrics'!S40="","",'C2 Validation Rubrics'!S40) | H70: =IF(OR(G70="",F70="",F70=0),"",ROUND(E70*MIN(G70/F70,1),2)) | I70: =IF(H70="","",ROUND(H70/E70*100,2)) | J70: =IF(I70="","",IF(I70>YT*100,"Y",IF(I70>=CT*100,"C",IF(I70>=WT*100,"W","D")))) | K70: =IF($J70="Y",1,"") | L70: =IF($J70="C",1,"") | M70: =IF($J70="W",1,"") | N70: =IF($J70="D",1,"") | O70: =IF('C2 Validation Rubrics'!M40="","",'C2 Validation Rubrics'!M40) | P70: =IF('C2 Validation Rubrics'!N40="","",'C2 Validation Rubrics'!N40) | Q70: =IF(N(O70)=0,"",ROUND(N(P70)/O70*100,2)) | R70: =IF('C2 Validation Rubrics'!O40="","",'C2 Validation Rubrics'!O40)
A71: 2.8 | B71: Industry-institute interaction | E71: #REF! | F71: =IF('C2 Validation Rubrics'!R41="","",'C2 Validation Rubrics'!R41) | G71: =IF('C2 Validation Rubrics'!S41="","",'C2 Validation Rubrics'!S41) | H71: =IF(COUNT(H72:H76)=0,"",SUM(H72:H76)) | I71: =IF(H71="","",ROUND(H71/E71*100,2)) | J71: =IF(I71="","",IF(I71>YT*100,"Y",IF(I71>=CT*100,"C",IF(I71>=WT*100,"W","D")))) | K71: =SUM(K72:K76) -> 0 | L71: =SUM(L72:L76) -> 0 | M71: =SUM(M72:M76) -> 0 | N71: =SUM(N72:N76) -> 0 | O71: =IF(COUNT(O72:O76)=0,"",SUM(O72:O76)) | P71: =IF(COUNT(P72:P76)=0,"",SUM(P72:P76)) | Q71: =IF(N(O71)=0,"",ROUND(N(P71)/O71*100,2))
A72: 2.8.a | B72: Active MoUs | C72: Number of MoUs with >=1 documented activity in the period | D72: No. | E72: #REF! | F72: =IF('C2 Validation Rubrics'!R42="","",'C2 Validation Rubrics'!R42) | G72: =IF('C2 Validation Rubrics'!S42="","",'C2 Validation Rubrics'!S42) | H72: =IF(OR(G72="",F72="",F72=0),"",ROUND(E72*MIN(G72/F72,1),2)) | I72: =IF(H72="","",ROUND(H72/E72*100,2)) | J72: =IF(I72="","",IF(I72>YT*100,"Y",IF(I72>=CT*100,"C",IF(I72>=WT*100,"W","D")))) | K72: =IF($J72="Y",1,"") | L72: =IF($J72="C",1,"") | M72: =IF($J72="W",1,"") | N72: =IF($J72="D",1,"") | O72: =IF('C2 Validation Rubrics'!M42="","",'C2 Validation Rubrics'!M42) | P72: =IF('C2 Validation Rubrics'!N42="","",'C2 Validation Rubrics'!N42) | Q72: =IF(N(O72)=0,"",ROUND(N(P72)/O72*100,2)) | R72: =IF('C2 Validation Rubrics'!O42="","",'C2 Validation Rubrics'!O42)
A73: 2.8.b | B73: Industry expert lectures | C73: Number of guest lectures by industry experts | D73: No. | E73: #REF! | F73: =IF('C2 Validation Rubrics'!R43="","",'C2 Validation Rubrics'!R43) | G73: =IF('C2 Validation Rubrics'!S43="","",'C2 Validation Rubrics'!S43) | H73: =IF(OR(G73="",F73="",F73=0),"",ROUND(E73*MIN(G73/F73,1),2)) | I73: =IF(H73="","",ROUND(H73/E73*100,2)) | J73: =IF(I73="","",IF(I73>YT*100,"Y",IF(I73>=CT*100,"C",IF(I73>=WT*100,"W","D")))) | K73: =IF($J73="Y",1,"") | L73: =IF($J73="C",1,"") | M73: =IF($J73="W",1,"") | N73: =IF($J73="D",1,"") | O73: =IF('C2 Validation Rubrics'!M43="","",'C2 Validation Rubrics'!M43) | P73: =IF('C2 Validation Rubrics'!N43="","",'C2 Validation Rubrics'!N43) | Q73: =IF(N(O73)=0,"",ROUND(N(P73)/O73*100,2)) | R73: =IF('C2 Validation Rubrics'!O43="","",'C2 Validation Rubrics'!O43)
A74: 2.8.c | B74: Industrial visits | C74: Students covered by industrial visits / Students on roll | D74: % | E74: #REF! | F74: =IF('C2 Validation Rubrics'!R44="","",'C2 Validation Rubrics'!R44) | G74: =IF('C2 Validation Rubrics'!S44="","",'C2 Validation Rubrics'!S44) | H74: =IF(OR(G74="",F74="",F74=0),"",ROUND(E74*MIN(G74/F74,1),2)) | I74: =IF(H74="","",ROUND(H74/E74*100,2)) | J74: =IF(I74="","",IF(I74>YT*100,"Y",IF(I74>=CT*100,"C",IF(I74>=WT*100,"W","D")))) | K74: =IF($J74="Y",1,"") | L74: =IF($J74="C",1,"") | M74: =IF($J74="W",1,"") | N74: =IF($J74="D",1,"") | O74: =IF('C2 Validation Rubrics'!M44="","",'C2 Validation Rubrics'!M44) | P74: =IF('C2 Validation Rubrics'!N44="","",'C2 Validation Rubrics'!N44) | Q74: =IF(N(O74)=0,"",ROUND(N(P74)/O74*100,2)) | R74: =IF('C2 Validation Rubrics'!O44="","",'C2 Validation Rubrics'!O44)
A75: 2.8.d | B75: Industry co-delivered courses or labs | C75: Number of co-delivered courses, labs or certifications | D75: No. | E75: #REF! | F75: =IF('C2 Validation Rubrics'!R45="","",'C2 Validation Rubrics'!R45) | G75: =IF('C2 Validation Rubrics'!S45="","",'C2 Validation Rubrics'!S45) | H75: =IF(OR(G75="",F75="",F75=0),"",ROUND(E75*MIN(G75/F75,1),2)) | I75: =IF(H75="","",ROUND(H75/E75*100,2)) | J75: =IF(I75="","",IF(I75>YT*100,"Y",IF(I75>=CT*100,"C",IF(I75>=WT*100,"W","D")))) | K75: =IF($J75="Y",1,"") | L75: =IF($J75="C",1,"") | M75: =IF($J75="W",1,"") | N75: =IF($J75="D",1,"") | O75: =IF('C2 Validation Rubrics'!M45="","",'C2 Validation Rubrics'!M45) | P75: =IF('C2 Validation Rubrics'!N45="","",'C2 Validation Rubrics'!N45) | Q75: =IF(N(O75)=0,"",ROUND(N(P75)/O75*100,2)) | R75: =IF('C2 Validation Rubrics'!O45="","",'C2 Validation Rubrics'!O45)
A76: 2.8.e | B76: Industry-supported projects or internships | C76: Number of industry-supported projects or internships | D76: No. | E76: #REF! | F76: =IF('C2 Validation Rubrics'!R46="","",'C2 Validation Rubrics'!R46) | G76: =IF('C2 Validation Rubrics'!S46="","",'C2 Validation Rubrics'!S46) | H76: =IF(OR(G76="",F76="",F76=0),"",ROUND(E76*MIN(G76/F76,1),2)) | I76: =IF(H76="","",ROUND(H76/E76*100,2)) | J76: =IF(I76="","",IF(I76>YT*100,"Y",IF(I76>=CT*100,"C",IF(I76>=WT*100,"W","D")))) | K76: =IF($J76="Y",1,"") | L76: =IF($J76="C",1,"") | M76: =IF($J76="W",1,"") | N76: =IF($J76="D",1,"") | O76: =IF('C2 Validation Rubrics'!M46="","",'C2 Validation Rubrics'!M46) | P76: =IF('C2 Validation Rubrics'!N46="","",'C2 Validation Rubrics'!N46) | Q76: =IF(N(O76)=0,"",ROUND(N(P76)/O76*100,2)) | R76: =IF('C2 Validation Rubrics'!O46="","",'C2 Validation Rubrics'!O46)
A77: C2 | B77: CRITERION 2 TOTAL | E77: #REF! | F77: =IF('C2 Validation Rubrics'!R47="","",'C2 Validation Rubrics'!R47) | G77: =IF('C2 Validation Rubrics'!S47="","",'C2 Validation Rubrics'!S47) | H77: =IF(COUNT(H38,H44,H50,H54,H58,H62,H66,H71)=0,"",N(H38)+N(H44)+N(H50)+N(H54)+N(H58)+N(H62)+N(H66)+N(H71)) | I77: =IF(H77="","",ROUND(H77/E77*100,2)) | J77: =IF(I77="","",IF(I77>YT*100,"Y",IF(I77>=CT*100,"C",IF(I77>=WT*100,"W","D")))) | K77: =N(K38)+N(K44)+N(K50)+N(K54)+N(K58)+N(K62)+N(K66)+N(K71) -> #VALUE! | L77: =N(L38)+N(L44)+N(L50)+N(L54)+N(L58)+N(L62)+N(L66)+N(L71) -> #VALUE! | M77: =N(M38)+N(M44)+N(M50)+N(M54)+N(M58)+N(M62)+N(M66)+N(M71) -> #VALUE! | N77: =N(N38)+N(N44)+N(N50)+N(N54)+N(N58)+N(N62)+N(N66)+N(N71) -> #VALUE! | O77: =IF(COUNT(O38,O44,O50,O54,O58,O62,O66,O71)=0,"",N(O38)+N(O44)+N(O50)+N(O54)+N(O58)+N(O62)+N(O66)+N(O71)) | P77: =IF(COUNT(P38,P44,P50,P54,P58,P62,P66,P71)=0,"",N(P38)+N(P44)+N(P50)+N(P54)+N(P58)+N(P62)+N(P66)+N(P71)) | Q77: =IF(N(O77)=0,"",ROUND(N(P77)/O77*100,2))
A78: C3 | B78: CRITERION 3 - OUTCOME-BASED ASSESSMENT
A79: 3.1 | B79: Evaluation of continuous assessment | E79: #REF! | F79: #REF! | G79: #REF! | H79: =IF(COUNT(H80:H82)=0,"",SUM(H80:H82)) | I79: =IF(H79="","",ROUND(H79/E79*100,2)) | J79: =IF(I79="","",IF(I79>YT*100,"Y",IF(I79>=CT*100,"C",IF(I79>=WT*100,"W","D")))) | K79: =SUM(K80:K82) -> #VALUE! | L79: =SUM(L80:L82) -> #VALUE! | M79: =SUM(M80:M82) -> #VALUE! | N79: =SUM(N80:N82) -> #VALUE! | O79: =IF(COUNT(O80:O82)=0,"",SUM(O80:O82)) | P79: =IF(COUNT(P80:P82)=0,"",SUM(P80:P82)) | Q79: =IF(N(O79)=0,"",ROUND(N(P79)/O79*100,2))
A80: 3.1.a | B80: CA papers mapped to CO and Bloom's level | C80: CA papers with CO/BL mapping / CA papers set | D80: % | E80: #REF! | F80: #REF! | G80: #REF! | H80: =IF(OR(G80="",F80="",F80=0),"",ROUND(E80*MIN(G80/F80,1),2)) -> #VALUE! | I80: =IF(H80="","",ROUND(H80/E80*100,2)) -> #VALUE! | J80: =IF(I80="","",IF(I80>YT*100,"Y",IF(I80>=CT*100,"C",IF(I80>=WT*100,"W","D")))) -> #VALUE! | K80: =IF($J80="Y",1,"") -> #VALUE! | L80: =IF($J80="C",1,"") -> #VALUE! | M80: =IF($J80="W",1,"") -> #VALUE! | N80: =IF($J80="D",1,"") -> #VALUE! | O80: =IF('C3 Validation Rubrics'!M9="","",'C3 Validation Rubrics'!M9) | P80: =IF('C3 Validation Rubrics'!N9="","",'C3 Validation Rubrics'!N9) | Q80: =IF(N(O80)=0,"",ROUND(N(P80)/O80*100,2)) | R80: =IF('C3 Validation Rubrics'!O9="","",'C3 Validation Rubrics'!O9)
A81: 3.1.b | B81: CA papers scrutinised before use | C81: Papers scrutinised / CA papers set | D81: % | E81: #REF! | F81: #REF! | G81: #REF! | H81: =IF(OR(G81="",F81="",F81=0),"",ROUND(E81*MIN(G81/F81,1),2)) -> #VALUE! | I81: =IF(H81="","",ROUND(H81/E81*100,2)) -> #VALUE! | J81: =IF(I81="","",IF(I81>YT*100,"Y",IF(I81>=CT*100,"C",IF(I81>=WT*100,"W","D")))) -> #VALUE! | K81: =IF($J81="Y",1,"") -> #VALUE! | L81: =IF($J81="C",1,"") -> #VALUE! | M81: =IF($J81="W",1,"") -> #VALUE! | N81: =IF($J81="D",1,"") -> #VALUE! | O81: =IF('C3 Validation Rubrics'!M10="","",'C3 Validation Rubrics'!M10) | P81: =IF('C3 Validation Rubrics'!N10="","",'C3 Validation Rubrics'!N10) | Q81: =IF(N(O81)=0,"",ROUND(N(P81)/O81*100,2)) | R81: =IF('C3 Validation Rubrics'!O10="","",'C3 Validation Rubrics'!O10)
A82: 3.1.c | B82: CA results published on time | C82: Assessments with results published within timeline / Assessments conducted | D82: % | E82: #REF! | F82: #REF! | G82: #REF! | H82: =IF(OR(G82="",F82="",F82=0),"",ROUND(E82*MIN(G82/F82,1),2)) -> #VALUE! | I82: =IF(H82="","",ROUND(H82/E82*100,2)) -> #VALUE! | J82: =IF(I82="","",IF(I82>YT*100,"Y",IF(I82>=CT*100,"C",IF(I82>=WT*100,"W","D")))) -> #VALUE! | K82: =IF($J82="Y",1,"") -> #VALUE! | L82: =IF($J82="C",1,"") -> #VALUE! | M82: =IF($J82="W",1,"") -> #VALUE! | N82: =IF($J82="D",1,"") -> #VALUE! | O82: =IF('C3 Validation Rubrics'!M11="","",'C3 Validation Rubrics'!M11) | P82: =IF('C3 Validation Rubrics'!N11="","",'C3 Validation Rubrics'!N11) | Q82: =IF(N(O82)=0,"",ROUND(N(P82)/O82*100,2)) | R82: =IF('C3 Validation Rubrics'!O11="","",'C3 Validation Rubrics'!O11)
A83: 3.2 | B83: Evaluation of SEE question papers | E83: #REF! | F83: #REF! | G83: #REF! | H83: =IF(COUNT(H84:H85)=0,"",SUM(H84:H85)) | I83: =IF(H83="","",ROUND(H83/E83*100,2)) | J83: =IF(I83="","",IF(I83>YT*100,"Y",IF(I83>=CT*100,"C",IF(I83>=WT*100,"W","D")))) | K83: =SUM(K84:K85) -> #VALUE! | L83: =SUM(L84:L85) -> #VALUE! | M83: =SUM(M84:M85) -> #VALUE! | N83: =SUM(N84:N85) -> #VALUE! | O83: =IF(COUNT(O84:O85)=0,"",SUM(O84:O85)) | P83: =IF(COUNT(P84:P85)=0,"",SUM(P84:P85)) | Q83: =IF(N(O83)=0,"",ROUND(N(P83)/O83*100,2))
A84: 3.2.a | B84: SEE papers analysed for CO/BL coverage | C84: SEE papers analysed / SEE papers | D84: % | E84: #REF! | F84: #REF! | G84: #REF! | H84: =IF(OR(G84="",F84="",F84=0),"",ROUND(E84*MIN(G84/F84,1),2)) -> #VALUE! | I84: =IF(H84="","",ROUND(H84/E84*100,2)) -> #VALUE! | J84: =IF(I84="","",IF(I84>YT*100,"Y",IF(I84>=CT*100,"C",IF(I84>=WT*100,"W","D")))) -> #VALUE! | K84: =IF($J84="Y",1,"") -> #VALUE! | L84: =IF($J84="C",1,"") -> #VALUE! | M84: =IF($J84="W",1,"") -> #VALUE! | N84: =IF($J84="D",1,"") -> #VALUE! | O84: =IF('C3 Validation Rubrics'!M13="","",'C3 Validation Rubrics'!M13) | P84: =IF('C3 Validation Rubrics'!N13="","",'C3 Validation Rubrics'!N13) | Q84: =IF(N(O84)=0,"",ROUND(N(P84)/O84*100,2)) | R84: =IF('C3 Validation Rubrics'!O13="","",'C3 Validation Rubrics'!O13)
A85: 3.2.b | B85: SEE papers with adequate higher-order questions | C85: Papers with required share of Apply-and-above marks / Papers analysed | D85: % | E85: #REF! | F85: #REF! | G85: #REF! | H85: =IF(OR(G85="",F85="",F85=0),"",ROUND(E85*MIN(G85/F85,1),2)) -> #VALUE! | I85: =IF(H85="","",ROUND(H85/E85*100,2)) -> #VALUE! | J85: =IF(I85="","",IF(I85>YT*100,"Y",IF(I85>=CT*100,"C",IF(I85>=WT*100,"W","D")))) -> #VALUE! | K85: =IF($J85="Y",1,"") -> #VALUE! | L85: =IF($J85="C",1,"") -> #VALUE! | M85: =IF($J85="W",1,"") -> #VALUE! | N85: =IF($J85="D",1,"") -> #VALUE! | O85: =IF('C3 Validation Rubrics'!M14="","",'C3 Validation Rubrics'!M14) | P85: =IF('C3 Validation Rubrics'!N14="","",'C3 Validation Rubrics'!N14) | Q85: =IF(N(O85)=0,"",ROUND(N(P85)/O85*100,2)) | R85: =IF('C3 Validation Rubrics'!O14="","",'C3 Validation Rubrics'!O14)
A86: 3.3 | B86: Evaluation of laboratory work | E86: #REF! | F86: #REF! | G86: #REF! | H86: =IF(COUNT(H87:H89)=0,"",SUM(H87:H89)) | I86: =IF(H86="","",ROUND(H86/E86*100,2)) | J86: =IF(I86="","",IF(I86>YT*100,"Y",IF(I86>=CT*100,"C",IF(I86>=WT*100,"W","D")))) | K86: =SUM(K87:K89) -> #VALUE! | L86: =SUM(L87:L89) -> #VALUE! | M86: =SUM(M87:M89) -> #VALUE! | N86: =SUM(N87:N89) -> #VALUE! | O86: =IF(COUNT(O87:O89)=0,"",SUM(O87:O89)) | P86: =IF(COUNT(P87:P89)=0,"",SUM(P87:P89)) | Q86: =IF(N(O86)=0,"",ROUND(N(P86)/O86*100,2))
A87: 3.3.a | B87: Rubric-based continuous lab evaluation | C87: Lab courses with rubric evaluation / Lab courses | D87: % | E87: #REF! | F87: #REF! | G87: #REF! | H87: =IF(OR(G87="",F87="",F87=0),"",ROUND(E87*MIN(G87/F87,1),2)) -> #VALUE! | I87: =IF(H87="","",ROUND(H87/E87*100,2)) -> #VALUE! | J87: =IF(I87="","",IF(I87>YT*100,"Y",IF(I87>=CT*100,"C",IF(I87>=WT*100,"W","D")))) -> #VALUE! | K87: =IF($J87="Y",1,"") -> #VALUE! | L87: =IF($J87="C",1,"") -> #VALUE! | M87: =IF($J87="W",1,"") -> #VALUE! | N87: =IF($J87="D",1,"") -> #VALUE! | O87: =IF('C3 Validation Rubrics'!M16="","",'C3 Validation Rubrics'!M16) | P87: =IF('C3 Validation Rubrics'!N16="","",'C3 Validation Rubrics'!N16) | Q87: =IF(N(O87)=0,"",ROUND(N(P87)/O87*100,2)) | R87: =IF('C3 Validation Rubrics'!O16="","",'C3 Validation Rubrics'!O16)
A88: 3.3.b | B88: Experiments evaluated on schedule | C88: Experiments evaluated on schedule / Experiments conducted | D88: % | E88: #REF! | F88: #REF! | G88: #REF! | H88: =IF(OR(G88="",F88="",F88=0),"",ROUND(E88*MIN(G88/F88,1),2)) -> #VALUE! | I88: =IF(H88="","",ROUND(H88/E88*100,2)) -> #VALUE! | J88: =IF(I88="","",IF(I88>YT*100,"Y",IF(I88>=CT*100,"C",IF(I88>=WT*100,"W","D")))) -> #VALUE! | K88: =IF($J88="Y",1,"") -> #VALUE! | L88: =IF($J88="C",1,"") -> #VALUE! | M88: =IF($J88="W",1,"") -> #VALUE! | N88: =IF($J88="D",1,"") -> #VALUE! | O88: =IF('C3 Validation Rubrics'!M17="","",'C3 Validation Rubrics'!M17) | P88: =IF('C3 Validation Rubrics'!N17="","",'C3 Validation Rubrics'!N17) | Q88: =IF(N(O88)=0,"",ROUND(N(P88)/O88*100,2)) | R88: =IF('C3 Validation Rubrics'!O17="","",'C3 Validation Rubrics'!O17)
A89: 3.3.c | B89: Lab records assessed | C89: Students with records assessed / Students in lab courses | D89: % | E89: #REF! | F89: #REF! | G89: #REF! | H89: =IF(OR(G89="",F89="",F89=0),"",ROUND(E89*MIN(G89/F89,1),2)) -> #VALUE! | I89: =IF(H89="","",ROUND(H89/E89*100,2)) -> #VALUE! | J89: =IF(I89="","",IF(I89>YT*100,"Y",IF(I89>=CT*100,"C",IF(I89>=WT*100,"W","D")))) -> #VALUE! | K89: =IF($J89="Y",1,"") -> #VALUE! | L89: =IF($J89="C",1,"") -> #VALUE! | M89: =IF($J89="W",1,"") -> #VALUE! | N89: =IF($J89="D",1,"") -> #VALUE! | O89: =IF('C3 Validation Rubrics'!M18="","",'C3 Validation Rubrics'!M18) | P89: =IF('C3 Validation Rubrics'!N18="","",'C3 Validation Rubrics'!N18) | Q89: =IF(N(O89)=0,"",ROUND(N(P89)/O89*100,2)) | R89: =IF('C3 Validation Rubrics'!O18="","",'C3 Validation Rubrics'!O18)
A90: 3.4 | B90: Evaluation of industrial training / internship | E90: #REF! | F90: #REF! | G90: #REF! | H90: =IF(COUNT(H91:H92)=0,"",SUM(H91:H92)) | I90: =IF(H90="","",ROUND(H90/E90*100,2)) | J90: =IF(I90="","",IF(I90>YT*100,"Y",IF(I90>=CT*100,"C",IF(I90>=WT*100,"W","D")))) | K90: =SUM(K91:K92) -> #VALUE! | L90: =SUM(L91:L92) -> #VALUE! | M90: =SUM(M91:M92) -> #VALUE! | N90: =SUM(N91:N92) -> #VALUE! | O90: =IF(COUNT(O91:O92)=0,"",SUM(O91:O92)) | P90: =IF(COUNT(P91:P92)=0,"",SUM(P91:P92)) | Q90: =IF(N(O90)=0,"",ROUND(N(P90)/O90*100,2))
A91: 3.4.a | B91: Internships evaluated with rubric | C91: Internships evaluated with rubric / Internships completed | D91: % | E91: #REF! | F91: #REF! | G91: #REF! | H91: =IF(OR(G91="",F91="",F91=0),"",ROUND(E91*MIN(G91/F91,1),2)) -> #VALUE! | I91: =IF(H91="","",ROUND(H91/E91*100,2)) -> #VALUE! | J91: =IF(I91="","",IF(I91>YT*100,"Y",IF(I91>=CT*100,"C",IF(I91>=WT*100,"W","D")))) -> #VALUE! | K91: =IF($J91="Y",1,"") -> #VALUE! | L91: =IF($J91="C",1,"") -> #VALUE! | M91: =IF($J91="W",1,"") -> #VALUE! | N91: =IF($J91="D",1,"") -> #VALUE! | O91: =IF('C3 Validation Rubrics'!M20="","",'C3 Validation Rubrics'!M20) | P91: =IF('C3 Validation Rubrics'!N20="","",'C3 Validation Rubrics'!N20) | Q91: =IF(N(O91)=0,"",ROUND(N(P91)/O91*100,2)) | R91: =IF('C3 Validation Rubrics'!O20="","",'C3 Validation Rubrics'!O20)
A92: 3.4.b | B92: Internship presentation / viva held | C92: Internships with presentation or viva / Internships completed | D92: % | E92: #REF! | F92: #REF! | G92: #REF! | H92: =IF(OR(G92="",F92="",F92=0),"",ROUND(E92*MIN(G92/F92,1),2)) -> #VALUE! | I92: =IF(H92="","",ROUND(H92/E92*100,2)) -> #VALUE! | J92: =IF(I92="","",IF(I92>YT*100,"Y",IF(I92>=CT*100,"C",IF(I92>=WT*100,"W","D")))) -> #VALUE! | K92: =IF($J92="Y",1,"") -> #VALUE! | L92: =IF($J92="C",1,"") -> #VALUE! | M92: =IF($J92="W",1,"") -> #VALUE! | N92: =IF($J92="D",1,"") -> #VALUE! | O92: =IF('C3 Validation Rubrics'!M21="","",'C3 Validation Rubrics'!M21) | P92: =IF('C3 Validation Rubrics'!N21="","",'C3 Validation Rubrics'!N21) | Q92: =IF(N(O92)=0,"",ROUND(N(P92)/O92*100,2)) | R92: =IF('C3 Validation Rubrics'!O21="","",'C3 Validation Rubrics'!O21)
A93: 3.5 | B93: Evaluation of projects | E93: #REF! | F93: #REF! | G93: #REF! | H93: =IF(COUNT(H94:H96)=0,"",SUM(H94:H96)) | I93: =IF(H93="","",ROUND(H93/E93*100,2)) | J93: =IF(I93="","",IF(I93>YT*100,"Y",IF(I93>=CT*100,"C",IF(I93>=WT*100,"W","D")))) | K93: =SUM(K94:K96) -> #VALUE! | L93: =SUM(L94:L96) -> #VALUE! | M93: =SUM(M94:M96) -> #VALUE! | N93: =SUM(N94:N96) -> #VALUE! | O93: =IF(COUNT(O94:O96)=0,"",SUM(O94:O96)) | P93: =IF(COUNT(P94:P96)=0,"",SUM(P94:P96)) | Q93: =IF(N(O93)=0,"",ROUND(N(P93)/O93*100,2))
A94: 3.5.a | B94: Projects with 3 or more rubric reviews | C94: Projects with >=3 rubric reviews / Projects | D94: % | E94: #REF! | F94: #REF! | G94: #REF! | H94: =IF(OR(G94="",F94="",F94=0),"",ROUND(E94*MIN(G94/F94,1),2)) -> #VALUE! | I94: =IF(H94="","",ROUND(H94/E94*100,2)) -> #VALUE! | J94: =IF(I94="","",IF(I94>YT*100,"Y",IF(I94>=CT*100,"C",IF(I94>=WT*100,"W","D")))) -> #VALUE! | K94: =IF($J94="Y",1,"") -> #VALUE! | L94: =IF($J94="C",1,"") -> #VALUE! | M94: =IF($J94="W",1,"") -> #VALUE! | N94: =IF($J94="D",1,"") -> #VALUE! | O94: =IF('C3 Validation Rubrics'!M23="","",'C3 Validation Rubrics'!M23) | P94: =IF('C3 Validation Rubrics'!N23="","",'C3 Validation Rubrics'!N23) | Q94: =IF(N(O94)=0,"",ROUND(N(P94)/O94*100,2)) | R94: =IF('C3 Validation Rubrics'!O23="","",'C3 Validation Rubrics'!O23)
A95: 3.5.b | B95: Projects evaluated by external examiner | C95: Projects with external evaluation / Projects | D95: % | E95: #REF! | F95: #REF! | G95: #REF! | H95: =IF(OR(G95="",F95="",F95=0),"",ROUND(E95*MIN(G95/F95,1),2)) -> #VALUE! | I95: =IF(H95="","",ROUND(H95/E95*100,2)) -> #VALUE! | J95: =IF(I95="","",IF(I95>YT*100,"Y",IF(I95>=CT*100,"C",IF(I95>=WT*100,"W","D")))) -> #VALUE! | K95: =IF($J95="Y",1,"") -> #VALUE! | L95: =IF($J95="C",1,"") -> #VALUE! | M95: =IF($J95="W",1,"") -> #VALUE! | N95: =IF($J95="D",1,"") -> #VALUE! | O95: =IF('C3 Validation Rubrics'!M24="","",'C3 Validation Rubrics'!M24) | P95: =IF('C3 Validation Rubrics'!N24="","",'C3 Validation Rubrics'!N24) | Q95: =IF(N(O95)=0,"",ROUND(N(P95)/O95*100,2)) | R95: =IF('C3 Validation Rubrics'!O24="","",'C3 Validation Rubrics'!O24)
A96: 3.5.c | B96: PO attainment computed from projects | C96: Projects with PO attainment computed / Projects | D96: % | E96: #REF! | F96: #REF! | G96: #REF! | H96: =IF(OR(G96="",F96="",F96=0),"",ROUND(E96*MIN(G96/F96,1),2)) -> #VALUE! | I96: =IF(H96="","",ROUND(H96/E96*100,2)) -> #VALUE! | J96: =IF(I96="","",IF(I96>YT*100,"Y",IF(I96>=CT*100,"C",IF(I96>=WT*100,"W","D")))) -> #VALUE! | K96: =IF($J96="Y",1,"") -> #VALUE! | L96: =IF($J96="C",1,"") -> #VALUE! | M96: =IF($J96="W",1,"") -> #VALUE! | N96: =IF($J96="D",1,"") -> #VALUE! | O96: =IF('C3 Validation Rubrics'!M25="","",'C3 Validation Rubrics'!M25) | P96: =IF('C3 Validation Rubrics'!N25="","",'C3 Validation Rubrics'!N25) | Q96: =IF(N(O96)=0,"",ROUND(N(P96)/O96*100,2)) | R96: =IF('C3 Validation Rubrics'!O25="","",'C3 Validation Rubrics'!O25)
A97: 3.6 | B97: Evidence of addressing SDGs | E97: #REF! | F97: #REF! | G97: #REF! | H97: =IF(COUNT(H98:H99)=0,"",SUM(H98:H99)) | I97: =IF(H97="","",ROUND(H97/E97*100,2)) | J97: =IF(I97="","",IF(I97>YT*100,"Y",IF(I97>=CT*100,"C",IF(I97>=WT*100,"W","D")))) | K97: =SUM(K98:K99) -> #VALUE! | L97: =SUM(L98:L99) -> #VALUE! | M97: =SUM(M98:M99) -> #VALUE! | N97: =SUM(N98:N99) -> #VALUE! | O97: =IF(COUNT(O98:O99)=0,"",SUM(O98:O99)) | P97: =IF(COUNT(P98:P99)=0,"",SUM(P98:P99)) | Q97: =IF(N(O97)=0,"",ROUND(N(P97)/O97*100,2))
A98: 3.6.a | B98: Courses with SDG-mapped assessment | C98: Courses with SDG-mapped assessment items / Courses offered | D98: % | E98: #REF! | F98: #REF! | G98: #REF! | H98: =IF(OR(G98="",F98="",F98=0),"",ROUND(E98*MIN(G98/F98,1),2)) -> #VALUE! | I98: =IF(H98="","",ROUND(H98/E98*100,2)) -> #VALUE! | J98: =IF(I98="","",IF(I98>YT*100,"Y",IF(I98>=CT*100,"C",IF(I98>=WT*100,"W","D")))) -> #VALUE! | K98: =IF($J98="Y",1,"") -> #VALUE! | L98: =IF($J98="C",1,"") -> #VALUE! | M98: =IF($J98="W",1,"") -> #VALUE! | N98: =IF($J98="D",1,"") -> #VALUE! | O98: =IF('C3 Validation Rubrics'!M27="","",'C3 Validation Rubrics'!M27) | P98: =IF('C3 Validation Rubrics'!N27="","",'C3 Validation Rubrics'!N27) | Q98: =IF(N(O98)=0,"",ROUND(N(P98)/O98*100,2)) | R98: =IF('C3 Validation Rubrics'!O27="","",'C3 Validation Rubrics'!O27)
A99: 3.6.b | B99: Projects / assignments addressing SDGs | C99: SDG-addressing projects and assignments / Total projects and assignments | D99: % | E99: #REF! | F99: #REF! | G99: #REF! | H99: =IF(OR(G99="",F99="",F99=0),"",ROUND(E99*MIN(G99/F99,1),2)) -> #VALUE! | I99: =IF(H99="","",ROUND(H99/E99*100,2)) -> #VALUE! | J99: =IF(I99="","",IF(I99>YT*100,"Y",IF(I99>=CT*100,"C",IF(I99>=WT*100,"W","D")))) -> #VALUE! | K99: =IF($J99="Y",1,"") -> #VALUE! | L99: =IF($J99="C",1,"") -> #VALUE! | M99: =IF($J99="W",1,"") -> #VALUE! | N99: =IF($J99="D",1,"") -> #VALUE! | O99: =IF('C3 Validation Rubrics'!M28="","",'C3 Validation Rubrics'!M28) | P99: =IF('C3 Validation Rubrics'!N28="","",'C3 Validation Rubrics'!N28) | Q99: =IF(N(O99)=0,"",ROUND(N(P99)/O99*100,2)) | R99: =IF('C3 Validation Rubrics'!O28="","",'C3 Validation Rubrics'!O28)
A100: 3.7 | B100: Attainment of Course Outcomes | E100: #REF! | F100: #REF! | G100: #REF! | H100: =IF(COUNT(H101:H103)=0,"",SUM(H101:H103)) | I100: =IF(H100="","",ROUND(H100/E100*100,2)) | J100: =IF(I100="","",IF(I100>YT*100,"Y",IF(I100>=CT*100,"C",IF(I100>=WT*100,"W","D")))) | K100: =SUM(K101:K103) -> #VALUE! | L100: =SUM(L101:L103) -> #VALUE! | M100: =SUM(M101:M103) -> #VALUE! | N100: =SUM(N101:N103) -> #VALUE! | O100: =IF(COUNT(O101:O103)=0,"",SUM(O101:O103)) | P100: =IF(COUNT(P101:P103)=0,"",SUM(P101:P103)) | Q100: =IF(N(O100)=0,"",ROUND(N(P100)/O100*100,2))
A101: 3.7.a | B101: Assessment tools defined (3.7.1) | C101: Courses with direct + indirect tools and weightages defined / Courses offered | D101: % | E101: #REF! | F101: #REF! | G101: #REF! | H101: =IF(OR(G101="",F101="",F101=0),"",ROUND(E101*MIN(G101/F101,1),2)) -> #VALUE! | I101: =IF(H101="","",ROUND(H101/E101*100,2)) -> #VALUE! | J101: =IF(I101="","",IF(I101>YT*100,"Y",IF(I101>=CT*100,"C",IF(I101>=WT*100,"W","D")))) -> #VALUE! | K101: =IF($J101="Y",1,"") -> #VALUE! | L101: =IF($J101="C",1,"") -> #VALUE! | M101: =IF($J101="W",1,"") -> #VALUE! | N101: =IF($J101="D",1,"") -> #VALUE! | O101: =IF('C3 Validation Rubrics'!M30="","",'C3 Validation Rubrics'!M30) | P101: =IF('C3 Validation Rubrics'!N30="","",'C3 Validation Rubrics'!N30) | Q101: =IF(N(O101)=0,"",ROUND(N(P101)/O101*100,2)) | R101: =IF('C3 Validation Rubrics'!O30="","",'C3 Validation Rubrics'!O30)
...

Sheet C1 Validation Rubrics
A1: CRITERION 1 - OUTCOME-BASED CURRICULUM - VALIDATION RUBRICS AND SAMPLE SIZES (physical audit)
A2: Sampling: check at least the Sample % of the population, but never fewer than the Minimum (check all items if the population is smaller). Sample % and Minimum are defaults - IQAC may change them.
A3: For % indicators: Validated value = Valid items / Items checked x 100. For count indicators: Validated value = number of claimed items found valid.
A4: Enter the Benchmark (col R) and Validated value (col S) here. Marks, Percentage and Grade (Y > 75, C 60-75, W 40-60, D < 40) are calculated automatically and flow to the C1 Quantitative and All Criteria tabs.
A5: Yellow/blue = input: Items checked, Valid items, Auditor remarks, Benchmark, Validated value (and Sample % / Minimum if IQAC changes them).
A7: Code | B7: Key aspect | C7: What the auditor verifies | D7: An item counts as valid only if | E7: Sampling unit | F7: Sample % | G7: Minimum sample | H7: How to sample | I7: Y (> 75%) | J7: C (60-75%) | K7: W (40-60%) | L7: D (< 40%) | M7: Items checked | N7: Valid items | O7: Auditor remarks | P7: Unit | Q7: Max marks | R7: Benchmark | S7: Validated value | T7: Marks obtained | U7: Percentage | V7: Grade | W7: Y | X7: C | Y7: W | Z7: D
A8: 1.1 | B8: Vision, Mission and PEOs | Q8: =SUM(Q9:Q16) -> 35 | R8: 30 | T8: =SUM(T9:T16) -> 0 | U8: =IF(COUNT(T9:T16)=0,"",ROUND(T8/Q8*100,2)) | V8: =IF(U8="","",IF(U8>YT*100,"Y",IF(U8>=CT*100,"C",IF(U8>=WT*100,"W","D")))) | W8: =SUM(W9:W16) -> 0 | X8: =SUM(X9:X16) -> 0 | Y8: =SUM(Y9:Y16) -> 0 | Z8: =SUM(Z9:Z16) -> 0
A9: 1.1.a | B9: Approval of Vision & Mission (1.1.1) | C9: Approval of Vision & Mission | D9: Signed minutes of IQAC, DAB and GB approving the current V&M | E9: Approvals (count) | F9: 1 | G9: 3 | H9: Check every required approval (IQAC, DAB, GB) | I9: All approvals with signed, dated minutes | J9: One approval with minutes unsigned or undated | K9: One approval missing | L9: Approvals not obtained or minutes absent | P9: % | Q9: 5 | T9: =IF(OR(S9="",R9="",R9=0),"",ROUND(Q9*MIN(S9/R9,1),2)) | U9: =IF(T9="","",ROUND(T9/Q9*100,2)) | V9: =IF(U9="","",IF(U9>YT*100,"Y",IF(U9>=CT*100,"C",IF(U9>=WT*100,"W","D")))) | W9: =IF($V9="Y",1,"") | X9: =IF($V9="C",1,"") | Y9: =IF($V9="W",1,"") | Z9: =IF($V9="D",1,"")
A10: 1.1.b | B10: Quality of PEOs (1.1.2) | C10: Quality of PEOs | D10: PEO is specific, measurable and describes graduates 3-5 years after graduation | E10: PEOs | F10: 1 | G10: 3 | H10: Check every PEO against the 3 criteria | I10: All PEOs meet all criteria | J10: Most PEOs meet criteria; wording minor gaps | K10: Several PEOs vague or not measurable | L10: PEOs not defined or copied from other programmes | P10: % | Q10: 5 | T10: =IF(OR(S10="",R10="",R10=0),"",ROUND(Q10*MIN(S10/R10,1),2)) | U10: =IF(T10="","",ROUND(T10/Q10*100,2)) | V10: =IF(U10="","",IF(U10>YT*100,"Y",IF(U10>=CT*100,"C",IF(U10>=WT*100,"W","D")))) | W10: =IF($V10="Y",1,"") | X10: =IF($V10="C",1,"") | Y10: =IF($V10="W",1,"") | Z10: =IF($V10="D",1,"")
A11: 1.1.c | B11: Stakeholder categories consulted (1.1.3) | C11: Stakeholder categories consulted | D11: Dated consultation record (minutes/survey) for the category | E11: Stakeholder categories | F11: 1 | G11: 6 | H11: Check all 6 categories (students, alumni, employers, parents, faculty, industry) | I11: All categories consulted with records | J11: One category missing | K11: Two or three categories missing | L11: Little or no documented consultation | P11: % | Q11: 5 | T11: =IF(OR(S11="",R11="",R11=0),"",ROUND(Q11*MIN(S11/R11,1),2)) | U11: =IF(T11="","",ROUND(T11/Q11*100,2)) | V11: =IF(U11="","",IF(U11>YT*100,"Y",IF(U11>=CT*100,"C",IF(U11>=WT*100,"W","D")))) | W11: =IF($V11="Y",1,"") | X11: =IF($V11="C",1,"") | Y11: =IF($V11="W",1,"") | Z11: =IF($V11="D",1,"")
A12: 1.1.d | B12: Stakeholder survey responses (1.1.3) | C12: Stakeholder survey responses | D12: Response traceable to a named respondent (form export with timestamp/email) | E12: Survey responses | F12: 0.1 | G12: 10 | H12: Random responses from raw survey export; call 2 respondents | I12: Responses meet target, all traceable | J12: Slightly below target; traceable | K12: Well below target or partly untraceable | L12: Responses not traceable or survey not done | P12: % | Q12: 5 | T12: =IF(OR(S12="",R12="",R12=0),"",ROUND(Q12*MIN(S12/R12,1),2)) | U12: =IF(T12="","",ROUND(T12/Q12*100,2)) | V12: =IF(U12="","",IF(U12>YT*100,"Y",IF(U12>=CT*100,"C",IF(U12>=WT*100,"W","D")))) | W12: =IF($V12="Y",1,"") | X12: =IF($V12="C",1,"") | Y12: =IF($V12="W",1,"") | Z12: =IF($V12="D",1,"")
A13: 1.1.e | B13: Dissemination points (1.1.4) | C13: Dissemination points | D13: V/M/PEOs physically displayed or published at the location | E13: Locations | F13: 1 | G13: 6 | H13: Walk-through of website, dept, labs, classrooms; open course files and handbook | I13: Displayed at all required points | J13: Missing at one point | K13: Missing at several points | L13: Not displayed | P13: % | Q13: 2 | T13: =IF(OR(S13="",R13="",R13=0),"",ROUND(Q13*MIN(S13/R13,1),2)) | U13: =IF(T13="","",ROUND(T13/Q13*100,2)) | V13: =IF(U13="","",IF(U13>YT*100,"Y",IF(U13>=CT*100,"C",IF(U13>=WT*100,"W","D")))) | W13: =IF($V13="Y",1,"") | X13: =IF($V13="C",1,"") | Y13: =IF($V13="W",1,"") | Z13: =IF($V13="D",1,"")
A14: 1.1.f | B14: Stakeholder awareness (1.1.4) | C14: Stakeholder awareness | D14: Student correctly states the gist of Vision, Mission and at least one PEO | E14: Students | F14: 0.05 | G14: 10 | H14: Interview random students across years during physical audit | I14: Most students aware | J14: Majority aware | K14: About half aware | L14: Few aware | P14: % | Q14: 3 | T14: =IF(OR(S14="",R14="",R14=0),"",ROUND(Q14*MIN(S14/R14,1),2)) | U14: =IF(T14="","",ROUND(T14/Q14*100,2)) | V14: =IF(U14="","",IF(U14>YT*100,"Y",IF(U14>=CT*100,"C",IF(U14>=WT*100,"W","D")))) | W14: =IF($V14="Y",1,"") | X14: =IF($V14="C",1,"") | Y14: =IF($V14="W",1,"") | Z14: =IF($V14="D",1,"")
A15: 1.1.g | B15: PEO-Mission mapping completeness (1.1.5) | C15: PEO-Mission mapping completeness | D15: Mapping cell filled with correlation level and written justification | E15: Mapping cells | F15: 0.25 | G15: 5 | H15: Random cells from PEO-Mission matrix | I15: All cells filled and justified | J15: Filled; justification thin in a few | K15: Several cells blank or unjustified | L15: Matrix absent | P15: % | Q15: 5 | T15: =IF(OR(S15="",R15="",R15=0),"",ROUND(Q15*MIN(S15/R15,1),2)) | U15: =IF(T15="","",ROUND(T15/Q15*100,2)) | V15: =IF(U15="","",IF(U15>YT*100,"Y",IF(U15>=CT*100,"C",IF(U15>=WT*100,"W","D")))) | W15: =IF($V15="Y",1,"") | X15: =IF($V15="C",1,"") | Y15: =IF($V15="W",1,"") | Z15: =IF($V15="D",1,"")
A16: 1.1.h | B16: PEO-Mission correlation strength (1.1.5) | C16: PEO-Mission correlation strength | D16: PEO has a strong (3) correlation that the justification supports | E16: PEOs | F16: 1 | G16: 3 | H16: Check every PEO | I16: All PEOs strongly mapped with sound justification | J16: Most strongly mapped | K16: Mostly weak correlations | L16: No strong correlations or unjustified | P16: % | Q16: 5 | T16: =IF(OR(S16="",R16="",R16=0),"",ROUND(Q16*MIN(S16/R16,1),2)) | U16: =IF(T16="","",ROUND(T16/Q16*100,2)) | V16: =IF(U16="","",IF(U16>YT*100,"Y",IF(U16>=CT*100,"C",IF(U16>=WT*100,"W","D")))) | W16: =IF($V16="Y",1,"") | X16: =IF($V16="C",1,"") | Y16: =IF($V16="W",1,"") | Z16: =IF($V16="D",1,"")
A17: 1.2 | B17: Curriculum structure and features | Q17: =SUM(Q18:Q24) -> 30 | T17: =SUM(T18:T24) -> 0 | U17: =IF(COUNT(T18:T24)=0,"",ROUND(T17/Q17*100,2)) | V17: =IF(U17="","",IF(U17>YT*100,"Y",IF(U17>=CT*100,"C",IF(U17>=WT*100,"W","D")))) | W17: =SUM(W18:W24) -> 0 | X17: =SUM(X18:X24) -> 0 | Y17: =SUM(Y18:Y24) -> 0 | Z17: =SUM(Z18:Z24) -> 0
A18: 1.2.a | B18: Curriculum feedback collected and analysed (1.2.1) | C18: Curriculum feedback analysed | D18: Feedback raw data + analysis report + BoS discussion for the category | E18: Stakeholder categories | F18: 1 | G18: 4 | H18: Check all 4 categories (students, alumni, employers, faculty) | I18: All categories analysed and discussed at BoS | J18: Analysed; BoS discussion partial | K18: Collected but not analysed | L18: Not collected | P18: % | Q18: 5 | T18: =IF(OR(S18="",R18="",R18=0),"",ROUND(Q18*MIN(S18/R18,1),2)) | U18: =IF(T18="","",ROUND(T18/Q18*100,2)) | V18: =IF(U18="","",IF(U18>YT*100,"Y",IF(U18>=CT*100,"C",IF(U18>=WT*100,"W","D")))) | W18: =IF($V18="Y",1,"") | X18: =IF($V18="C",1,"") | Y18: =IF($V18="W",1,"") | Z18: =IF($V18="D",1,"")
A19: 1.2.b | B19: Curriculum gaps addressed (1.2.1) | C19: Curriculum gaps addressed | D19: Gap has BoS revision or content-beyond-syllabus record with attendance | E19: Gaps | F19: 0.5 | G19: 3 | H19: Random gaps from the gap analysis register | I19: All sampled gaps closed with proof | J19: Most closed | K19: About half closed | L19: Few or none closed | P19: % | Q19: 5 | T19: =IF(OR(S19="",R19="",R19=0),"",ROUND(Q19*MIN(S19/R19,1),2)) | U19: =IF(T19="","",ROUND(T19/Q19*100,2)) | V19: =IF(U19="","",IF(U19>YT*100,"Y",IF(U19>=CT*100,"C",IF(U19>=WT*100,"W","D")))) | W19: =IF($V19="Y",1,"") | X19: =IF($V19="C",1,"") | Y19: =IF($V19="W",1,"") | Z19: =IF($V19="D",1,"")
A20: 1.2.c | B20: Complete syllabi (1.2.2) | C20: Complete syllabi | D20: Syllabus has COs, unit content, hours, text and reference books | E20: Courses | F20: 0.2 | G20: 5 | H20: Random courses across semesters incl. electives and labs | I20: All complete | J20: Minor elements missing in a few | K20: Several incomplete | L20: Syllabi largely incomplete | P20: % | Q20: 5 | T20: =IF(OR(S20="",R20="",R20=0),"",ROUND(Q20*MIN(S20/R20,1),2)) | U20: =IF(T20="","",ROUND(T20/Q20*100,2)) | V20: =IF(U20="","",IF(U20>YT*100,"Y",IF(U20>=CT*100,"C",IF(U20>=WT*100,"W","D")))) | W20: =IF($V20="Y",1,"") | X20: =IF($V20="C",1,"") | Y20: =IF($V20="W",1,"") | Z20: =IF($V20="D",1,"")
A21: 1.2.d | B21: Credit compliance (1.2.2) | C21: Credit compliance | D21: Semester credits within university/AICTE norm as per approved scheme | E21: Semesters | F21: 1 | G21: 8 | H21: Check every semester in approved curriculum | I21: All semesters compliant | J21: One semester marginally off | K21: Several semesters off | L21: Scheme not compliant | P21: % | Q21: 5 | T21: =IF(OR(S21="",R21="",R21=0),"",ROUND(Q21*MIN(S21/R21,1),2)) | U21: =IF(T21="","",ROUND(T21/Q21*100,2)) | V21: =IF(U21="","",IF(U21>YT*100,"Y",IF(U21>=CT*100,"C",IF(U21>=WT*100,"W","D")))) | W21: =IF($V21="Y",1,"") | X21: =IF($V21="C",1,"") | Y21: =IF($V21="W",1,"") | Z21: =IF($V21="D",1,"")
A22: 1.2.e | B22: Curriculum components within AICTE range (1.2.3) | C22: Curriculum components in AICTE range | D22: Category credits within AICTE range in approved scheme | E22: Categories | F22: 1 | G22: 7 | H22: Check all 7 categories (BS, ES, HSS, PC, PE, OE, Project) | I22: All 7 within range | J22: 6 within range | K22: 4-5 within range | L22: Fewer than 4 within range | P22: % | Q22: 5 | T22: =IF(OR(S22="",R22="",R22=0),"",ROUND(Q22*MIN(S22/R22,1),2)) | U22: =IF(T22="","",ROUND(T22/Q22*100,2)) | V22: =IF(U22="","",IF(U22>YT*100,"Y",IF(U22>=CT*100,"C",IF(U22>=WT*100,"W","D")))) | W22: =IF($V22="Y",1,"") | X22: =IF($V22="C",1,"") | Y22: =IF($V22="W",1,"") | Z22: =IF($V22="D",1,"")
A23: 1.2.f | B23: Interdisciplinary / honours / minor options (1.2.4) | C23: Interdisciplinary / honours / minor options | D23: Option approved by BoS/AC with student enrolment record | E23: Options (count) | F23: 1 | G23: 3 | H23: Verify every claimed option | I23: Meets benchmark, enrolments verified | J23: Slightly below benchmark | K23: Well below benchmark | L23: None offered | P23: No. | Q23: 2 | T23: =IF(OR(S23="",R23="",R23=0),"",ROUND(Q23*MIN(S23/R23,1),2)) | U23: =IF(T23="","",ROUND(T23/Q23*100,2)) | V23: =IF(U23="","",IF(U23>YT*100,"Y",IF(U23>=CT*100,"C",IF(U23>=WT*100,"W","D")))) | W23: =IF($V23="Y",1,"") | X23: =IF($V23="C",1,"") | Y23: =IF($V23="W",1,"") | Z23: =IF($V23="D",1,"")
A24: 1.2.g | B24: Academic Bank of Credits registration (1.2.4) | C24: ABC registration | D24: ABC ID verifiable on the ABC/DigiLocker list for the student | E24: Students | F24: 0.1 | G24: 10 | H24: Random students from roll list; match with ABC portal export | I24: All sampled students registered | J24: Most registered | K24: About half registered | L24: Few registered | P24: % | Q24: 3 | T24: =IF(OR(S24="",R24="",R24=0),"",ROUND(Q24*MIN(S24/R24,1),2)) | U24: =IF(T24="","",ROUND(T24/Q24*100,2)) | V24: =IF(U24="","",IF(U24>YT*100,"Y",IF(U24>=CT*100,"C",IF(U24>=WT*100,"W","D")))) | W24: =IF($V24="Y",1,"") | X24: =IF($V24="C",1,"") | Y24: =IF($V24="W",1,"") | Z24: =IF($V24="D",1,"")
A25: 1.3 | B25: Mapping of POs and PSOs | Q25: =SUM(Q26:Q28) -> 20 | T25: =SUM(T26:T28) -> 0 | U25: =IF(COUNT(T26:T28)=0,"",ROUND(T25/Q25*100,2)) | V25: =IF(U25="","",IF(U25>YT*100,"Y",IF(U25>=CT*100,"C",IF(U25>=WT*100,"W","D")))) | W25: =SUM(W26:W28) -> 0 | X25: =SUM(X26:X28) -> 0 | Y25: =SUM(Y26:Y28) -> 0 | Z25: =SUM(Z26:Z28) -> 0
A26: 1.3.a | B26: PSOs defined and approved (1.3.1) | C26: PSOs defined and approved | D26: PSO approved in signed BoS/DAB minutes | E26: PSOs | F26: 1 | G26: 2 | H26: Check every PSO | I26: All PSOs approved and programme-specific | J26: Approved; wording generic | K26: Partly approved | L26: Not approved | P26: % | Q26: 5 | T26: =IF(OR(S26="",R26="",R26=0),"",ROUND(Q26*MIN(S26/R26,1),2)) | U26: =IF(T26="","",ROUND(T26/Q26*100,2)) | V26: =IF(U26="","",IF(U26>YT*100,"Y",IF(U26>=CT*100,"C",IF(U26>=WT*100,"W","D")))) | W26: =IF($V26="Y",1,"") | X26: =IF($V26="C",1,"") | Y26: =IF($V26="W",1,"") | Z26: =IF($V26="D",1,"")
A27: 1.3.b | B27: Courses mapped to POs/PSOs (1.3.2) | C27: Courses mapped to POs/PSOs | D27: Course has CO-PO/PSO mapping table in course file | E27: Courses | F27: 0.2 | G27: 5 | H27: Random courses across all semesters | I27: All mapped | J27: Most mapped | K27: About half mapped | L27: Few or none | P27: % | Q27: 8 | T27: =IF(OR(S27="",R27="",R27=0),"",ROUND(Q27*MIN(S27/R27,1),2)) | U27: =IF(T27="","",ROUND(T27/Q27*100,2)) | V27: =IF(U27="","",IF(U27>YT*100,"Y",IF(U27>=CT*100,"C",IF(U27>=WT*100,"W","D")))) | W27: =IF($V27="Y",1,"") | X27: =IF($V27="C",1,"") | Y27: =IF($V27="W",1,"") | Z27: =IF($V27="D",1,"")
A28: 1.3.c | B28: Justified mappings (1.3.2) | C28: Justified mappings | D28: Each correlation level in the mapping has written justification | E28: Mapped courses | F28: 0.2 | G28: 5 | H28: Same courses as 1.3.b | I28: All justified and consistent | J28: Most justified | K28: Justification weak or generic | L28: No justification | P28: % | Q28: 7 | T28: =IF(OR(S28="",R28="",R28=0),"",ROUND(Q28*MIN(S28/R28,1),2)) | U28: =IF(T28="","",ROUND(T28/Q28*100,2)) | V28: =IF(U28="","",IF(U28>YT*100,"Y",IF(U28>=CT*100,"C",IF(U28>=WT*100,"W","D")))) | W28: =IF($V28="Y",1,"") | X28: =IF($V28="C",1,"") | Y28: =IF($V28="W",1,"") | Z28: =IF($V28="D",1,"")
A29: 1.4 | B29: Course Outcomes and Course Articulation Matrix | Q29: =SUM(Q30:Q34) -> 30 | T29: =SUM(T30:T34) -> 0 | U29: =IF(COUNT(T30:T34)=0,"",ROUND(T29/Q29*100,2)) | V29: =IF(U29="","",IF(U29>YT*100,"Y",IF(U29>=CT*100,"C",IF(U29>=WT*100,"W","D")))) | W29: =SUM(W30:W34) -> 0 | X29: =SUM(X30:X34) -> 0 | Y29: =SUM(Y30:Y34) -> 0 | Z29: =SUM(Z30:Z34) -> 0
A30: 1.4.a | B30: Courses with COs defined (1.4.1) | C30: Courses with COs defined | D30: Course file lists 4-6 COs approved by course committee | E30: Courses | F30: 0.2 | G30: 5 | H30: Random courses offered in the period | I30: All courses have COs | J30: Most have COs | K30: About half | L30: Few or none | P30: % | Q30: 5 | T30: =IF(OR(S30="",R30="",R30=0),"",ROUND(Q30*MIN(S30/R30,1),2)) | U30: =IF(T30="","",ROUND(T30/Q30*100,2)) | V30: =IF(U30="","",IF(U30>YT*100,"Y",IF(U30>=CT*100,"C",IF(U30>=WT*100,"W","D")))) | W30: =IF($V30="Y",1,"") | X30: =IF($V30="C",1,"") | Y30: =IF($V30="W",1,"") | Z30: =IF($V30="D",1,"")
A31: 1.4.b | B31: Measurable COs (1.4.1) | C31: Measurable COs | D31: CO starts with action verb and states Bloom level | E31: COs | F31: 0.1 | G31: 15 | H31: Random COs from sampled courses | I31: All measurable | J31: Most measurable | K31: About half | L31: Mostly vague | P31: % | Q31: 5 | T31: =IF(OR(S31="",R31="",R31=0),"",ROUND(Q31*MIN(S31/R31,1),2)) | U31: =IF(T31="","",ROUND(T31/Q31*100,2)) | V31: =IF(U31="","",IF(U31>YT*100,"Y",IF(U31>=CT*100,"C",IF(U31>=WT*100,"W","D")))) | W31: =IF($V31="Y",1,"") | X31: =IF($V31="C",1,"") | Y31: =IF($V31="W",1,"") | Z31: =IF($V31="D",1,"")
A32: 1.4.c | B32: Higher-order COs (1.4.1) | C32: Higher-order COs | D32: Course has at least one CO at Apply level or above, assessed in CA | E32: Courses | F32: 0.2 | G32: 5 | H32: Same courses as 1.4.a | I32: All courses have higher-order COs | J32: Most | K32: About half | L32: Few or none | P32: % | Q32: 5 | T32: =IF(OR(S32="",R32="",R32=0),"",ROUND(Q32*MIN(S32/R32,1),2)) | U32: =IF(T32="","",ROUND(T32/Q32*100,2)) | V32: =IF(U32="","",IF(U32>YT*100,"Y",IF(U32>=CT*100,"C",IF(U32>=WT*100,"W","D")))) | W32: =IF($V32="Y",1,"") | X32: =IF($V32="C",1,"") | Y32: =IF($V32="W",1,"") | Z32: =IF($V32="D",1,"")
A33: 1.4.d | B33: Course Articulation Matrix prepared (1.4.2) | C33: Course Articulation Matrix prepared | D33: CAM present in course file and approved | E33: Courses | F33: 0.2 | G33: 5 | H33: Random courses | I33: All have CAM | J33: Most have CAM | K33: About half | L33: Few or none | P33: % | Q33: 8 | T33: =IF(OR(S33="",R33="",R33=0),"",ROUND(Q33*MIN(S33/R33,1),2)) | U33: =IF(T33="","",ROUND(T33/Q33*100,2)) | V33: =IF(U33="","",IF(U33>YT*100,"Y",IF(U33>=CT*100,"C",IF(U33>=WT*100,"W","D")))) | W33: =IF($V33="Y",1,"") | X33: =IF($V33="C",1,"") | Y33: =IF($V33="W",1,"") | Z33: =IF($V33="D",1,"")
A34: 1.4.e | B34: CAM correlations justified (1.4.2) | C34: CAM correlations justified | D34: Every correlation in the CAM has justification | E34: CAMs | F34: 0.2 | G34: 5 | H34: Random CAMs from 1.4.d sample | I34: All justified | J34: Most justified | K34: Partly justified | L34: Not justified | P34: % | Q34: 7 | T34: =IF(OR(S34="",R34="",R34=0),"",ROUND(Q34*MIN(S34/R34,1),2)) | U34: =IF(T34="","",ROUND(T34/Q34*100,2)) | V34: =IF(U34="","",IF(U34>YT*100,"Y",IF(U34>=CT*100,"C",IF(U34>=WT*100,"W","D")))) | W34: =IF($V34="Y",1,"") | X34: =IF($V34="C",1,"") | Y34: =IF($V34="W",1,"") | Z34: =IF($V34="D",1,"")
A35: 1.5 | B35: Programme Articulation Matrix | Q35: =SUM(Q36:Q37) -> 5 | T35: =SUM(T36:T37) -> 0 | U35: =IF(COUNT(T36:T37)=0,"",ROUND(T35/Q35*100,2)) | V35: =IF(U35="","",IF(U35>YT*100,"Y",IF(U35>=CT*100,"C",IF(U35>=WT*100,"W","D")))) | W35: =SUM(W36:W37) -> 0 | X35: =SUM(X36:X37) -> 0 | Y35: =SUM(Y36:Y37) -> 0 | Z35: =SUM(Z36:Z37) -> 0
A36: 1.5.a | B36: PAM derived from CAMs | C36: PAM derived from CAMs | D36: PAM value recomputed by auditor matches the sheet (within 0.1) | E36: POs/PSOs | F36: 0.5 | G36: 5 | H36: Recompute PAM for random POs/PSOs from CAMs | I36: All recomputed values match | J36: Minor deviations | K36: Several mismatches | L36: PAM not derived from CAMs | P36: % | Q36: 3 | T36: =IF(OR(S36="",R36="",R36=0),"",ROUND(Q36*MIN(S36/R36,1),2)) | U36: =IF(T36="","",ROUND(T36/Q36*100,2)) | V36: =IF(U36="","",IF(U36>YT*100,"Y",IF(U36>=CT*100,"C",IF(U36>=WT*100,"W","D")))) | W36: =IF($V36="Y",1,"") | X36: =IF($V36="C",1,"") | Y36: =IF($V36="W",1,"") | Z36: =IF($V36="D",1,"")
A37: 1.5.b | B37: PO/PSO coverage | C37: PO/PSO coverage | D37: PO/PSO addressed by at least N courses in PAM | E37: POs/PSOs | F37: 1 | G37: 12 | H37: Check all POs and PSOs in PAM | I37: All POs/PSOs adequately covered | J37: One or two thinly covered | K37: Several thinly covered | L37: Many POs/PSOs uncovered | P37: % | Q37: 2 | T37: =IF(OR(S37="",R37="",R37=0),"",ROUND(Q37*MIN(S37/R37,1),2)) | U37: =IF(T37="","",ROUND(T37/Q37*100,2)) | V37: =IF(U37="","",IF(U37>YT*100,"Y",IF(U37>=CT*100,"C",IF(U37>=WT*100,"W","D")))) | W37: =IF($V37="Y",1,"") | X37: =IF($V37="C",1,"") | Y37: =IF($V37="W",1,"") | Z37: =IF($V37="D",1,"")
A38: C1 | B38: CRITERION 1 TOTAL | Q38: =Q8+Q17+Q25+Q29+Q35 -> 120 | T38: =T8+T17+T25+T29+T35 -> 0 | U38: =IF(T38=0,"",ROUND(T38/Q38*100,2)) | V38: =IF(U38="","",IF(U38>YT*100,"Y",IF(U38>=CT*100,"C",IF(U38>=WT*100,"W","D")))) | W38: =W8+W17+W25+W29+W35 -> 0 | X38: =X8+X17+X25+X29+X35 -> 0 | Y38: =Y8+Y17+Y25+Y29+Y35 -> 0 | Z38: =Z8+Z17+Z25+Z29+Z35 -> 0

Sheet C2 Validation Rubrics
A1: CRITERION 2 - VALIDATION RUBRICS AND SAMPLE SIZES (physical audit)
A2: Sampling: check at least the Sample % of the population, but never fewer than the Minimum (check all items if the population is smaller). Sample % and Minimum are defaults - IQAC may change them.
A3: For % indicators: Validated value = Valid items / Items checked x 100. For count indicators: Validated value = number of claimed items found valid.
A4: Enter the Benchmark (col R) and Validated value (col S) here. Marks, Percentage and Grade (Y > 75, C 60-75, W 40-60, D < 40) are calculated automatically and flow to the C2 Quantitative and All Criteria tabs.
A5: Yellow/blue = input: Items checked, Valid items, Auditor remarks, Benchmark, Validated value (and Sample % / Minimum if IQAC changes them).
A7: Code | B7: Key aspect | C7: What the auditor verifies | D7: An item counts as valid only if | E7: Sampling unit | F7: Sample % | G7: Minimum sample | H7: How to sample | I7: Y (> 75%) | J7: C (60-75%) | K7: W (40-60%) | L7: D (< 40%) | M7: Items checked | N7: Valid items | O7: Auditor remarks | P7: Unit | Q7: Max marks | R7: Benchmark | S7: Validated value | T7: Marks obtained | U7: Percentage | V7: Grade | W7: Y | X7: C | Y7: W | Z7: D
A8: 2.1 | B8: Quality of teaching-learning processes | Q8: =SUM(Q9:Q13) -> 20 | T8: =SUM(T9:T13) -> 2.67 | U8: =IF(COUNT(T9:T13)=0,"",ROUND(T8/Q8*100,2)) -> 13.35 | V8: =IF(U8="","",IF(U8>YT*100,"Y",IF(U8>=CT*100,"C",IF(U8>=WT*100,"W","D")))) -> D | W8: =SUM(W9:W13) -> 0 | X8: =SUM(X9:X13) -> 1 | Y8: =SUM(Y9:Y13) -> 0 | Z8: =SUM(Z9:Z13) -> 0
A9: 2.1.a | B9: Course files complete before semester start | C9: Completeness of course files before semester start | D9: File has lesson plan, COs, CAM, timetable and dated upload before semester start | E9: Courses | F9: 0.25 | G9: 3 | H9: Random draw across all years; include at least 1 lab course | I9: All components present, dated before start, signed by HoD | J9: Minor component missing in a few files (e.g. CAM unsigned) | K9: Several files missing CAM or lesson plan; late uploads | L9: Files absent or prepared after semester start | P9: % | Q9: 4 | R9: 3 | S9: 2 | T9: =IF(OR(S9="",R9="",R9=0),"",ROUND(Q9*MIN(S9/R9,1),2)) -> 2.67 | U9: =IF(T9="","",ROUND(T9/Q9*100,2)) -> 66.75 | V9: =IF(U9="","",IF(U9>YT*100,"Y",IF(U9>=CT*100,"C",IF(U9>=WT*100,"W","D")))) -> C | W9: =IF($V9="Y",1,"") | X9: =IF($V9="C",1,"") -> 1 | Y9: =IF($V9="W",1,"") | Z9: =IF($V9="D",1,"")
A10: 2.1.b | B10: Syllabus coverage as per lesson plan | C10: Syllabus coverage vs lesson plan | D10: Topics in log book match lesson plan to audit date (lag <= 1 week) | E10: Courses | F10: 0.25 | G10: 3 | H10: Same courses as 2.1.a; compare log book, attendance and lesson plan | I10: On schedule or ahead; log book tallies with attendance | J10: Lag 1-2 weeks with documented recovery plan | K10: Lag 2-3 weeks; no recovery plan | L10: Lag beyond 3 weeks or log book not maintained | P10: % | Q10: 4 | T10: =IF(OR(S10="",R10="",R10=0),"",ROUND(Q10*MIN(S10/R10,1),2)) | U10: =IF(T10="","",ROUND(T10/Q10*100,2)) | V10: =IF(U10="","",IF(U10>YT*100,"Y",IF(U10>=CT*100,"C",IF(U10>=WT*100,"W","D")))) | W10: =IF($V10="Y",1,"") | X10: =IF($V10="C",1,"") | Y10: =IF($V10="W",1,"") | Z10: =IF($V10="D",1,"")
A11: 2.1.c | B11: Classes conducted vs scheduled | C11: Classes conducted vs timetabled | D11: Hours in attendance register equal timetabled hours (missed hours compensated) | E11: Course-weeks | F11: 0.1 | G11: 4 | H11: Pick 1 random week for each sampled course | I11: All scheduled hours held or compensated | J11: Up to 10% hours missed, partly compensated | K11: 10-25% hours missed | L11: Over 25% hours missed or registers incomplete | P11: % | Q11: 4 | T11: =IF(OR(S11="",R11="",R11=0),"",ROUND(Q11*MIN(S11/R11,1),2)) | U11: =IF(T11="","",ROUND(T11/Q11*100,2)) | V11: =IF(U11="","",IF(U11>YT*100,"Y",IF(U11>=CT*100,"C",IF(U11>=WT*100,"W","D")))) | W11: =IF($V11="Y",1,"") | X11: =IF($V11="C",1,"") | Y11: =IF($V11="W",1,"") | Z11: =IF($V11="D",1,"")
A12: 2.1.d | B12: Courses using active learning / ICT | C12: Use of active learning / ICT | D12: Documented session (plan + photo/LMS link + student work) in the course | E12: Courses | F12: 0.25 | G12: 3 | H12: Random courses; observe 1 live class during physical audit | I12: Regular, documented active learning in most units; observed in class | J12: Used in some units with evidence | K12: Occasional; evidence weak | L12: Not evident; chalk-and-talk only | P12: % | Q12: 4 | T12: =IF(OR(S12="",R12="",R12=0),"",ROUND(Q12*MIN(S12/R12,1),2)) | U12: =IF(T12="","",ROUND(T12/Q12*100,2)) | V12: =IF(U12="","",IF(U12>YT*100,"Y",IF(U12>=CT*100,"C",IF(U12>=WT*100,"W","D")))) | W12: =IF($V12="Y",1,"") | X12: =IF($V12="C",1,"") | Y12: =IF($V12="W",1,"") | Z12: =IF($V12="D",1,"")
A13: 2.1.e | B13: Student feedback on teaching | C13: Student feedback on teaching | D13: Feedback collected from >= 60% of class and analysed course-wise | E13: Courses | F13: 0.25 | G13: 3 | H13: Cross-check feedback report against raw responses for sampled courses | I13: High scores, analysis done, actions recorded | J13: Moderate scores, analysis done | K13: Low scores or analysis partial | L13: Feedback not collected or not analysed | P13: % | Q13: 4 | T13: =IF(OR(S13="",R13="",R13=0),"",ROUND(Q13*MIN(S13/R13,1),2)) | U13: =IF(T13="","",ROUND(T13/Q13*100,2)) | V13: =IF(U13="","",IF(U13>YT*100,"Y",IF(U13>=CT*100,"C",IF(U13>=WT*100,"W","D")))) | W13: =IF($V13="Y",1,"") | X13: =IF($V13="C",1,"") | Y13: =IF($V13="W",1,"") | Z13: =IF($V13="D",1,"")
A14: 2.2 | B14: Quality of capstone project | Q14: =SUM(Q15:Q19) -> 25 | T14: =SUM(T15:T19) -> 0 | U14: =IF(COUNT(T15:T19)=0,"",ROUND(T14/Q14*100,2)) | V14: =IF(U14="","",IF(U14>YT*100,"Y",IF(U14>=CT*100,"C",IF(U14>=WT*100,"W","D")))) | W14: =SUM(W15:W19) -> 0 | X14: =SUM(X15:X19) -> 0 | Y14: =SUM(Y15:Y19) -> 0 | Z14: =SUM(Z15:Z19) -> 0
A15: 2.2.a | B15: Projects mapped to POs/PSOs | C15: Projects mapped to POs/PSOs | D15: Each project has PO/PSO mapping with justification in project file | E15: Projects | F15: 0.2 | G15: 5 | H15: Random projects across guides | I15: All sampled projects mapped and justified | J15: Mapped, justification thin | K15: Mapping partial | L15: No mapping | P15: % | Q15: 5 | T15: =IF(OR(S15="",R15="",R15=0),"",ROUND(Q15*MIN(S15/R15,1),2)) | U15: =IF(T15="","",ROUND(T15/Q15*100,2)) | V15: =IF(U15="","",IF(U15>YT*100,"Y",IF(U15>=CT*100,"C",IF(U15>=WT*100,"W","D")))) | W15: =IF($V15="Y",1,"") | X15: =IF($V15="C",1,"") | Y15: =IF($V15="W",1,"") | Z15: =IF($V15="D",1,"")
A16: 2.2.b | B16: Industry / research-linked projects | C16: Industry / research linkage | D16: Signed letter from industry or linked to funded/lab research | E16: Projects | F16: 0.2 | G16: 5 | H16: Prefer projects claimed as industry-linked | I16: Strong linkage with sponsor involvement | J16: Linkage documented, limited involvement | K16: Claimed linkage, weak proof | L16: No valid proof | P16: % | Q16: 5 | T16: =IF(OR(S16="",R16="",R16=0),"",ROUND(Q16*MIN(S16/R16,1),2)) | U16: =IF(T16="","",ROUND(T16/Q16*100,2)) | V16: =IF(U16="","",IF(U16>YT*100,"Y",IF(U16>=CT*100,"C",IF(U16>=WT*100,"W","D")))) | W16: =IF($V16="Y",1,"") | X16: =IF($V16="C",1,"") | Y16: =IF($V16="W",1,"") | Z16: =IF($V16="D",1,"")
A17: 2.2.c | B17: Projects with tangible outcome | C17: Tangible outcomes | D17: Paper/patent/prototype/award with verifiable proof (DOI, filing no., demo) | E17: Projects | F17: 0.2 | G17: 5 | H17: Sample from claimed outcome list; see 2 prototypes working | I17: Outcomes verified, prototypes working | J17: Most outcomes verified | K17: Few outcomes verifiable | L17: Outcomes not verifiable | P17: % | Q17: 5 | T17: =IF(OR(S17="",R17="",R17=0),"",ROUND(Q17*MIN(S17/R17,1),2)) | U17: =IF(T17="","",ROUND(T17/Q17*100,2)) | V17: =IF(U17="","",IF(U17>YT*100,"Y",IF(U17>=CT*100,"C",IF(U17>=WT*100,"W","D")))) | W17: =IF($V17="Y",1,"") | X17: =IF($V17="C",1,"") | Y17: =IF($V17="W",1,"") | Z17: =IF($V17="D",1,"")
A18: 2.2.d | B18: Rubric-based reviews on schedule | C18: Rubric-based reviews | D18: At least 3 dated reviews with rubric score sheets signed by panel | E18: Projects | F18: 0.2 | G18: 5 | H18: Random projects; check review registers | I18: All reviews on schedule with rubrics | J18: One review late or rubric partly filled | K18: Fewer than 3 reviews | L18: No rubric-based reviews | P18: % | Q18: 5 | T18: =IF(OR(S18="",R18="",R18=0),"",ROUND(Q18*MIN(S18/R18,1),2)) | U18: =IF(T18="","",ROUND(T18/Q18*100,2)) | V18: =IF(U18="","",IF(U18>YT*100,"Y",IF(U18>=CT*100,"C",IF(U18>=WT*100,"W","D")))) | W18: =IF($V18="Y",1,"") | X18: =IF($V18="C",1,"") | Y18: =IF($V18="W",1,"") | Z18: =IF($V18="D",1,"")
A19: 2.2.e | B19: Interdisciplinary / SDG-linked projects | C19: Interdisciplinary / SDG linkage | D19: Team or problem spans 2+ disciplines or mapped to a named SDG with rationale | E19: Projects | F19: 0.2 | G19: 5 | H19: Random projects | I19: Clear interdisciplinary/SDG design | J19: Linkage present, rationale weak | K19: Token linkage | L19: None | P19: % | Q19: 5 | T19: =IF(OR(S19="",R19="",R19=0),"",ROUND(Q19*MIN(S19/R19,1),2)) | U19: =IF(T19="","",ROUND(T19/Q19*100,2)) | V19: =IF(U19="","",IF(U19>YT*100,"Y",IF(U19>=CT*100,"C",IF(U19>=WT*100,"W","D")))) | W19: =IF($V19="Y",1,"") | X19: =IF($V19="C",1,"") | Y19: =IF($V19="W",1,"") | Z19: =IF($V19="D",1,"")
A20: 2.3 | B20: Internship and industrial training | Q20: =SUM(Q21:Q23) -> 10 | T20: =SUM(T21:T23) -> 1 | U20: =IF(COUNT(T21:T23)=0,"",ROUND(T20/Q20*100,2)) -> 10 | V20: =IF(U20="","",IF(U20>YT*100,"Y",IF(U20>=CT*100,"C",IF(U20>=WT*100,"W","D")))) -> D | W20: =SUM(W21:W23) -> 0 | X20: =SUM(X21:X23) -> 0 | Y20: =SUM(Y21:Y23) -> 1 | Z20: =SUM(Z21:Z23) -> 0
A21: 2.3.a | B21: Internship completion | C21: Internship completion | D21: Completion certificate + report + attendance for required duration | E21: Students | F21: 0.1 | G21: 10 | H21: Random students from eligible list | I21: All sampled students completed with full proof | J21: Minor gaps (e.g. report missing) | K21: Several without certificate or short duration | L21: Most not completed | P21: % | Q21: 5 | T21: =IF(OR(S21="",R21="",R21=0),"",ROUND(Q21*MIN(S21/R21,1),2)) | U21: =IF(T21="","",ROUND(T21/Q21*100,2)) | V21: =IF(U21="","",IF(U21>YT*100,"Y",IF(U21>=CT*100,"C",IF(U21>=WT*100,"W","D")))) | W21: =IF($V21="Y",1,"") | X21: =IF($V21="C",1,"") | Y21: =IF($V21="W",1,"") | Z21: =IF($V21="D",1,"")
A22: 2.3.b | B22: Quality of internship host | C22: Quality of internship host | D22: Host is registered industry/R&D organisation (verifiable GST/website/contact) | E22: Internships | F22: 0.1 | G22: 10 | H22: Random internships; call or email 2 hosts | I22: Reputed hosts, verified | J22: Mostly genuine hosts | K22: Many online / unverifiable hosts | L22: Hosts not verifiable | P22: % | Q22: 3 | T22: =IF(OR(S22="",R22="",R22=0),"",ROUND(Q22*MIN(S22/R22,1),2)) | U22: =IF(T22="","",ROUND(T22/Q22*100,2)) | V22: =IF(U22="","",IF(U22>YT*100,"Y",IF(U22>=CT*100,"C",IF(U22>=WT*100,"W","D")))) | W22: =IF($V22="Y",1,"") | X22: =IF($V22="C",1,"") | Y22: =IF($V22="W",1,"") | Z22: =IF($V22="D",1,"")
A23: 2.3.c | B23: Internship to stipend / PPO | C23: Stipend / PPO | D23: Stipend proof (bank/offer letter) or PPO letter | E23: Internships | F23: 0.1 | G23: 10 | H23: Sample from claimed stipend/PPO list | I23: All claims verified | J23: Most verified | K23: Few verified | L23: None verified | P23: % | Q23: 2 | R23: 2 | S23: 1 | T23: =IF(OR(S23="",R23="",R23=0),"",ROUND(Q23*MIN(S23/R23,1),2)) -> 1 | U23: =IF(T23="","",ROUND(T23/Q23*100,2)) -> 50 | V23: =IF(U23="","",IF(U23>YT*100,"Y",IF(U23>=CT*100,"C",IF(U23>=WT*100,"W","D")))) -> W | W23: =IF($V23="Y",1,"") | X23: =IF($V23="C",1,"") | Y23: =IF($V23="W",1,"") -> 1 | Z23: =IF($V23="D",1,"")
A24: 2.4 | B24: Seminar and mini/micro projects | Q24: =SUM(Q25:Q27) -> 10 | T24: =SUM(T25:T27) -> 0 | U24: =IF(COUNT(T25:T27)=0,"",ROUND(T24/Q24*100,2)) | V24: =IF(U24="","",IF(U24>YT*100,"Y",IF(U24>=CT*100,"C",IF(U24>=WT*100,"W","D")))) | W24: =SUM(W25:W27) -> 0 | X24: =SUM(X25:X27) -> 0 | Y24: =SUM(Y25:Y27) -> 0 | Z24: =SUM(Z25:Z27) -> 0
A25: 2.4.a | B25: Seminar participation | C25: Seminar participation | D25: Student presented with abstract, slides and rubric score | E25: Students | F25: 0.1 | G25: 10 | H25: Random students from roll list | I25: All sampled students presented and assessed | J25: Most presented | K25: About half presented | L25: Few or none | P25: % | Q25: 4 | T25: =IF(OR(S25="",R25="",R25=0),"",ROUND(Q25*MIN(S25/R25,1),2)) | U25: =IF(T25="","",ROUND(T25/Q25*100,2)) | V25: =IF(U25="","",IF(U25>YT*100,"Y",IF(U25>=CT*100,"C",IF(U25>=WT*100,"W","D")))) | W25: =IF($V25="Y",1,"") | X25: =IF($V25="C",1,"") | Y25: =IF($V25="W",1,"") | Z25: =IF($V25="D",1,"")
A26: 2.4.b | B26: Mini/micro-project completion | C26: Mini/micro-project completion | D26: Report + demo/working model or code repository | E26: Students | F26: 0.1 | G26: 10 | H26: Random students; see 2 demos | I26: All completed with working output | J26: Most completed | K26: About half completed | L26: Few or none | P26: % | Q26: 4 | T26: =IF(OR(S26="",R26="",R26=0),"",ROUND(Q26*MIN(S26/R26,1),2)) | U26: =IF(T26="","",ROUND(T26/Q26*100,2)) | V26: =IF(U26="","",IF(U26>YT*100,"Y",IF(U26>=CT*100,"C",IF(U26>=WT*100,"W","D")))) | W26: =IF($V26="Y",1,"") | X26: =IF($V26="C",1,"") | Y26: =IF($V26="W",1,"") | Z26: =IF($V26="D",1,"")
A27: 2.4.c | B27: Rubric-evaluated mini-projects | C27: Rubric evaluation of mini-projects | D27: Rubric sheet with criteria and marks, signed by evaluator | E27: Mini-projects | F27: 0.2 | G27: 5 | H27: Random mini-projects | I27: Rubrics used consistently | J27: Rubrics used, some incomplete | K27: Rubrics occasional | L27: No rubrics | P27: % | Q27: 2 | T27: =IF(OR(S27="",R27="",R27=0),"",ROUND(Q27*MIN(S27/R27,1),2)) | U27: =IF(T27="","",ROUND(T27/Q27*100,2)) | V27: =IF(U27="","",IF(U27>YT*100,"Y",IF(U27>=CT*100,"C",IF(U27>=WT*100,"W","D")))) | W27: =IF($V27="Y",1,"") | X27: =IF($V27="C",1,"") | Y27: =IF($V27="W",1,"") | Z27: =IF($V27="D",1,"")
A28: 2.5 | B28: Case studies and real-life examples | Q28: =SUM(Q29:Q31) -> 10 | T28: =SUM(T29:T31) -> 0 | U28: =IF(COUNT(T29:T31)=0,"",ROUND(T28/Q28*100,2)) | V28: =IF(U28="","",IF(U28>YT*100,"Y",IF(U28>=CT*100,"C",IF(U28>=WT*100,"W","D")))) | W28: =SUM(W29:W31) -> 0 | X28: =SUM(X29:X31) -> 0 | Y28: =SUM(Y29:Y31) -> 0 | Z28: =SUM(Z29:Z31) -> 0
A29: 2.5.a | B29: Courses using case studies | C29: Courses using case studies | D29: At least N case studies documented in course file with discussion record | E29: Theory courses | F29: 0.25 | G29: 3 | H29: Random theory courses | I29: Case studies embedded in most units | J29: N case studies met | K29: Fewer than N | L29: None | P29: % | Q29: 4 | T29: =IF(OR(S29="",R29="",R29=0),"",ROUND(Q29*MIN(S29/R29,1),2)) | U29: =IF(T29="","",ROUND(T29/Q29*100,2)) | V29: =IF(U29="","",IF(U29>YT*100,"Y",IF(U29>=CT*100,"C",IF(U29>=WT*100,"W","D")))) | W29: =IF($V29="Y",1,"") | X29: =IF($V29="C",1,"") | Y29: =IF($V29="W",1,"") | Z29: =IF($V29="D",1,"")
A30: 2.5.b | B30: Case-based assessment | C30: Case-based assessment | D30: Case-based question present in internal assessment papers | E30: Theory courses | F30: 0.25 | G30: 3 | H30: Check CA papers of sampled courses | I30: Case questions in every CA | J30: In most CAs | K30: In few CAs | L30: None | P30: % | Q30: 3 | T30: =IF(OR(S30="",R30="",R30=0),"",ROUND(Q30*MIN(S30/R30,1),2)) | U30: =IF(T30="","",ROUND(T30/Q30*100,2)) | V30: =IF(U30="","",IF(U30>YT*100,"Y",IF(U30>=CT*100,"C",IF(U30>=WT*100,"W","D")))) | W30: =IF($V30="Y",1,"") | X30: =IF($V30="C",1,"") | Y30: =IF($V30="W",1,"") | Z30: =IF($V30="D",1,"")
A31: 2.5.c | B31: Industry-led case sessions | C31: Industry-led case sessions | D31: Session report with expert details, attendance, photos | E31: Sessions (count) | F31: 1 | G31: 5 | H31: Verify every claimed session (or at least 5) | I31: Claims fully verified, meets benchmark | J31: Verified, slightly below benchmark | K31: Well below benchmark | L31: Little or no verified sessions | P31: No. | Q31: 3 | T31: =IF(OR(S31="",R31="",R31=0),"",ROUND(Q31*MIN(S31/R31,1),2)) | U31: =IF(T31="","",ROUND(T31/Q31*100,2)) | V31: =IF(U31="","",IF(U31>YT*100,"Y",IF(U31>=CT*100,"C",IF(U31>=WT*100,"W","D")))) | W31: =IF($V31="Y",1,"") | X31: =IF($V31="C",1,"") | Y31: =IF($V31="W",1,"") | Z31: =IF($V31="D",1,"")
A32: 2.6 | B32: MOOC / SWAYAM / NPTEL / self-learning | Q32: =SUM(Q33:Q35) -> 10 | T32: =SUM(T33:T35) -> 0 | U32: =IF(COUNT(T33:T35)=0,"",ROUND(T32/Q32*100,2)) | V32: =IF(U32="","",IF(U32>YT*100,"Y",IF(U32>=CT*100,"C",IF(U32>=WT*100,"W","D")))) | W32: =SUM(W33:W35) -> 0 | X32: =SUM(X33:X35) -> 0 | Y32: =SUM(Y33:Y35) -> 0 | Z32: =SUM(Z33:Z35) -> 0
A33: 2.6.a | B33: MOOC certification | C33: MOOC certification | D33: Certificate verifiable on NPTEL/SWAYAM/platform portal with roll no./name | E33: Students | F33: 0.1 | G33: 10 | H33: Random certified students; verify online | I33: All certificates verified | J33: Most verified | K33: Several unverifiable | L33: Mostly unverifiable | P33: % | Q33: 5 | T33: =IF(OR(S33="",R33="",R33=0),"",ROUND(Q33*MIN(S33/R33,1),2)) | U33: =IF(T33="","",ROUND(T33/Q33*100,2)) | V33: =IF(U33="","",IF(U33>YT*100,"Y",IF(U33>=CT*100,"C",IF(U33>=WT*100,"W","D")))) | W33: =IF($V33="Y",1,"") | X33: =IF($V33="C",1,"") | Y33: =IF($V33="W",1,"") | Z33: =IF($V33="D",1,"")
A34: 2.6.b | B34: Credit transfer via MOOC | C34: Credit transfer via MOOC | D34: Credit transfer approved by exam cell / university | E34: Students | F34: 0.2 | G34: 5 | H34: Sample from credit-transfer list | I34: All transfers approved | J34: Most approved | K34: Few approved | L34: None | P34: % | Q34: 2 | T34: =IF(OR(S34="",R34="",R34=0),"",ROUND(Q34*MIN(S34/R34,1),2)) | U34: =IF(T34="","",ROUND(T34/Q34*100,2)) | V34: =IF(U34="","",IF(U34>YT*100,"Y",IF(U34>=CT*100,"C",IF(U34>=WT*100,"W","D")))) | W34: =IF($V34="Y",1,"") | X34: =IF($V34="C",1,"") | Y34: =IF($V34="W",1,"") | Z34: =IF($V34="D",1,"")
A35: 2.6.c | B35: High-performance MOOC certificates | C35: High-performance certificates | D35: Elite/Silver/Gold/Topper shown on verified certificate | E35: Certificates | F35: 0.2 | G35: 5 | H35: Sample from claimed list; verify online | I35: All verified | J35: Most verified | K35: Few verified | L35: None verified | P35: % | Q35: 3 | T35: =IF(OR(S35="",R35="",R35=0),"",ROUND(Q35*MIN(S35/R35,1),2)) | U35: =IF(T35="","",ROUND(T35/Q35*100,2)) | V35: =IF(U35="","",IF(U35>YT*100,"Y",IF(U35>=CT*100,"C",IF(U35>=WT*100,"W","D")))) | W35: =IF($V35="Y",1,"") | X35: =IF($V35="C",1,"") | Y35: =IF($V35="W",1,"") | Z35: =IF($V35="D",1,"")
A36: 2.7 | B36: Complex engineering problems with SDGs | Q36: =SUM(Q37:Q40) -> 20 | T36: =SUM(T37:T40) -> 0 | U36: =IF(COUNT(T37:T40)=0,"",ROUND(T36/Q36*100,2)) | V36: =IF(U36="","",IF(U36>YT*100,"Y",IF(U36>=CT*100,"C",IF(U36>=WT*100,"W","D")))) | W36: =SUM(W37:W40) -> 0 | X36: =SUM(X37:X40) -> 0 | Y36: =SUM(Y37:Y40) -> 0 | Z36: =SUM(Z37:Z40) -> 0
A37: 2.7.a | B37: Courses with complex engineering problems | C37: Complex engineering problems in courses | D37: Problem statement meets NBA complexity attributes (depth, conflicting requirements, no obvious solution) | E37: Courses | F37: 0.25 | G37: 3 | H37: Random core courses; auditor scores problem against attributes | I37: Genuine complex problems, attributes mapped | J37: Complex but attributes partly mapped | K37: Routine problems labelled complex | L37: None | P37: % | Q37: 6 | T37: =IF(OR(S37="",R37="",R37=0),"",ROUND(Q37*MIN(S37/R37,1),2)) | U37: =IF(T37="","",ROUND(T37/Q37*100,2)) | V37: =IF(U37="","",IF(U37>YT*100,"Y",IF(U37>=CT*100,"C",IF(U37>=WT*100,"W","D")))) | W37: =IF($V37="Y",1,"") | X37: =IF($V37="C",1,"") | Y37: =IF($V37="W",1,"") | Z37: =IF($V37="D",1,"")
A38: 2.7.b | B38: Student coverage | C38: Student coverage | D38: Student submission exists for the complex-problem task | E38: Students | F38: 0.1 | G38: 10 | H38: Random students from sampled courses | I38: All sampled students submitted | J38: Most submitted | K38: About half | L38: Few or none | P38: % | Q38: 4 | T38: =IF(OR(S38="",R38="",R38=0),"",ROUND(Q38*MIN(S38/R38,1),2)) | U38: =IF(T38="","",ROUND(T38/Q38*100,2)) | V38: =IF(U38="","",IF(U38>YT*100,"Y",IF(U38>=CT*100,"C",IF(U38>=WT*100,"W","D")))) | W38: =IF($V38="Y",1,"") | X38: =IF($V38="C",1,"") | Y38: =IF($V38="W",1,"") | Z38: =IF($V38="D",1,"")
A39: 2.7.c | B39: SDG linkage | C39: SDG linkage of complex problems | D39: Task explicitly mapped to an SDG target with rationale | E39: Tasks | F39: 0.25 | G39: 3 | H39: Same tasks as 2.7.a | I39: Clear SDG target linkage | J39: SDG named, rationale weak | K39: Token linkage | L39: None | P39: % | Q39: 5 | T39: =IF(OR(S39="",R39="",R39=0),"",ROUND(Q39*MIN(S39/R39,1),2)) | U39: =IF(T39="","",ROUND(T39/Q39*100,2)) | V39: =IF(U39="","",IF(U39>YT*100,"Y",IF(U39>=CT*100,"C",IF(U39>=WT*100,"W","D")))) | W39: =IF($V39="Y",1,"") | X39: =IF($V39="C",1,"") | Y39: =IF($V39="W",1,"") | Z39: =IF($V39="D",1,"")
A40: 2.7.d | B40: Solution quality | C40: Quality of solutions | D40: Auditor re-scores solution with the same rubric; within 10% of faculty score | E40: Solutions | F40: 0.1 | G40: 5 | H40: Random solutions from sampled courses | I40: High rubric scores, re-score agrees | J40: Moderate scores, re-score agrees | K40: Low scores or re-score differs >10% | L40: Rubric not used | P40: % | Q40: 5 | T40: =IF(OR(S40="",R40="",R40=0),"",ROUND(Q40*MIN(S40/R40,1),2)) | U40: =IF(T40="","",ROUND(T40/Q40*100,2)) | V40: =IF(U40="","",IF(U40>YT*100,"Y",IF(U40>=CT*100,"C",IF(U40>=WT*100,"W","D")))) | W40: =IF($V40="Y",1,"") | X40: =IF($V40="C",1,"") | Y40: =IF($V40="W",1,"") | Z40: =IF($V40="D",1,"")
A41: 2.8 | B41: Industry-institute interaction | Q41: =SUM(Q42:Q46) -> 15 | T41: =SUM(T42:T46) -> 0 | U41: =IF(COUNT(T42:T46)=0,"",ROUND(T41/Q41*100,2)) | V41: =IF(U41="","",IF(U41>YT*100,"Y",IF(U41>=CT*100,"C",IF(U41>=WT*100,"W","D")))) | W41: =SUM(W42:W46) -> 0 | X41: =SUM(X42:X46) -> 0 | Y41: =SUM(Y42:Y46) -> 0 | Z41: =SUM(Z42:Z46) -> 0
A42: 2.8.a | B42: Active MoUs | C42: Active MoUs | D42: MoU valid in period with at least 1 dated activity report | E42: MoUs (count) | F42: 1 | G42: 5 | H42: Verify every claimed MoU (or at least 5) | I42: All MoUs active, meets benchmark | J42: Active, slightly below benchmark | K42: Many MoUs dormant | L42: No active MoUs | P42: No. | Q42: 3 | T42: =IF(OR(S42="",R42="",R42=0),"",ROUND(Q42*MIN(S42/R42,1),2)) | U42: =IF(T42="","",ROUND(T42/Q42*100,2)) | V42: =IF(U42="","",IF(U42>YT*100,"Y",IF(U42>=CT*100,"C",IF(U42>=WT*100,"W","D")))) | W42: =IF($V42="Y",1,"") | X42: =IF($V42="C",1,"") | Y42: =IF($V42="W",1,"") | Z42: =IF($V42="D",1,"")
A43: 2.8.b | B43: Industry expert lectures | C43: Industry expert lectures | D43: Report with expert name, organisation, date, attendance, photos | E43: Lectures (count) | F43: 1 | G43: 5 | H43: Verify every claimed lecture (or at least 5) | I43: Meets benchmark, all verified | J43: Slightly below benchmark | K43: Well below benchmark | L43: Little or none | P43: No. | Q43: 3 | T43: =IF(OR(S43="",R43="",R43=0),"",ROUND(Q43*MIN(S43/R43,1),2)) | U43: =IF(T43="","",ROUND(T43/Q43*100,2)) | V43: =IF(U43="","",IF(U43>YT*100,"Y",IF(U43>=CT*100,"C",IF(U43>=WT*100,"W","D")))) | W43: =IF($V43="Y",1,"") | X43: =IF($V43="C",1,"") | Y43: =IF($V43="W",1,"") | Z43: =IF($V43="D",1,"")
A44: 2.8.c | B44: Industrial visits | C44: Industrial visits | D44: Permission letter + visit report + student list | E44: Students | F44: 0.1 | G44: 10 | H44: Random students; check they appear in visit lists | I44: Most students covered, verified | J44: Majority covered | K44: About half covered | L44: Few covered | P44: % | Q44: 3 | T44: =IF(OR(S44="",R44="",R44=0),"",ROUND(Q44*MIN(S44/R44,1),2)) | U44: =IF(T44="","",ROUND(T44/Q44*100,2)) | V44: =IF(U44="","",IF(U44>YT*100,"Y",IF(U44>=CT*100,"C",IF(U44>=WT*100,"W","D")))) | W44: =IF($V44="Y",1,"") | X44: =IF($V44="C",1,"") | Y44: =IF($V44="W",1,"") | Z44: =IF($V44="D",1,"")
A45: 2.8.d | B45: Industry co-delivered courses or labs | C45: Industry co-delivered courses / labs | D45: Agreement + schedule + attendance of co-delivered sessions | E45: Courses/labs (count) | F45: 1 | G45: 3 | H45: Verify all claimed; visit lab if any | I45: Meets benchmark, active | J45: Slightly below benchmark | K45: Well below benchmark | L45: None | P45: No. | Q45: 3 | T45: =IF(OR(S45="",R45="",R45=0),"",ROUND(Q45*MIN(S45/R45,1),2)) | U45: =IF(T45="","",ROUND(T45/Q45*100,2)) | V45: =IF(U45="","",IF(U45>YT*100,"Y",IF(U45>=CT*100,"C",IF(U45>=WT*100,"W","D")))) | W45: =IF($V45="Y",1,"") | X45: =IF($V45="C",1,"") | Y45: =IF($V45="W",1,"") | Z45: =IF($V45="D",1,"")
A46: 2.8.e | B46: Industry-supported projects or internships | C46: Industry-supported projects / internships | D46: Support letter from industry naming students/project | E46: Items (count) | F46: 1 | G46: 5 | H46: Verify all claimed (or at least 5) | I46: Meets benchmark, verified | J46: Slightly below | K46: Well below | L46: None verified | P46: No. | Q46: 3 | T46: =IF(OR(S46="",R46="",R46=0),"",ROUND(Q46*MIN(S46/R46,1),2)) | U46: =IF(T46="","",ROUND(T46/Q46*100,2)) | V46: =IF(U46="","",IF(U46>YT*100,"Y",IF(U46>=CT*100,"C",IF(U46>=WT*100,"W","D")))) | W46: =IF($V46="Y",1,"") | X46: =IF($V46="C",1,"") | Y46: =IF($V46="W",1,"") | Z46: =IF($V46="D",1,"")
Q47: =Q8+Q14+Q20+Q24+Q28+Q32+Q36+Q41 -> 120 | T47: =T8+T14+T20+T24+T28+T32+T36+T41 -> 3.67 | U47: =IF(T47=0,"",ROUND(T47/Q47*100,2)) -> 3.06 | V47: =IF(U47="","",IF(U47>YT*100,"Y",IF(U47>=CT*100,"C",IF(U47>=WT*100,"W","D")))) -> D | W47: =W8+W14+W20+W24+W28+W32+W36+W41 -> 0 | X47: =X8+X14+X20+X24+X28+X32+X36+X41 -> 1 | Y47: =Y8+Y14+Y20+Y24+Y28+Y32+Y36+Y41 -> 1 | Z47: =Z8+Z14+Z20+Z24+Z28+Z32+Z36+Z41 -> 0

Sheet C3 Validation Rubrics
A1: CRITERION 3 - OUTCOME-BASED ASSESSMENT - VALIDATION RUBRICS AND SAMPLE SIZES (physical audit)
A2: Sampling: check at least the Sample % of the population, but never fewer than the Minimum (check all items if the population is smaller). Sample % and Minimum are defaults - IQAC may change them.
A3: For % indicators: Validated value = Valid items / Items checked x 100. For count indicators: Validated value = number of claimed items found valid.
A4: Enter the Benchmark (col R) and Validated value (col S) here. Marks, Percentage and Grade (Y > 75, C 60-75, W 40-60, D < 40) are calculated automatically and flow to the C3 Quantitative and All Criteria tabs.
A5: Yellow/blue = input: Items checked, Valid items, Auditor remarks, Benchmark, Validated value (and Sample % / Minimum if IQAC changes them).
A7: Code | B7: Key aspect | C7: What the auditor verifies | D7: An item counts as valid only if | E7: Sampling unit | F7: Sample % | G7: Minimum sample | H7: How to sample | I7: Y (> 75%) | J7: C (60-75%) | K7: W (40-60%) | L7: D (< 40%) | M7: Items checked | N7: Valid items | O7: Auditor remarks | P7: Unit | Q7: Max marks | R7: Benchmark | S7: Validated value | T7: Marks obtained | U7: Percentage | V7: Grade | W7: Y | X7: C | Y7: W | Z7: D
A8: 3.1 | B8: Evaluation of continuous assessment | Q8: =SUM(Q9:Q11) -> 10 | R8: 8 | T8: =SUM(T9:T11) -> 3.83 | U8: =IF(COUNT(T9:T11)=0,"",ROUND(T8/Q8*100,2)) -> 38.3 | V8: =IF(U8="","",IF(U8>YT*100,"Y",IF(U8>=CT*100,"C",IF(U8>=WT*100,"W","D")))) -> D | W8: =SUM(W9:W11) -> 0 | X8: =SUM(X9:X11) -> 0 | Y8: =SUM(Y9:Y11) -> 1 | Z8: =SUM(Z9:Z11) -> 2
A9: 3.1.a | B9: CA papers mapped to CO and Bloom's level | C9: CA papers mapped to CO and Bloom level | D9: Each question in the paper tagged with CO and BL | E9: CA papers | F9: 0.2 | G9: 5 | H9: Random CA papers across courses and CA cycles | I9: All papers fully mapped | J9: Minor untagged questions | K9: Several papers partly mapped | L9: Not mapped | P9: % | Q9: 4 | R9: 3 | S9: 1 | T9: =IF(OR(S9="",R9="",R9=0),"",ROUND(Q9*MIN(S9/R9,1),2)) -> 1.33 | U9: =IF(T9="","",ROUND(T9/Q9*100,2)) -> 33.25 | V9: =IF(U9="","",IF(U9>YT*100,"Y",IF(U9>=CT*100,"C",IF(U9>=WT*100,"W","D")))) -> D | W9: =IF($V9="Y",1,"") | X9: =IF($V9="C",1,"") | Y9: =IF($V9="W",1,"") | Z9: =IF($V9="D",1,"") -> 1
A10: 3.1.b | B10: CA papers scrutinised before use | C10: CA papers scrutinised before use | D10: Scrutiny form signed by scrutiniser dated before exam date | E10: CA papers | F10: 0.2 | G10: 5 | H10: Same papers as 3.1.a | I10: All scrutinised before use | J10: Scrutiny done, some undated | K10: Several not scrutinised | L10: No scrutiny | P10: % | Q10: 3 | R10: 3 | S10: 1 | T10: =IF(OR(S10="",R10="",R10=0),"",ROUND(Q10*MIN(S10/R10,1),2)) -> 1 | U10: =IF(T10="","",ROUND(T10/Q10*100,2)) -> 33.33 | V10: =IF(U10="","",IF(U10>YT*100,"Y",IF(U10>=CT*100,"C",IF(U10>=WT*100,"W","D")))) -> D | W10: =IF($V10="Y",1,"") | X10: =IF($V10="C",1,"") | Y10: =IF($V10="W",1,"") | Z10: =IF($V10="D",1,"") -> 1
A11: 3.1.c | B11: CA results published on time | C11: CA results published on time | D11: Result upload/notice date within institute timeline | E11: Assessments | F11: 0.2 | G11: 5 | H11: Random assessments; check ERP/notice timestamps | I11: All on time | J11: Few slightly late | K11: Many late | L11: Results not published / no record | P11: % | Q11: 3 | R11: 2 | S11: 1 | T11: =IF(OR(S11="",R11="",R11=0),"",ROUND(Q11*MIN(S11/R11,1),2)) -> 1.5 | U11: =IF(T11="","",ROUND(T11/Q11*100,2)) -> 50 | V11: =IF(U11="","",IF(U11>YT*100,"Y",IF(U11>=CT*100,"C",IF(U11>=WT*100,"W","D")))) -> W | W11: =IF($V11="Y",1,"") | X11: =IF($V11="C",1,"") | Y11: =IF($V11="W",1,"") -> 1 | Z11: =IF($V11="D",1,"")
A12: 3.2 | B12: Evaluation of SEE question papers | Q12: =SUM(Q13:Q14) -> 10 | T12: =SUM(T13:T14) -> 0 | U12: =IF(COUNT(T13:T14)=0,"",ROUND(T12/Q12*100,2)) | V12: =IF(U12="","",IF(U12>YT*100,"Y",IF(U12>=CT*100,"C",IF(U12>=WT*100,"W","D")))) | W12: =SUM(W13:W14) -> 0 | X12: =SUM(X13:X14) -> 0 | Y12: =SUM(Y13:Y14) -> 0 | Z12: =SUM(Z13:Z14) -> 0
A13: 3.2.a | B13: SEE papers analysed for CO/BL coverage | C13: SEE papers analysed for CO/BL coverage | D13: Analysis sheet shows CO and BL marks distribution for the paper | E13: SEE papers | F13: 0.25 | G13: 4 | H13: Random SEE papers from last exam | I13: All analysed | J13: Most analysed | K13: About half | L13: Not analysed | P13: % | Q13: 5 | T13: =IF(OR(S13="",R13="",R13=0),"",ROUND(Q13*MIN(S13/R13,1),2)) | U13: =IF(T13="","",ROUND(T13/Q13*100,2)) | V13: =IF(U13="","",IF(U13>YT*100,"Y",IF(U13>=CT*100,"C",IF(U13>=WT*100,"W","D")))) | W13: =IF($V13="Y",1,"") | X13: =IF($V13="C",1,"") | Y13: =IF($V13="W",1,"") | Z13: =IF($V13="D",1,"")
A14: 3.2.b | B14: SEE papers with adequate higher-order questions | C14: SEE papers with higher-order questions | D14: Apply-and-above marks share meets required % | E14: Papers analysed | F14: 0.25 | G14: 4 | H14: Same papers as 3.2.a; auditor re-checks BL tags | I14: All meet required share | J14: Most meet | K14: About half | L14: Few or none | P14: % | Q14: 5 | T14: =IF(OR(S14="",R14="",R14=0),"",ROUND(Q14*MIN(S14/R14,1),2)) | U14: =IF(T14="","",ROUND(T14/Q14*100,2)) | V14: =IF(U14="","",IF(U14>YT*100,"Y",IF(U14>=CT*100,"C",IF(U14>=WT*100,"W","D")))) | W14: =IF($V14="Y",1,"") | X14: =IF($V14="C",1,"") | Y14: =IF($V14="W",1,"") | Z14: =IF($V14="D",1,"")
A15: 3.3 | B15: Evaluation of laboratory work | Q15: =SUM(Q16:Q18) -> 10 | T15: =SUM(T16:T18) -> 0 | U15: =IF(COUNT(T16:T18)=0,"",ROUND(T15/Q15*100,2)) | V15: =IF(U15="","",IF(U15>YT*100,"Y",IF(U15>=CT*100,"C",IF(U15>=WT*100,"W","D")))) | W15: =SUM(W16:W18) -> 0 | X15: =SUM(X16:X18) -> 0 | Y15: =SUM(Y16:Y18) -> 0 | Z15: =SUM(Z16:Z18) -> 0
A16: 3.3.a | B16: Rubric-based continuous lab evaluation | C16: Rubric-based continuous lab evaluation | D16: Rubric sheet with criteria and marks per experiment | E16: Lab courses | F16: 0.25 | G16: 3 | H16: Random lab courses; observe 1 lab session | I16: Rubrics used consistently | J16: Rubrics used, some incomplete | K16: Occasional use | L16: No rubrics | P16: % | Q16: 5 | T16: =IF(OR(S16="",R16="",R16=0),"",ROUND(Q16*MIN(S16/R16,1),2)) | U16: =IF(T16="","",ROUND(T16/Q16*100,2)) | V16: =IF(U16="","",IF(U16>YT*100,"Y",IF(U16>=CT*100,"C",IF(U16>=WT*100,"W","D")))) | W16: =IF($V16="Y",1,"") | X16: =IF($V16="C",1,"") | Y16: =IF($V16="W",1,"") | Z16: =IF($V16="D",1,"")
A17: 3.3.b | B17: Experiments evaluated on schedule | C17: Experiments evaluated on schedule | D17: Evaluation dated within 1 week of experiment | E17: Experiments | F17: 0.1 | G17: 10 | H17: Random experiments from sampled lab courses | I17: All on schedule | J17: Minor delays | K17: Many delayed | L17: Not evaluated | P17: % | Q17: 3 | T17: =IF(OR(S17="",R17="",R17=0),"",ROUND(Q17*MIN(S17/R17,1),2)) | U17: =IF(T17="","",ROUND(T17/Q17*100,2)) | V17: =IF(U17="","",IF(U17>YT*100,"Y",IF(U17>=CT*100,"C",IF(U17>=WT*100,"W","D")))) | W17: =IF($V17="Y",1,"") | X17: =IF($V17="C",1,"") | Y17: =IF($V17="W",1,"") | Z17: =IF($V17="D",1,"")
A18: 3.3.c | B18: Lab records assessed | C18: Lab records assessed | D18: Record signed and marked for every completed experiment | E18: Students | F18: 0.05 | G18: 10 | H18: Random student records from sampled labs | I18: All assessed | J18: Most assessed | K18: About half | L18: Few or none | P18: % | Q18: 2 | T18: =IF(OR(S18="",R18="",R18=0),"",ROUND(Q18*MIN(S18/R18,1),2)) | U18: =IF(T18="","",ROUND(T18/Q18*100,2)) | V18: =IF(U18="","",IF(U18>YT*100,"Y",IF(U18>=CT*100,"C",IF(U18>=WT*100,"W","D")))) | W18: =IF($V18="Y",1,"") | X18: =IF($V18="C",1,"") | Y18: =IF($V18="W",1,"") | Z18: =IF($V18="D",1,"")
A19: 3.4 | B19: Evaluation of industrial training / internship | Q19: =SUM(Q20:Q21) -> 10 | T19: =SUM(T20:T21) -> 0 | U19: =IF(COUNT(T20:T21)=0,"",ROUND(T19/Q19*100,2)) | V19: =IF(U19="","",IF(U19>YT*100,"Y",IF(U19>=CT*100,"C",IF(U19>=WT*100,"W","D")))) | W19: =SUM(W20:W21) -> 0 | X19: =SUM(X20:X21) -> 0 | Y19: =SUM(Y20:Y21) -> 0 | Z19: =SUM(Z20:Z21) -> 0
A20: 3.4.a | B20: Internships evaluated with rubric | C20: Internships evaluated with rubric | D20: Rubric score sheet signed by evaluator for the internship | E20: Internships | F20: 0.1 | G20: 10 | H20: Random internships from completed list | I20: All evaluated with rubric | J20: Most | K20: About half | L20: No rubric evaluation | P20: % | Q20: 5 | T20: =IF(OR(S20="",R20="",R20=0),"",ROUND(Q20*MIN(S20/R20,1),2)) | U20: =IF(T20="","",ROUND(T20/Q20*100,2)) | V20: =IF(U20="","",IF(U20>YT*100,"Y",IF(U20>=CT*100,"C",IF(U20>=WT*100,"W","D")))) | W20: =IF($V20="Y",1,"") | X20: =IF($V20="C",1,"") | Y20: =IF($V20="W",1,"") | Z20: =IF($V20="D",1,"")
A21: 3.4.b | B21: Internship presentation / viva held | C21: Internship presentation / viva | D21: Dated presentation/viva record with panel signatures | E21: Internships | F21: 0.1 | G21: 10 | H21: Same internships as 3.4.a | I21: All presented with records | J21: Most | K21: About half | L21: None | P21: % | Q21: 5 | T21: =IF(OR(S21="",R21="",R21=0),"",ROUND(Q21*MIN(S21/R21,1),2)) | U21: =IF(T21="","",ROUND(T21/Q21*100,2)) | V21: =IF(U21="","",IF(U21>YT*100,"Y",IF(U21>=CT*100,"C",IF(U21>=WT*100,"W","D")))) | W21: =IF($V21="Y",1,"") | X21: =IF($V21="C",1,"") | Y21: =IF($V21="W",1,"") | Z21: =IF($V21="D",1,"")
A22: 3.5 | B22: Evaluation of projects | Q22: =SUM(Q23:Q25) -> 20 | T22: =SUM(T23:T25) -> 0 | U22: =IF(COUNT(T23:T25)=0,"",ROUND(T22/Q22*100,2)) | V22: =IF(U22="","",IF(U22>YT*100,"Y",IF(U22>=CT*100,"C",IF(U22>=WT*100,"W","D")))) | W22: =SUM(W23:W25) -> 0 | X22: =SUM(X23:X25) -> 0 | Y22: =SUM(Y23:Y25) -> 0 | Z22: =SUM(Z23:Z25) -> 0
A23: 3.5.a | B23: Projects with 3 or more rubric reviews | C23: Projects with 3+ rubric reviews | D23: At least 3 dated reviews with rubric sheets | E23: Projects | F23: 0.2 | G23: 5 | H23: Random final-year projects across guides | I23: All sampled meet | J23: One review missing in a few | K23: Many fewer than 3 | L23: No rubric reviews | P23: % | Q23: 8 | T23: =IF(OR(S23="",R23="",R23=0),"",ROUND(Q23*MIN(S23/R23,1),2)) | U23: =IF(T23="","",ROUND(T23/Q23*100,2)) | V23: =IF(U23="","",IF(U23>YT*100,"Y",IF(U23>=CT*100,"C",IF(U23>=WT*100,"W","D")))) | W23: =IF($V23="Y",1,"") | X23: =IF($V23="C",1,"") | Y23: =IF($V23="W",1,"") | Z23: =IF($V23="D",1,"")
A24: 3.5.b | B24: Projects evaluated by external examiner | C24: Projects evaluated by external examiner | D24: External examiner name, signature and marks recorded | E24: Projects | F24: 0.2 | G24: 5 | H24: Random projects; check viva register | I24: All externally evaluated | J24: Most | K24: About half | L24: None | P24: % | Q24: 6 | T24: =IF(OR(S24="",R24="",R24=0),"",ROUND(Q24*MIN(S24/R24,1),2)) | U24: =IF(T24="","",ROUND(T24/Q24*100,2)) | V24: =IF(U24="","",IF(U24>YT*100,"Y",IF(U24>=CT*100,"C",IF(U24>=WT*100,"W","D")))) | W24: =IF($V24="Y",1,"") | X24: =IF($V24="C",1,"") | Y24: =IF($V24="W",1,"") | Z24: =IF($V24="D",1,"")
A25: 3.5.c | B25: PO attainment computed from projects | C25: PO attainment from projects | D25: Project rubric marks mapped to POs with attainment computed | E25: Projects | F25: 0.2 | G25: 5 | H25: Random projects; auditor recomputes 1 | I25: Computed for all, recompute matches | J25: Computed, minor errors | K25: Partly computed | L25: Not computed | P25: % | Q25: 6 | T25: =IF(OR(S25="",R25="",R25=0),"",ROUND(Q25*MIN(S25/R25,1),2)) | U25: =IF(T25="","",ROUND(T25/Q25*100,2)) | V25: =IF(U25="","",IF(U25>YT*100,"Y",IF(U25>=CT*100,"C",IF(U25>=WT*100,"W","D")))) | W25: =IF($V25="Y",1,"") | X25: =IF($V25="C",1,"") | Y25: =IF($V25="W",1,"") | Z25: =IF($V25="D",1,"")
A26: 3.6 | B26: Evidence of addressing SDGs | Q26: =SUM(Q27:Q28) -> 10 | T26: =SUM(T27:T28) -> 0 | U26: =IF(COUNT(T27:T28)=0,"",ROUND(T26/Q26*100,2)) | V26: =IF(U26="","",IF(U26>YT*100,"Y",IF(U26>=CT*100,"C",IF(U26>=WT*100,"W","D")))) | W26: =SUM(W27:W28) -> 0 | X26: =SUM(X27:X28) -> 0 | Y26: =SUM(Y27:Y28) -> 0 | Z26: =SUM(Z27:Z28) -> 0
A27: 3.6.a | B27: Courses with SDG-mapped assessment | C27: Courses with SDG-mapped assessment | D27: Assessment item explicitly mapped to an SDG target | E27: Courses | F27: 0.2 | G27: 5 | H27: Random courses; check CA papers/assignments | I27: All sampled courses | J27: Most | K27: Few | L27: None | P27: % | Q27: 5 | T27: =IF(OR(S27="",R27="",R27=0),"",ROUND(Q27*MIN(S27/R27,1),2)) | U27: =IF(T27="","",ROUND(T27/Q27*100,2)) | V27: =IF(U27="","",IF(U27>YT*100,"Y",IF(U27>=CT*100,"C",IF(U27>=WT*100,"W","D")))) | W27: =IF($V27="Y",1,"") | X27: =IF($V27="C",1,"") | Y27: =IF($V27="W",1,"") | Z27: =IF($V27="D",1,"")
A28: 3.6.b | B28: Projects / assignments addressing SDGs | C28: Projects / assignments addressing SDGs | D28: Problem statement addresses a named SDG with rationale | E28: Projects/assignments | F28: 0.1 | G28: 10 | H28: Random projects and assignments | I28: Clear SDG linkage in all | J28: Most linked | K28: Token linkage | L28: None | P28: % | Q28: 5 | T28: =IF(OR(S28="",R28="",R28=0),"",ROUND(Q28*MIN(S28/R28,1),2)) | U28: =IF(T28="","",ROUND(T28/Q28*100,2)) | V28: =IF(U28="","",IF(U28>YT*100,"Y",IF(U28>=CT*100,"C",IF(U28>=WT*100,"W","D")))) | W28: =IF($V28="Y",1,"") | X28: =IF($V28="C",1,"") | Y28: =IF($V28="W",1,"") | Z28: =IF($V28="D",1,"")
A29: 3.7 | B29: Attainment of Course Outcomes | Q29: =SUM(Q30:Q32) -> 25 | T29: =SUM(T30:T32) -> 0 | U29: =IF(COUNT(T30:T32)=0,"",ROUND(T29/Q29*100,2)) | V29: =IF(U29="","",IF(U29>YT*100,"Y",IF(U29>=CT*100,"C",IF(U29>=WT*100,"W","D")))) | W29: =SUM(W30:W32) -> 0 | X29: =SUM(X30:X32) -> 0 | Y29: =SUM(Y30:Y32) -> 0 | Z29: =SUM(Z30:Z32) -> 0
A30: 3.7.a | B30: Assessment tools defined (3.7.1) | C30: Assessment tools defined | D30: Direct and indirect tools with weightages documented in course file | E30: Courses | F30: 0.2 | G30: 5 | H30: Random courses | I30: All defined | J30: Most defined | K30: Partly defined | L30: Not defined | P30: % | Q30: 5 | T30: =IF(OR(S30="",R30="",R30=0),"",ROUND(Q30*MIN(S30/R30,1),2)) | U30: =IF(T30="","",ROUND(T30/Q30*100,2)) | V30: =IF(U30="","",IF(U30>YT*100,"Y",IF(U30>=CT*100,"C",IF(U30>=WT*100,"W","D")))) | W30: =IF($V30="Y",1,"") | X30: =IF($V30="C",1,"") | Y30: =IF($V30="W",1,"") | Z30: =IF($V30="D",1,"")
A31: 3.7.b | B31: CO attainment computed (3.7.2) | C31: CO attainment computed | D31: Attainment sheet with computation from marks; auditor recompute matches | E31: Courses | F31: 0.2 | G31: 5 | H31: Random courses; recompute 2 COs | I31: Computed for all; recompute matches | J31: Computed, minor errors | K31: Partly computed | L31: Not computed | P31: % | Q31: 8 | T31: =IF(OR(S31="",R31="",R31=0),"",ROUND(Q31*MIN(S31/R31,1),2)) | U31: =IF(T31="","",ROUND(T31/Q31*100,2)) | V31: =IF(U31="","",IF(U31>YT*100,"Y",IF(U31>=CT*100,"C",IF(U31>=WT*100,"W","D")))) | W31: =IF($V31="Y",1,"") | X31: =IF($V31="C",1,"") | Y31: =IF($V31="W",1,"") | Z31: =IF($V31="D",1,"")
A32: 3.7.c | B32: Courses attaining CO target (3.7.2) | C32: Courses attaining CO target | D32: Computed attainment level meets set target | E32: Courses with attainment | F32: 0.25 | G32: 5 | H32: Random courses from 3.7.b sample | I32: Most courses attain target | J32: Majority attain | K32: About half | L32: Few attain | P32: % | Q32: 12 | T32: =IF(OR(S32="",R32="",R32=0),"",ROUND(Q32*MIN(S32/R32,1),2)) | U32: =IF(T32="","",ROUND(T32/Q32*100,2)) | V32: =IF(U32="","",IF(U32>YT*100,"Y",IF(U32>=CT*100,"C",IF(U32>=WT*100,"W","D")))) | W32: =IF($V32="Y",1,"") | X32: =IF($V32="C",1,"") | Y32: =IF($V32="W",1,"") | Z32: =IF($V32="D",1,"")
A33: 3.8 | B33: Attainment of POs and PSOs | Q33: =SUM(Q34:Q35) -> 25 | T33: =SUM(T34:T35) -> 0 | U33: =IF(COUNT(T34:T35)=0,"",ROUND(T33/Q33*100,2)) | V33: =IF(U33="","",IF(U33>YT*100,"Y",IF(U33>=CT*100,"C",IF(U33>=WT*100,"W","D")))) | W33: =SUM(W34:W35) -> 0 | X33: =SUM(X34:X35) -> 0 | Y33: =SUM(Y34:Y35) -> 0 | Z33: =SUM(Z34:Z35) -> 0
A34: 3.8.a | B34: PO/PSO attainment computed | C34: PO/PSO attainment computed | D34: Direct + indirect attainment computed per PO/PSO with sheet | E34: POs/PSOs | F34: 0.5 | G34: 6 | H34: Random POs/PSOs; recompute 2 | I34: Computed for all; recompute matches | J34: Minor errors | K34: Partly computed | L34: Not computed | P34: % | Q34: 10 | T34: =IF(OR(S34="",R34="",R34=0),"",ROUND(Q34*MIN(S34/R34,1),2)) | U34: =IF(T34="","",ROUND(T34/Q34*100,2)) | V34: =IF(U34="","",IF(U34>YT*100,"Y",IF(U34>=CT*100,"C",IF(U34>=WT*100,"W","D")))) | W34: =IF($V34="Y",1,"") | X34: =IF($V34="C",1,"") | Y34: =IF($V34="W",1,"") | Z34: =IF($V34="D",1,"")
A35: 3.8.b | B35: POs/PSOs attaining target | C35: POs/PSOs attaining target | D35: Computed attainment meets target level | E35: POs/PSOs | F35: 1 | G35: 12 | H35: Check all POs/PSOs | I35: Most attain target | J35: Majority attain | K35: About half | L35: Few attain | P35: % | Q35: 15 | T35: =IF(OR(S35="",R35="",R35=0),"",ROUND(Q35*MIN(S35/R35,1),2)) | U35: =IF(T35="","",ROUND(T35/Q35*100,2)) | V35: =IF(U35="","",IF(U35>YT*100,"Y",IF(U35>=CT*100,"C",IF(U35>=WT*100,"W","D")))) | W35: =IF($V35="Y",1,"") | X35: =IF($V35="C",1,"") | Y35: =IF($V35="W",1,"") | Z35: =IF($V35="D",1,"")
A36: C3 | B36: CRITERION 3 TOTAL | Q36: =Q8+Q12+Q15+Q19+Q22+Q26+Q29+Q33 -> 120 | T36: =T8+T12+T15+T19+T22+T26+T29+T33 -> 3.83 | U36: =IF(T36=0,"",ROUND(T36/Q36*100,2)) -> 3.19 | V36: =IF(U36="","",IF(U36>YT*100,"Y",IF(U36>=CT*100,"C",IF(U36>=WT*100,"W","D")))) -> D | W36: =W8+W12+W15+W19+W22+W26+W29+W33 -> 0 | X36: =X8+X12+X15+X19+X22+X26+X29+X33 -> 0 | Y36: =Y8+Y12+Y15+Y19+Y22+Y26+Y29+Y33 -> 1 | Z36: =Z8+Z12+Z15+Z19+Z22+Z26+Z29+Z33 -> 2

Sheet C4 Validation Rubrics
A1: CRITERION 4 - STUDENTS' PERFORMANCE - VALIDATION RUBRICS AND SAMPLE SIZES (physical audit)
A2: Sampling: check at least the Sample % of the population, but never fewer than the Minimum (check all items if the population is smaller). Sample % and Minimum are defaults - IQAC may change them.
A3: For % indicators: Validated value = Valid items / Items checked x 100. For count indicators: Validated value = number of claimed items found valid.
A4: Enter the Benchmark (col R) and Validated value (col S) here. Marks, Percentage and Grade (Y > 75, C 60-75, W 40-60, D < 40) are calculated automatically and flow to the C4 Quantitative and All Criteria tabs.
A5: Yellow/blue = input: Items checked, Valid items, Auditor remarks, Benchmark, Validated value (and Sample % / Minimum if IQAC changes them).
A7: Code | B7: Key aspect | C7: What the auditor verifies | D7: An item counts as valid only if | E7: Sampling unit | F7: Sample % | G7: Minimum sample | H7: How to sample | I7: Y (> 75%) | J7: C (60-75%) | K7: W (40-60%) | L7: D (< 40%) | M7: Items checked | N7: Valid items | O7: Auditor remarks | P7: Unit | Q7: Max marks | R7: Benchmark | S7: Validated value | T7: Marks obtained | U7: Percentage | V7: Grade | W7: Y | X7: C | Y7: W | Z7: D
A8: 4.1 | B8: Enrolment ratio | Q8: =SUM(Q9) -> 20 | T8: =SUM(T9) -> 0 | U8: =IF(COUNT(T9)=0,"",ROUND(T8/Q8*100,2)) | V8: =IF(U8="","",IF(U8>YT*100,"Y",IF(U8>=CT*100,"C",IF(U8>=WT*100,"W","D")))) | W8: =SUM(W9) -> 0 | X8: =SUM(X9) -> 0 | Y8: =SUM(Y9) -> 0 | Z8: =SUM(Z9) -> 0
A9: 4.1.a | B9: Enrolment ratio | C9: Enrolment ratio | D9: Admission record (university approval list) matches the student | E9: Students admitted | F9: 0.05 | G9: 10 | H9: Random admitted students; match with approved admission list and sanctioned intake letter | I9: Intake filled, all verified | J9: Slight shortfall, verified | K9: Significant shortfall | L9: Large shortfall or unverifiable | P9: % | Q9: 20 | T9: =IF(OR(S9="",R9="",R9=0),"",ROUND(Q9*MIN(S9/R9,1),2)) | U9: =IF(T9="","",ROUND(T9/Q9*100,2)) | V9: =IF(U9="","",IF(U9>YT*100,"Y",IF(U9>=CT*100,"C",IF(U9>=WT*100,"W","D")))) | W9: =IF($V9="Y",1,"") | X9: =IF($V9="C",1,"") | Y9: =IF($V9="W",1,"") | Z9: =IF($V9="D",1,"")
A10: 4.2 | B10: Success rate in stipulated period | Q10: =SUM(Q11:Q12) -> 15 | T10: =SUM(T11:T12) -> 0 | U10: =IF(COUNT(T11:T12)=0,"",ROUND(T10/Q10*100,2)) | V10: =IF(U10="","",IF(U10>YT*100,"Y",IF(U10>=CT*100,"C",IF(U10>=WT*100,"W","D")))) | W10: =SUM(W11:W12) -> 0 | X10: =SUM(X11:X12) -> 0 | Y10: =SUM(Y11:Y12) -> 0 | Z10: =SUM(Z11:Z12) -> 0
A11: 4.2.a | B11: Success without backlog | C11: Success without backlog | D11: Grade sheet shows no arrear within stipulated period | E11: Graduated students | F11: 0.1 | G11: 10 | H11: Random students from the claimed list; verify university grade sheets | I11: All claims verified | J11: Most verified | K11: Several mismatches | L11: Mostly unverifiable | P11: % | Q11: 10 | T11: =IF(OR(S11="",R11="",R11=0),"",ROUND(Q11*MIN(S11/R11,1),2)) | U11: =IF(T11="","",ROUND(T11/Q11*100,2)) | V11: =IF(U11="","",IF(U11>YT*100,"Y",IF(U11>=CT*100,"C",IF(U11>=WT*100,"W","D")))) | W11: =IF($V11="Y",1,"") | X11: =IF($V11="C",1,"") | Y11: =IF($V11="W",1,"") | Z11: =IF($V11="D",1,"")
A12: 4.2.b | B12: Success with backlog | C12: Success with backlog | D12: Graduated within stipulated period with arrears cleared | E12: Graduated students | F12: 0.1 | G12: 10 | H12: Random students from claimed list | I12: All verified | J12: Most verified | K12: Several mismatches | L12: Mostly unverifiable | P12: % | Q12: 5 | T12: =IF(OR(S12="",R12="",R12=0),"",ROUND(Q12*MIN(S12/R12,1),2)) | U12: =IF(T12="","",ROUND(T12/Q12*100,2)) | V12: =IF(U12="","",IF(U12>YT*100,"Y",IF(U12>=CT*100,"C",IF(U12>=WT*100,"W","D")))) | W12: =IF($V12="Y",1,"") | X12: =IF($V12="C",1,"") | Y12: =IF($V12="W",1,"") | Z12: =IF($V12="D",1,"")
A13: 4.3 | B13: Academic performance - first year | Q13: =SUM(Q14:Q15) -> 10 | T13: =SUM(T14:T15) -> 0 | U13: =IF(COUNT(T14:T15)=0,"",ROUND(T13/Q13*100,2)) | V13: =IF(U13="","",IF(U13>YT*100,"Y",IF(U13>=CT*100,"C",IF(U13>=WT*100,"W","D")))) | W13: =SUM(W14:W15) -> 0 | X13: =SUM(X14:X15) -> 0 | Y13: =SUM(Y14:Y15) -> 0 | Z13: =SUM(Z14:Z15) -> 0
A14: 4.3.a | B14: First-year pass rate | C14: First-year pass rate | D14: University result shows student passed all first-year courses | E14: Students | F14: 0.1 | G14: 10 | H14: Random students; check result sheet | I14: All claims verified | J14: Most verified | K14: Several mismatches | L14: Unverifiable | P14: % | Q14: 5 | T14: =IF(OR(S14="",R14="",R14=0),"",ROUND(Q14*MIN(S14/R14,1),2)) | U14: =IF(T14="","",ROUND(T14/Q14*100,2)) | V14: =IF(U14="","",IF(U14>YT*100,"Y",IF(U14>=CT*100,"C",IF(U14>=WT*100,"W","D")))) | W14: =IF($V14="Y",1,"") | X14: =IF($V14="C",1,"") | Y14: =IF($V14="W",1,"") | Z14: =IF($V14="D",1,"")
A15: 4.3.b | B15: First-year mean CGPA | C15: First-year mean CGPA | D15: CGPA in grade sheet matches department data | E15: Students | F15: 0.1 | G15: 10 | H15: Random students; auditor recomputes mean from sample | I15: Data matches; CGPA high | J15: Matches; CGPA moderate | K15: Minor mismatches or low CGPA | L15: Data does not match | P15: % | Q15: 5 | T15: =IF(OR(S15="",R15="",R15=0),"",ROUND(Q15*MIN(S15/R15,1),2)) | U15: =IF(T15="","",ROUND(T15/Q15*100,2)) | V15: =IF(U15="","",IF(U15>YT*100,"Y",IF(U15>=CT*100,"C",IF(U15>=WT*100,"W","D")))) | W15: =IF($V15="Y",1,"") | X15: =IF($V15="C",1,"") | Y15: =IF($V15="W",1,"") | Z15: =IF($V15="D",1,"")
A16: 4.4 | B16: Academic performance - second year | Q16: =SUM(Q17:Q18) -> 10 | T16: =SUM(T17:T18) -> 0 | U16: =IF(COUNT(T17:T18)=0,"",ROUND(T16/Q16*100,2)) | V16: =IF(U16="","",IF(U16>YT*100,"Y",IF(U16>=CT*100,"C",IF(U16>=WT*100,"W","D")))) | W16: =SUM(W17:W18) -> 0 | X16: =SUM(X17:X18) -> 0 | Y16: =SUM(Y17:Y18) -> 0 | Z16: =SUM(Z17:Z18) -> 0
A17: 4.4.a | B17: Second-year pass rate | C17: Second-year pass rate | D17: University result shows student passed all second-year courses | E17: Students | F17: 0.1 | G17: 10 | H17: Random students; check result sheet | I17: All claims verified | J17: Most verified | K17: Several mismatches | L17: Unverifiable | P17: % | Q17: 5 | T17: =IF(OR(S17="",R17="",R17=0),"",ROUND(Q17*MIN(S17/R17,1),2)) | U17: =IF(T17="","",ROUND(T17/Q17*100,2)) | V17: =IF(U17="","",IF(U17>YT*100,"Y",IF(U17>=CT*100,"C",IF(U17>=WT*100,"W","D")))) | W17: =IF($V17="Y",1,"") | X17: =IF($V17="C",1,"") | Y17: =IF($V17="W",1,"") | Z17: =IF($V17="D",1,"")
A18: 4.4.b | B18: Second-year mean CGPA | C18: Second-year mean CGPA | D18: CGPA in grade sheet matches department data | E18: Students | F18: 0.1 | G18: 10 | H18: Random students | I18: Data matches; CGPA high | J18: Matches; CGPA moderate | K18: Minor mismatches or low CGPA | L18: Data does not match | P18: % | Q18: 5 | T18: =IF(OR(S18="",R18="",R18=0),"",ROUND(Q18*MIN(S18/R18,1),2)) | U18: =IF(T18="","",ROUND(T18/Q18*100,2)) | V18: =IF(U18="","",IF(U18>YT*100,"Y",IF(U18>=CT*100,"C",IF(U18>=WT*100,"W","D")))) | W18: =IF($V18="Y",1,"") | X18: =IF($V18="C",1,"") | Y18: =IF($V18="W",1,"") | Z18: =IF($V18="D",1,"")
A19: 4.5 | B19: Academic performance - third year | Q19: =SUM(Q20:Q21) -> 10 | T19: =SUM(T20:T21) -> 0 | U19: =IF(COUNT(T20:T21)=0,"",ROUND(T19/Q19*100,2)) | V19: =IF(U19="","",IF(U19>YT*100,"Y",IF(U19>=CT*100,"C",IF(U19>=WT*100,"W","D")))) | W19: =SUM(W20:W21) -> 0 | X19: =SUM(X20:X21) -> 0 | Y19: =SUM(Y20:Y21) -> 0 | Z19: =SUM(Z20:Z21) -> 0
A20: 4.5.a | B20: Third-year pass rate | C20: Third-year pass rate | D20: University result shows student passed all third-year courses | E20: Students | F20: 0.1 | G20: 10 | H20: Random students; check result sheet | I20: All claims verified | J20: Most verified | K20: Several mismatches | L20: Unverifiable | P20: % | Q20: 5 | T20: =IF(OR(S20="",R20="",R20=0),"",ROUND(Q20*MIN(S20/R20,1),2)) | U20: =IF(T20="","",ROUND(T20/Q20*100,2)) | V20: =IF(U20="","",IF(U20>YT*100,"Y",IF(U20>=CT*100,"C",IF(U20>=WT*100,"W","D")))) | W20: =IF($V20="Y",1,"") | X20: =IF($V20="C",1,"") | Y20: =IF($V20="W",1,"") | Z20: =IF($V20="D",1,"")
A21: 4.5.b | B21: Third-year mean CGPA | C21: Third-year mean CGPA | D21: CGPA in grade sheet matches department data | E21: Students | F21: 0.1 | G21: 10 | H21: Random students | I21: Data matches; CGPA high | J21: Matches; CGPA moderate | K21: Minor mismatches or low CGPA | L21: Data does not match | P21: % | Q21: 5 | T21: =IF(OR(S21="",R21="",R21=0),"",ROUND(Q21*MIN(S21/R21,1),2)) | U21: =IF(T21="","",ROUND(T21/Q21*100,2)) | V21: =IF(U21="","",IF(U21>YT*100,"Y",IF(U21>=CT*100,"C",IF(U21>=WT*100,"W","D")))) | W21: =IF($V21="Y",1,"") | X21: =IF($V21="C",1,"") | Y21: =IF($V21="W",1,"") | Z21: =IF($V21="D",1,"")
A22: 4.6 | B22: Placement, higher studies and entrepreneurship | Q22: =SUM(Q23:Q26) -> 30 | T22: =SUM(T23:T26) -> 0 | U22: =IF(COUNT(T23:T26)=0,"",ROUND(T22/Q22*100,2)) | V22: =IF(U22="","",IF(U22>YT*100,"Y",IF(U22>=CT*100,"C",IF(U22>=WT*100,"W","D")))) | W22: =SUM(W23:W26) -> 0 | X22: =SUM(X23:X26) -> 0 | Y22: =SUM(Y23:Y26) -> 0 | Z22: =SUM(Z23:Z26) -> 0
A23: 4.6.a | B23: Placement | C23: Placement | D23: Offer letter on company letterhead + joining/acceptance proof; company verifiable | E23: Placed students | F23: 0.1 | G23: 10 | H23: Random placed students; call or email 2 HR contacts | I23: All offers verified | J23: Most verified | K23: Several unverifiable | L23: Mostly unverifiable | P23: % | Q23: 15 | T23: =IF(OR(S23="",R23="",R23=0),"",ROUND(Q23*MIN(S23/R23,1),2)) | U23: =IF(T23="","",ROUND(T23/Q23*100,2)) | V23: =IF(U23="","",IF(U23>YT*100,"Y",IF(U23>=CT*100,"C",IF(U23>=WT*100,"W","D")))) | W23: =IF($V23="Y",1,"") | X23: =IF($V23="C",1,"") | Y23: =IF($V23="W",1,"") | Z23: =IF($V23="D",1,"")
A24: 4.6.b | B24: Higher studies | C24: Higher studies | D24: Admission letter/ID card from the institution with programme name | E24: Students | F24: 0.2 | G24: 5 | H24: Random students from claimed list | I24: All verified | J24: Most verified | K24: Several unverifiable | L24: Mostly unverifiable | P24: % | Q24: 8 | T24: =IF(OR(S24="",R24="",R24=0),"",ROUND(Q24*MIN(S24/R24,1),2)) | U24: =IF(T24="","",ROUND(T24/Q24*100,2)) | V24: =IF(U24="","",IF(U24>YT*100,"Y",IF(U24>=CT*100,"C",IF(U24>=WT*100,"W","D")))) | W24: =IF($V24="Y",1,"") | X24: =IF($V24="C",1,"") | Y24: =IF($V24="W",1,"") | Z24: =IF($V24="D",1,"")
A25: 4.6.c | B25: Entrepreneurs | C25: Entrepreneurs | D25: Registration proof (MCA/Udyam/GST/DPIIT) naming the student as founder | E25: Startups (count) | F25: 1 | G25: 3 | H25: Verify every claimed entrepreneur | I25: Meets benchmark, all verified | J25: Slightly below benchmark | K25: Well below benchmark | L25: None verified | P25: No. | Q25: 2 | T25: =IF(OR(S25="",R25="",R25=0),"",ROUND(Q25*MIN(S25/R25,1),2)) | U25: =IF(T25="","",ROUND(T25/Q25*100,2)) | V25: =IF(U25="","",IF(U25>YT*100,"Y",IF(U25>=CT*100,"C",IF(U25>=WT*100,"W","D")))) | W25: =IF($V25="Y",1,"") | X25: =IF($V25="C",1,"") | Y25: =IF($V25="W",1,"") | Z25: =IF($V25="D",1,"")
A26: 4.6.d | B26: Median salary | C26: Median salary | D26: Offer letter shows CTC; auditor recomputes median from verified offers | E26: Offer letters | F26: 0.1 | G26: 10 | H26: Random offers across salary range; recompute median | I26: Recomputed median matches and meets benchmark | J26: Matches, slightly below | K26: Well below or mismatch | L26: Unverifiable | P26: No. | Q26: 5 | T26: =IF(OR(S26="",R26="",R26=0),"",ROUND(Q26*MIN(S26/R26,1),2)) | U26: =IF(T26="","",ROUND(T26/Q26*100,2)) | V26: =IF(U26="","",IF(U26>YT*100,"Y",IF(U26>=CT*100,"C",IF(U26>=WT*100,"W","D")))) | W26: =IF($V26="Y",1,"") | X26: =IF($V26="C",1,"") | Y26: =IF($V26="W",1,"") | Z26: =IF($V26="D",1,"")
A27: 4.7 | B27: Professional activities | Q27: =SUM(Q28:Q32) -> 25 | T27: =SUM(T28:T32) -> 0 | U27: =IF(COUNT(T28:T32)=0,"",ROUND(T27/Q27*100,2)) | V27: =IF(U27="","",IF(U27>YT*100,"Y",IF(U27>=CT*100,"C",IF(U27>=WT*100,"W","D")))) | W27: =SUM(W28:W32) -> 0 | X27: =SUM(X28:X32) -> 0 | Y27: =SUM(Y28:Y32) -> 0 | Z27: =SUM(Z28:Z32) -> 0
A28: 4.7.a | B28: Professional events organised (4.7.1) | C28: Professional events organised | D28: Event report with date, resource person, attendance and photos | E28: Events (count) | F28: 1 | G28: 5 | H28: Verify every claimed event (or at least 5) | I28: Meets benchmark, verified | J28: Slightly below | K28: Well below | L28: Little or none | P28: No. | Q28: 5 | T28: =IF(OR(S28="",R28="",R28=0),"",ROUND(Q28*MIN(S28/R28,1),2)) | U28: =IF(T28="","",ROUND(T28/Q28*100,2)) | V28: =IF(U28="","",IF(U28>YT*100,"Y",IF(U28>=CT*100,"C",IF(U28>=WT*100,"W","D")))) | W28: =IF($V28="Y",1,"") | X28: =IF($V28="C",1,"") | Y28: =IF($V28="W",1,"") | Z28: =IF($V28="D",1,"")
A29: 4.7.b | B29: Student participation in professional events (4.7.2) | C29: Student participation in professional events | D29: Student name in attendance/certificate list of the event | E29: Students | F29: 0.05 | G29: 10 | H29: Random students; match with event attendance lists | I29: Most students participated | J29: Majority | K29: About half | L29: Few | P29: % | Q29: 6 | T29: =IF(OR(S29="",R29="",R29=0),"",ROUND(Q29*MIN(S29/R29,1),2)) | U29: =IF(T29="","",ROUND(T29/Q29*100,2)) | V29: =IF(U29="","",IF(U29>YT*100,"Y",IF(U29>=CT*100,"C",IF(U29>=WT*100,"W","D")))) | W29: =IF($V29="Y",1,"") | X29: =IF($V29="C",1,"") | Y29: =IF($V29="W",1,"") | Z29: =IF($V29="D",1,"")
A30: 4.7.c | B30: Prizes won in professional events (4.7.2) | C30: Prizes won | D30: Prize certificate or organiser letter naming the student | E30: Prizes (count) | F30: 1 | G30: 5 | H30: Verify every claimed prize (or at least 5) | I30: Meets benchmark, verified | J30: Slightly below | K30: Well below | L30: None verified | P30: No. | Q30: 4 | T30: =IF(OR(S30="",R30="",R30=0),"",ROUND(Q30*MIN(S30/R30,1),2)) | U30: =IF(T30="","",ROUND(T30/Q30*100,2)) | V30: =IF(U30="","",IF(U30>YT*100,"Y",IF(U30>=CT*100,"C",IF(U30>=WT*100,"W","D")))) | W30: =IF($V30="Y",1,"") | X30: =IF($V30="C",1,"") | Y30: =IF($V30="W",1,"") | Z30: =IF($V30="D",1,"")
A31: 4.7.d | B31: Department publications (4.7.3) | C31: Department publications | D31: Published issue (print/PDF) with date and editorial board | E31: Issues (count) | F31: 1 | G31: 3 | H31: Verify every claimed issue | I31: Meets benchmark, regular issues | J31: Slightly below | K31: Irregular | L31: None | P31: No. | Q31: 5 | T31: =IF(OR(S31="",R31="",R31=0),"",ROUND(Q31*MIN(S31/R31,1),2)) | U31: =IF(T31="","",ROUND(T31/Q31*100,2)) | V31: =IF(U31="","",IF(U31>YT*100,"Y",IF(U31>=CT*100,"C",IF(U31>=WT*100,"W","D")))) | W31: =IF($V31="Y",1,"") | X31: =IF($V31="C",1,"") | Y31: =IF($V31="W",1,"") | Z31: =IF($V31="D",1,"")
A32: 4.7.e | B32: Student publications (4.7.4) | C32: Student publications | D32: Paper verifiable online (DOI/proceedings) with student as author | E32: Papers (count) | F32: 1 | G32: 5 | H32: Verify every claimed paper (or at least 5) | I32: Meets benchmark, all verified | J32: Slightly below | K32: Well below | L32: None verified | P32: No. | Q32: 5 | T32: =IF(OR(S32="",R32="",R32=0),"",ROUND(Q32*MIN(S32/R32,1),2)) | U32: =IF(T32="","",ROUND(T32/Q32*100,2)) | V32: =IF(U32="","",IF(U32>YT*100,"Y",IF(U32>=CT*100,"C",IF(U32>=WT*100,"W","D")))) | W32: =IF($V32="Y",1,"") | X32: =IF($V32="C",1,"") | Y32: =IF($V32="W",1,"") | Z32: =IF($V32="D",1,"")
A33: C4 | B33: CRITERION 4 TOTAL | Q33: =Q8+Q10+Q13+Q16+Q19+Q22+Q27 -> 120 | T33: =T8+T10+T13+T16+T19+T22+T27 -> 0 | U33: =IF(T33=0,"",ROUND(T33/Q33*100,2)) | V33: =IF(U33="","",IF(U33>YT*100,"Y",IF(U33>=CT*100,"C",IF(U33>=WT*100,"W","D")))) | W33: =W8+W10+W13+W16+W19+W22+W27 -> 0 | X33: =X8+X10+X13+X16+X19+X22+X27 -> 0 | Y33: =Y8+Y10+Y13+Y16+Y19+Y22+Y27 -> 0 | Z33: =Z8+Z10+Z13+Z16+Z19+Z22+Z27 -> 0

Sheet C5 Validation Rubrics
A1: CRITERION 5 - FACULTY INFORMATION - VALIDATION RUBRICS AND SAMPLE SIZES (physical audit)
A2: Sampling: check at least the Sample % of the population, but never fewer than the Minimum (check all items if the population is smaller). Sample % and Minimum are defaults - IQAC may change them.
A3: For % indicators: Validated value = Valid items / Items checked x 100. For count indicators: Validated value = number of claimed items found valid.
A4: Enter the Benchmark (col R) and Validated value (col S) here. Marks, Percentage and Grade (Y > 75, C 60-75, W 40-60, D < 40) are calculated automatically and flow to the C5 Quantitative and All Criteria tabs.
A5: Yellow/blue = input: Items checked, Valid items, Auditor remarks, Benchmark, Validated value (and Sample % / Minimum if IQAC changes them).
A7: Code | B7: Key aspect | C7: What the auditor verifies | D7: An item counts as valid only if | E7: Sampling unit | F7: Sample % | G7: Minimum sample | H7: How to sample | I7: Y (> 75%) | J7: C (60-75%) | K7: W (40-60%) | L7: D (< 40%) | M7: Items checked | N7: Valid items | O7: Auditor remarks | P7: Unit | Q7: Max marks | R7: Benchmark | S7: Validated value | T7: Marks obtained | U7: Percentage | V7: Grade | W7: Y | X7: C | Y7: W | Z7: D
A8: 5.1 | B8: Student-faculty ratio | Q8: =SUM(Q9) -> 30 | T8: =SUM(T9) -> 0 | U8: =IF(COUNT(T9)=0,"",ROUND(T8/Q8*100,2)) | V8: =IF(U8="","",IF(U8>YT*100,"Y",IF(U8>=CT*100,"C",IF(U8>=WT*100,"W","D")))) | W8: =SUM(W9) -> 0 | X8: =SUM(X9) -> 0 | Y8: =SUM(Y9) -> 0 | Z8: =SUM(Z9) -> 0
A9: 5.1.a | B9: Faculty adequacy for SFR norm | C9: Faculty adequacy for SFR | D9: Faculty on roll: appointment order + salary/attendance proof for the period | E9: Faculty | F9: 0.2 | G9: 5 | H9: Random faculty from the claimed list; check payroll and attendance | I9: Adequate, all verified | J9: Slight shortfall | K9: Significant shortfall | L9: Large shortfall or unverifiable | P9: % | Q9: 30 | T9: =IF(OR(S9="",R9="",R9=0),"",ROUND(Q9*MIN(S9/R9,1),2)) | U9: =IF(T9="","",ROUND(T9/Q9*100,2)) | V9: =IF(U9="","",IF(U9>YT*100,"Y",IF(U9>=CT*100,"C",IF(U9>=WT*100,"W","D")))) | W9: =IF($V9="Y",1,"") | X9: =IF($V9="C",1,"") | Y9: =IF($V9="W",1,"") | Z9: =IF($V9="D",1,"")
A10: 5.2 | B10: Faculty qualification | Q10: =SUM(Q11:Q12) -> 25 | T10: =SUM(T11:T12) -> 0 | U10: =IF(COUNT(T11:T12)=0,"",ROUND(T10/Q10*100,2)) | V10: =IF(U10="","",IF(U10>YT*100,"Y",IF(U10>=CT*100,"C",IF(U10>=WT*100,"W","D")))) | W10: =SUM(W11:W12) -> 0 | X10: =SUM(X11:X12) -> 0 | Y10: =SUM(Y11:Y12) -> 0 | Z10: =SUM(Z11:Z12) -> 0
A11: 5.2.a | B11: Faculty with Ph.D. | C11: Faculty with Ph.D. | D11: Ph.D. degree certificate / provisional verified | E11: Faculty | F11: 0.25 | G11: 5 | H11: Random Ph.D. holders from claimed list | I11: All verified | J11: Most verified | K11: Several unverifiable | L11: Mostly unverifiable | P11: % | Q11: 15 | T11: =IF(OR(S11="",R11="",R11=0),"",ROUND(Q11*MIN(S11/R11,1),2)) | U11: =IF(T11="","",ROUND(T11/Q11*100,2)) | V11: =IF(U11="","",IF(U11>YT*100,"Y",IF(U11>=CT*100,"C",IF(U11>=WT*100,"W","D")))) | W11: =IF($V11="Y",1,"") | X11: =IF($V11="C",1,"") | Y11: =IF($V11="W",1,"") | Z11: =IF($V11="D",1,"")
A12: 5.2.b | B12: Faculty pursuing Ph.D. | C12: Faculty pursuing Ph.D. | D12: Registration letter from university with current status | E12: Faculty | F12: 0.25 | G12: 5 | H12: Random faculty from claimed list | I12: All registered, progress current | J12: Registered; progress records partial | K12: Several registrations lapsed | L12: Unverifiable | P12: % | Q12: 10 | T12: =IF(OR(S12="",R12="",R12=0),"",ROUND(Q12*MIN(S12/R12,1),2)) | U12: =IF(T12="","",ROUND(T12/Q12*100,2)) | V12: =IF(U12="","",IF(U12>YT*100,"Y",IF(U12>=CT*100,"C",IF(U12>=WT*100,"W","D")))) | W12: =IF($V12="Y",1,"") | X12: =IF($V12="C",1,"") | Y12: =IF($V12="W",1,"") | Z12: =IF($V12="D",1,"")
A13: 5.3 | B13: Faculty cadre proportion | Q13: =SUM(Q14:Q16) -> 25 | T13: =SUM(T14:T16) -> 0 | U13: =IF(COUNT(T14:T16)=0,"",ROUND(T13/Q13*100,2)) | V13: =IF(U13="","",IF(U13>YT*100,"Y",IF(U13>=CT*100,"C",IF(U13>=WT*100,"W","D")))) | W13: =SUM(W14:W16) -> 0 | X13: =SUM(X14:X16) -> 0 | Y13: =SUM(Y14:Y16) -> 0 | Z13: =SUM(Z14:Z16) -> 0
A14: 5.3.a | B14: Professors | C14: Professors | D14: Appointment order and qualification meet AICTE cadre norms | E14: Professors | F14: 1 | G14: 2 | H14: Verify every Professor claimed | I14: Cadre requirement met, all verified | J14: Slight shortfall | K14: Significant shortfall | L14: None qualified | P14: % | Q14: 10 | T14: =IF(OR(S14="",R14="",R14=0),"",ROUND(Q14*MIN(S14/R14,1),2)) | U14: =IF(T14="","",ROUND(T14/Q14*100,2)) | V14: =IF(U14="","",IF(U14>YT*100,"Y",IF(U14>=CT*100,"C",IF(U14>=WT*100,"W","D")))) | W14: =IF($V14="Y",1,"") | X14: =IF($V14="C",1,"") | Y14: =IF($V14="W",1,"") | Z14: =IF($V14="D",1,"")
A15: 5.3.b | B15: Associate Professors | C15: Associate Professors | D15: Appointment order and qualification meet AICTE cadre norms | E15: Associate Professors | F15: 0.5 | G15: 3 | H15: Random Associate Professors | I15: Cadre requirement met | J15: Slight shortfall | K15: Significant shortfall | L15: Large shortfall | P15: % | Q15: 10 | T15: =IF(OR(S15="",R15="",R15=0),"",ROUND(Q15*MIN(S15/R15,1),2)) | U15: =IF(T15="","",ROUND(T15/Q15*100,2)) | V15: =IF(U15="","",IF(U15>YT*100,"Y",IF(U15>=CT*100,"C",IF(U15>=WT*100,"W","D")))) | W15: =IF($V15="Y",1,"") | X15: =IF($V15="C",1,"") | Y15: =IF($V15="W",1,"") | Z15: =IF($V15="D",1,"")
A16: 5.3.c | B16: Assistant Professors | C16: Assistant Professors | D16: Appointment order and qualification meet AICTE norms | E16: Assistant Professors | F16: 0.2 | G16: 5 | H16: Random Assistant Professors | I16: Cadre requirement met | J16: Slight shortfall | K16: Significant shortfall | L16: Large shortfall | P16: % | Q16: 5 | T16: =IF(OR(S16="",R16="",R16=0),"",ROUND(Q16*MIN(S16/R16,1),2)) | U16: =IF(T16="","",ROUND(T16/Q16*100,2)) | V16: =IF(U16="","",IF(U16>YT*100,"Y",IF(U16>=CT*100,"C",IF(U16>=WT*100,"W","D")))) | W16: =IF($V16="Y",1,"") | X16: =IF($V16="C",1,"") | Y16: =IF($V16="W",1,"") | Z16: =IF($V16="D",1,"")
A17: 5.4 | B17: Visiting / adjunct faculty / professor of practice | Q17: =SUM(Q18) -> 10 | T17: =SUM(T18) -> 0 | U17: =IF(COUNT(T18)=0,"",ROUND(T17/Q17*100,2)) | V17: =IF(U17="","",IF(U17>YT*100,"Y",IF(U17>=CT*100,"C",IF(U17>=WT*100,"W","D")))) | W17: =SUM(W18) -> 0 | X17: =SUM(X18) -> 0 | Y17: =SUM(Y18) -> 0 | Z17: =SUM(Z18) -> 0
A18: 5.4.a | B18: Visiting / adjunct contact hours | C18: Visiting / adjunct contact hours | D18: Appointment letter + timetable + attendance for sessions handled | E18: Sessions | F18: 0.25 | G18: 5 | H18: Random sessions from claimed hours log | I18: Hours meet target, verified | J18: Slightly below target | K18: Well below target | L18: Little or none | P18: % | Q18: 10 | T18: =IF(OR(S18="",R18="",R18=0),"",ROUND(Q18*MIN(S18/R18,1),2)) | U18: =IF(T18="","",ROUND(T18/Q18*100,2)) | V18: =IF(U18="","",IF(U18>YT*100,"Y",IF(U18>=CT*100,"C",IF(U18>=WT*100,"W","D")))) | W18: =IF($V18="Y",1,"") | X18: =IF($V18="C",1,"") | Y18: =IF($V18="W",1,"") | Z18: =IF($V18="D",1,"")
A19: 5.5 | B19: Faculty retention | Q19: =SUM(Q20) -> 10 | T19: =SUM(T20) -> 0 | U19: =IF(COUNT(T20)=0,"",ROUND(T19/Q19*100,2)) | V19: =IF(U19="","",IF(U19>YT*100,"Y",IF(U19>=CT*100,"C",IF(U19>=WT*100,"W","D")))) | W19: =SUM(W20) -> 0 | X19: =SUM(X20) -> 0 | Y19: =SUM(Y20) -> 0 | Z19: =SUM(Z20) -> 0
A20: 5.5.a | B20: Faculty retention | C20: Faculty retention | D20: Faculty on roll at start and still on roll after 2 years (payroll) | E20: Faculty | F20: 0.2 | G20: 5 | H20: Random faculty from start-of-period list | I20: Retention high, verified | J20: Moderate retention | K20: Low retention | L20: Very low retention | P20: % | Q20: 10 | T20: =IF(OR(S20="",R20="",R20=0),"",ROUND(Q20*MIN(S20/R20,1),2)) | U20: =IF(T20="","",ROUND(T20/Q20*100,2)) | V20: =IF(U20="","",IF(U20>YT*100,"Y",IF(U20>=CT*100,"C",IF(U20>=WT*100,"W","D")))) | W20: =IF($V20="Y",1,"") | X20: =IF($V20="C",1,"") | Y20: =IF($V20="W",1,"") | Z20: =IF($V20="D",1,"")
A21: C5 | B21: CRITERION 5 TOTAL | Q21: =Q8+Q10+Q13+Q17+Q19 -> 100 | T21: =T8+T10+T13+T17+T19 -> 0 | U21: =IF(T21=0,"",ROUND(T21/Q21*100,2)) | V21: =IF(U21="","",IF(U21>YT*100,"Y",IF(U21>=CT*100,"C",IF(U21>=WT*100,"W","D")))) | W21: =W8+W10+W13+W17+W19 -> 0 | X21: =X8+X10+X13+X17+X19 -> 0 | Y21: =Y8+Y10+Y13+Y17+Y19 -> 0 | Z21: =Z8+Z10+Z13+Z17+Z19 -> 0

Sheet C6 Validation Rubrics
A1: CRITERION 6 - FACULTY CONTRIBUTIONS - VALIDATION RUBRICS AND SAMPLE SIZES (physical audit)
A2: Sampling: check at least the Sample % of the population, but never fewer than the Minimum (check all items if the population is smaller). Sample % and Minimum are defaults - IQAC may change them.
A3: For % indicators: Validated value = Valid items / Items checked x 100. For count indicators: Validated value = number of claimed items found valid.
A4: Enter the Benchmark (col R) and Validated value (col S) here. Marks, Percentage and Grade (Y > 75, C 60-75, W 40-60, D < 40) are calculated automatically and flow to the C6 Quantitative and All Criteria tabs.
A5: Yellow/blue = input: Items checked, Valid items, Auditor remarks, Benchmark, Validated value (and Sample % / Minimum if IQAC changes them).
A7: Code | B7: Key aspect | C7: What the auditor verifies | D7: An item counts as valid only if | E7: Sampling unit | F7: Sample % | G7: Minimum sample | H7: How to sample | I7: Y (> 75%) | J7: C (60-75%) | K7: W (40-60%) | L7: D (< 40%) | M7: Items checked | N7: Valid items | O7: Auditor remarks | P7: Unit | Q7: Max marks | R7: Benchmark | S7: Validated value | T7: Marks obtained | U7: Percentage | V7: Grade | W7: Y | X7: C | Y7: W | Z7: D
A8: 6.1 | B8: Professional development activities | Q8: =SUM(Q9:Q16) -> 60 | T8: =SUM(T9:T16) -> 0 | U8: =IF(COUNT(T9:T16)=0,"",ROUND(T8/Q8*100,2)) | V8: =IF(U8="","",IF(U8>YT*100,"Y",IF(U8>=CT*100,"C",IF(U8>=WT*100,"W","D")))) | W8: =SUM(W9:W16) -> 0 | X8: =SUM(X9:X16) -> 0 | Y8: =SUM(Y9:Y16) -> 0 | Z8: =SUM(Z9:Z16) -> 0
A9: 6.1.a | B9: Professional society membership (6.1.1) | C9: Professional society membership | D9: Valid membership card/receipt for the period | E9: Faculty | F9: 0.2 | G9: 5 | H9: Random faculty from claimed list | I9: All memberships active | J9: Most active | K9: Several lapsed | L9: Mostly lapsed or none | P9: % | Q9: 5 | T9: =IF(OR(S9="",R9="",R9=0),"",ROUND(Q9*MIN(S9/R9,1),2)) | U9: =IF(T9="","",ROUND(T9/Q9*100,2)) | V9: =IF(U9="","",IF(U9>YT*100,"Y",IF(U9>=CT*100,"C",IF(U9>=WT*100,"W","D")))) | W9: =IF($V9="Y",1,"") | X9: =IF($V9="C",1,"") | Y9: =IF($V9="W",1,"") | Z9: =IF($V9="D",1,"")
A10: 6.1.b | B10: Faculty as resource persons (6.1.2.1) | C10: Faculty as resource persons | D10: Invitation letter + certificate/letter of thanks from host | E10: Engagements (count) | F10: 1 | G10: 5 | H10: Verify every claim (or at least 5) | I10: Meets benchmark, verified | J10: Slightly below | K10: Well below | L10: None verified | P10: No. | Q10: 5 | T10: =IF(OR(S10="",R10="",R10=0),"",ROUND(Q10*MIN(S10/R10,1),2)) | U10: =IF(T10="","",ROUND(T10/Q10*100,2)) | V10: =IF(U10="","",IF(U10>YT*100,"Y",IF(U10>=CT*100,"C",IF(U10>=WT*100,"W","D")))) | W10: =IF($V10="Y",1,"") | X10: =IF($V10="C",1,"") | Y10: =IF($V10="W",1,"") | Z10: =IF($V10="D",1,"")
A11: 6.1.c | B11: Faculty attending FDP/STTP (6.1.2.2) | C11: Faculty attending FDP/STTP | D11: Certificate of completion for programme of required duration | E11: Faculty | F11: 0.2 | G11: 5 | H11: Random faculty from claimed list | I11: All verified | J11: Most verified | K11: Several unverifiable | L11: Mostly unverifiable | P11: % | Q11: 5 | T11: =IF(OR(S11="",R11="",R11=0),"",ROUND(Q11*MIN(S11/R11,1),2)) | U11: =IF(T11="","",ROUND(T11/Q11*100,2)) | V11: =IF(U11="","",IF(U11>YT*100,"Y",IF(U11>=CT*100,"C",IF(U11>=WT*100,"W","D")))) | W11: =IF($V11="Y",1,"") | X11: =IF($V11="C",1,"") | Y11: =IF($V11="W",1,"") | Z11: =IF($V11="D",1,"")
A12: 6.1.d | B12: E-content / MOOCs developed (6.1.3) | C12: E-content / MOOCs developed | D12: Content accessible online (link/LMS) with faculty as author | E12: Modules (count) | F12: 1 | G12: 3 | H12: Verify every claim; open 2 modules | I12: Meets benchmark, content live | J12: Slightly below | K12: Well below | L12: None verified | P12: No. | Q12: 7 | T12: =IF(OR(S12="",R12="",R12=0),"",ROUND(Q12*MIN(S12/R12,1),2)) | U12: =IF(T12="","",ROUND(T12/Q12*100,2)) | V12: =IF(U12="","",IF(U12>YT*100,"Y",IF(U12>=CT*100,"C",IF(U12>=WT*100,"W","D")))) | W12: =IF($V12="Y",1,"") | X12: =IF($V12="C",1,"") | Y12: =IF($V12="W",1,"") | Z12: =IF($V12="D",1,"")
A13: 6.1.e | B13: Faculty MOOC certification (6.1.4) | C13: Faculty MOOC certification | D13: Certificate verifiable on NPTEL/SWAYAM/platform portal | E13: Faculty | F13: 0.2 | G13: 5 | H13: Random certified faculty; verify online | I13: All verified | J13: Most verified | K13: Several unverifiable | L13: Mostly unverifiable | P13: % | Q13: 8 | T13: =IF(OR(S13="",R13="",R13=0),"",ROUND(Q13*MIN(S13/R13,1),2)) | U13: =IF(T13="","",ROUND(T13/Q13*100,2)) | V13: =IF(U13="","",IF(U13>YT*100,"Y",IF(U13>=CT*100,"C",IF(U13>=WT*100,"W","D")))) | W13: =IF($V13="Y",1,"") | X13: =IF($V13="C",1,"") | Y13: =IF($V13="W",1,"") | Z13: =IF($V13="D",1,"")
A14: 6.1.f | B14: FDP/STTP organised (6.1.5) | C14: FDP/STTP organised | D14: Approval, brochure, schedule, attendance, feedback and report | E14: Programmes (count) | F14: 1 | G14: 3 | H14: Verify every claimed programme | I14: Meets benchmark, full documentation | J14: Slightly below | K14: Well below | L14: None | P14: No. | Q14: 10 | T14: =IF(OR(S14="",R14="",R14=0),"",ROUND(Q14*MIN(S14/R14,1),2)) | U14: =IF(T14="","",ROUND(T14/Q14*100,2)) | V14: =IF(U14="","",IF(U14>YT*100,"Y",IF(U14>=CT*100,"C",IF(U14>=WT*100,"W","D")))) | W14: =IF($V14="Y",1,"") | X14: =IF($V14="C",1,"") | Y14: =IF($V14="W",1,"") | Z14: =IF($V14="D",1,"")
A15: 6.1.g | B15: Student innovative projects supported (6.1.6) | C15: Student innovative projects supported | D15: Project record with guide name and outcome (prototype/award/paper) | E15: Projects (count) | F15: 1 | G15: 5 | H15: Verify every claim (or at least 5); see 2 prototypes | I15: Meets benchmark, verified | J15: Slightly below | K15: Well below | L15: None verified | P15: No. | Q15: 10 | T15: =IF(OR(S15="",R15="",R15=0),"",ROUND(Q15*MIN(S15/R15,1),2)) | U15: =IF(T15="","",ROUND(T15/Q15*100,2)) | V15: =IF(U15="","",IF(U15>YT*100,"Y",IF(U15>=CT*100,"C",IF(U15>=WT*100,"W","D")))) | W15: =IF($V15="Y",1,"") | X15: =IF($V15="C",1,"") | Y15: =IF($V15="W",1,"") | Z15: =IF($V15="D",1,"")
A16: 6.1.h | B16: Faculty industry internship / training (6.1.7) | C16: Faculty industry internship / training | D16: Industry letter/certificate with duration and work done | E16: Faculty | F16: 0.25 | G16: 3 | H16: Random faculty from claimed list | I16: All verified | J16: Most verified | K16: Several unverifiable | L16: Mostly unverifiable | P16: % | Q16: 10 | T16: =IF(OR(S16="",R16="",R16=0),"",ROUND(Q16*MIN(S16/R16,1),2)) | U16: =IF(T16="","",ROUND(T16/Q16*100,2)) | V16: =IF(U16="","",IF(U16>YT*100,"Y",IF(U16>=CT*100,"C",IF(U16>=WT*100,"W","D")))) | W16: =IF($V16="Y",1,"") | X16: =IF($V16="C",1,"") | Y16: =IF($V16="W",1,"") | Z16: =IF($V16="D",1,"")
A17: 6.2 | B17: Research and development activities | Q17: =SUM(Q18:Q24) -> 60 | T17: =SUM(T18:T24) -> 0 | U17: =IF(COUNT(T18:T24)=0,"",ROUND(T17/Q17*100,2)) | V17: =IF(U17="","",IF(U17>YT*100,"Y",IF(U17>=CT*100,"C",IF(U17>=WT*100,"W","D")))) | W17: =SUM(W18:W24) -> 0 | X17: =SUM(X18:X24) -> 0 | Y17: =SUM(Y18:Y24) -> 0 | Z17: =SUM(Z18:Z24) -> 0
A18: 6.2.a | B18: Indexed publications (6.2.1) | C18: Indexed publications | D18: Paper listed in Scopus/WoS with faculty affiliation to institute | E18: Papers (count) | F18: 0.25 | G18: 10 | H18: Random papers; verify in Scopus/WoS | I18: Meets benchmark, all indexed | J18: Slightly below | K18: Well below or many not indexed | L18: None verified | P18: No. | Q18: 6 | T18: =IF(OR(S18="",R18="",R18=0),"",ROUND(Q18*MIN(S18/R18,1),2)) | U18: =IF(T18="","",ROUND(T18/Q18*100,2)) | V18: =IF(U18="","",IF(U18>YT*100,"Y",IF(U18>=CT*100,"C",IF(U18>=WT*100,"W","D")))) | W18: =IF($V18="Y",1,"") | X18: =IF($V18="C",1,"") | Y18: =IF($V18="W",1,"") | Z18: =IF($V18="D",1,"")
A19: 6.2.b | B19: Patents (6.2.1) | C19: Patents | D19: Filing/publication/grant number verifiable on IP India/other office | E19: Patents (count) | F19: 0.5 | G19: 5 | H19: Random patents; verify on IP portal | I19: Meets benchmark, all verified | J19: Slightly below | K19: Well below | L19: None verified | P19: No. | Q19: 4 | T19: =IF(OR(S19="",R19="",R19=0),"",ROUND(Q19*MIN(S19/R19,1),2)) | U19: =IF(T19="","",ROUND(T19/Q19*100,2)) | V19: =IF(U19="","",IF(U19>YT*100,"Y",IF(U19>=CT*100,"C",IF(U19>=WT*100,"W","D")))) | W19: =IF($V19="Y",1,"") | X19: =IF($V19="C",1,"") | Y19: =IF($V19="W",1,"") | Z19: =IF($V19="D",1,"")
A20: 6.2.c | B20: Ph.D. scholars (6.2.2) | C20: Ph.D. scholars | D20: University registration/award letter naming faculty as supervisor | E20: Scholars (count) | F20: 1 | G20: 3 | H20: Verify every claim | I20: Meets benchmark, verified | J20: Slightly below | K20: Well below | L20: None verified | P20: No. | Q20: 5 | T20: =IF(OR(S20="",R20="",R20=0),"",ROUND(Q20*MIN(S20/R20,1),2)) | U20: =IF(T20="","",ROUND(T20/Q20*100,2)) | V20: =IF(U20="","",IF(U20>YT*100,"Y",IF(U20>=CT*100,"C",IF(U20>=WT*100,"W","D")))) | W20: =IF($V20="Y",1,"") | X20: =IF($V20="C",1,"") | Y20: =IF($V20="W",1,"") | Z20: =IF($V20="D",1,"")
A21: 6.2.d | B21: Development activities (6.2.3) | C21: Development activities | D21: Product/lab set-up/material physically seen or accessible with record | E21: Items (count) | F21: 1 | G21: 3 | H21: Verify every claim; inspect 2 items | I21: Meets benchmark, verified | J21: Slightly below | K21: Well below | L21: None verified | P21: No. | Q21: 10 | T21: =IF(OR(S21="",R21="",R21=0),"",ROUND(Q21*MIN(S21/R21,1),2)) | U21: =IF(T21="","",ROUND(T21/Q21*100,2)) | V21: =IF(U21="","",IF(U21>YT*100,"Y",IF(U21>=CT*100,"C",IF(U21>=WT*100,"W","D")))) | W21: =IF($V21="Y",1,"") | X21: =IF($V21="C",1,"") | Y21: =IF($V21="W",1,"") | Z21: =IF($V21="D",1,"")
A22: 6.2.e | B22: Sponsored research (6.2.4) | C22: Sponsored research | D22: Sanction letter + fund receipt in institute account (Rs. lakhs) | E22: Projects | F22: 1 | G22: 3 | H22: Verify every claimed grant; match with accounts | I22: Amount meets benchmark, all verified | J22: Slightly below | K22: Well below | L22: Unverifiable | P22: No. | Q22: 15 | T22: =IF(OR(S22="",R22="",R22=0),"",ROUND(Q22*MIN(S22/R22,1),2)) | U22: =IF(T22="","",ROUND(T22/Q22*100,2)) | V22: =IF(U22="","",IF(U22>YT*100,"Y",IF(U22>=CT*100,"C",IF(U22>=WT*100,"W","D")))) | W22: =IF($V22="Y",1,"") | X22: =IF($V22="C",1,"") | Y22: =IF($V22="W",1,"") | Z22: =IF($V22="D",1,"")
A23: 6.2.f | B23: Consultancy (6.2.5) | C23: Consultancy | D23: Work order + invoice + payment receipt in institute account (Rs. lakhs) | E23: Assignments | F23: 1 | G23: 3 | H23: Verify every claim; match with accounts | I23: Amount meets benchmark, all verified | J23: Slightly below | K23: Well below | L23: Unverifiable | P23: No. | Q23: 15 | T23: =IF(OR(S23="",R23="",R23=0),"",ROUND(Q23*MIN(S23/R23,1),2)) | U23: =IF(T23="","",ROUND(T23/Q23*100,2)) | V23: =IF(U23="","",IF(U23>YT*100,"Y",IF(U23>=CT*100,"C",IF(U23>=WT*100,"W","D")))) | W23: =IF($V23="Y",1,"") | X23: =IF($V23="C",1,"") | Y23: =IF($V23="W",1,"") | Z23: =IF($V23="D",1,"")
A24: 6.2.g | B24: Seed money (6.2.6) | C24: Seed money | D24: Sanction order + utilisation certificate (Rs. lakhs) | E24: Grants | F24: 1 | G24: 3 | H24: Verify every grant | I24: Amount meets benchmark, utilised | J24: Slightly below | K24: Well below | L24: None | P24: No. | Q24: 5 | T24: =IF(OR(S24="",R24="",R24=0),"",ROUND(Q24*MIN(S24/R24,1),2)) | U24: =IF(T24="","",ROUND(T24/Q24*100,2)) | V24: =IF(U24="","",IF(U24>YT*100,"Y",IF(U24>=CT*100,"C",IF(U24>=WT*100,"W","D")))) | W24: =IF($V24="Y",1,"") | X24: =IF($V24="C",1,"") | Y24: =IF($V24="W",1,"") | Z24: =IF($V24="D",1,"")
A25: C6 | B25: CRITERION 6 TOTAL | Q25: =Q8+Q17 -> 120 | T25: =T8+T17 -> 0 | U25: =IF(T25=0,"",ROUND(T25/Q25*100,2)) | V25: =IF(U25="","",IF(U25>YT*100,"Y",IF(U25>=CT*100,"C",IF(U25>=WT*100,"W","D")))) | W25: =W8+W17 -> 0 | X25: =X8+X17 -> 0 | Y25: =Y8+Y17 -> 0 | Z25: =Z8+Z17 -> 0

Sheet C7 Validation Rubrics
A1: CRITERION 7 - FACILITIES AND TECHNICAL SUPPORT - VALIDATION RUBRICS AND SAMPLE SIZES (physical audit)
A2: Sampling: check at least the Sample % of the population, but never fewer than the Minimum (check all items if the population is smaller). Sample % and Minimum are defaults - IQAC may change them.
A3: For % indicators: Validated value = Valid items / Items checked x 100. For count indicators: Validated value = number of claimed items found valid.
A4: Enter the Benchmark (col R) and Validated value (col S) here. Marks, Percentage and Grade (Y > 75, C 60-75, W 40-60, D < 40) are calculated automatically and flow to the C7 Quantitative and All Criteria tabs.
A5: Yellow/blue = input: Items checked, Valid items, Auditor remarks, Benchmark, Validated value (and Sample % / Minimum if IQAC changes them).
A7: Code | B7: Key aspect | C7: What the auditor verifies | D7: An item counts as valid only if | E7: Sampling unit | F7: Sample % | G7: Minimum sample | H7: How to sample | I7: Y (> 75%) | J7: C (60-75%) | K7: W (40-60%) | L7: D (< 40%) | M7: Items checked | N7: Valid items | O7: Auditor remarks | P7: Unit | Q7: Max marks | R7: Benchmark | S7: Validated value | T7: Marks obtained | U7: Percentage | V7: Grade | W7: Y | X7: C | Y7: W | Z7: D
A8: 7.1 | B8: Laboratories and technical manpower | Q8: =SUM(Q9:Q12) -> 40 | T8: =SUM(T9:T12) -> 0 | U8: =IF(COUNT(T9:T12)=0,"",ROUND(T8/Q8*100,2)) | V8: =IF(U8="","",IF(U8>YT*100,"Y",IF(U8>=CT*100,"C",IF(U8>=WT*100,"W","D")))) | W8: =SUM(W9:W12) -> 0 | X8: =SUM(X9:X12) -> 0 | Y8: =SUM(Y9:Y12) -> 0 | Z8: =SUM(Z9:Z12) -> 0
A9: 7.1.a | B9: Labs as per curriculum | C9: Labs as per curriculum | D9: Lab exists with equipment to run all listed experiments | E9: Labs | F9: 0.5 | G9: 3 | H9: Visit random labs; run 1 experiment list check per lab | I9: All required labs available | J9: One lab partly equipped | K9: Several gaps | L9: Labs missing | P9: % | Q9: 10 | T9: =IF(OR(S9="",R9="",R9=0),"",ROUND(Q9*MIN(S9/R9,1),2)) | U9: =IF(T9="","",ROUND(T9/Q9*100,2)) | V9: =IF(U9="","",IF(U9>YT*100,"Y",IF(U9>=CT*100,"C",IF(U9>=WT*100,"W","D")))) | W9: =IF($V9="Y",1,"") | X9: =IF($V9="C",1,"") | Y9: =IF($V9="W",1,"") | Z9: =IF($V9="D",1,"")
A10: 7.1.b | B10: Equipment in working condition | C10: Equipment in working condition | D10: Item in stock register found and working on demonstration | E10: Equipment items | F10: 0.05 | G10: 15 | H10: Random items from stock register across labs | I10: All sampled working | J10: Few not working, repair logged | K10: Many not working | L10: Mostly not working | P10: % | Q10: 10 | T10: =IF(OR(S10="",R10="",R10=0),"",ROUND(Q10*MIN(S10/R10,1),2)) | U10: =IF(T10="","",ROUND(T10/Q10*100,2)) | V10: =IF(U10="","",IF(U10>YT*100,"Y",IF(U10>=CT*100,"C",IF(U10>=WT*100,"W","D")))) | W10: =IF($V10="Y",1,"") | X10: =IF($V10="C",1,"") | Y10: =IF($V10="W",1,"") | Z10: =IF($V10="D",1,"")
A11: 7.1.c | B11: Lab batch size within norm | C11: Lab batch size within norm | D11: Session attendance shows batch within norm | E11: Lab sessions | F11: 0.1 | G11: 10 | H11: Random lab sessions from timetable and attendance | I11: All within norm | J11: Few exceed | K11: Many exceed | L11: Mostly exceed | P11: % | Q11: 10 | T11: =IF(OR(S11="",R11="",R11=0),"",ROUND(Q11*MIN(S11/R11,1),2)) | U11: =IF(T11="","",ROUND(T11/Q11*100,2)) | V11: =IF(U11="","",IF(U11>YT*100,"Y",IF(U11>=CT*100,"C",IF(U11>=WT*100,"W","D")))) | W11: =IF($V11="Y",1,"") | X11: =IF($V11="C",1,"") | Y11: =IF($V11="W",1,"") | Z11: =IF($V11="D",1,"")
A12: 7.1.d | B12: Technical staff adequacy | C12: Technical staff adequacy | D12: Appointment order + attendance + qualification for staff claimed | E12: Technical staff | F12: 0.5 | G12: 3 | H12: Verify random staff; meet them in labs | I12: Adequate and qualified | J12: Slight shortfall | K12: Significant shortfall | L12: Large shortfall | P12: % | Q12: 10 | T12: =IF(OR(S12="",R12="",R12=0),"",ROUND(Q12*MIN(S12/R12,1),2)) | U12: =IF(T12="","",ROUND(T12/Q12*100,2)) | V12: =IF(U12="","",IF(U12>YT*100,"Y",IF(U12>=CT*100,"C",IF(U12>=WT*100,"W","D")))) | W12: =IF($V12="Y",1,"") | X12: =IF($V12="C",1,"") | Y12: =IF($V12="W",1,"") | Z12: =IF($V12="D",1,"")
A13: 7.2 | B13: Additional facilities in laboratories | Q13: =SUM(Q14:Q15) -> 20 | T13: =SUM(T14:T15) -> 0 | U13: =IF(COUNT(T14:T15)=0,"",ROUND(T13/Q13*100,2)) | V13: =IF(U13="","",IF(U13>YT*100,"Y",IF(U13>=CT*100,"C",IF(U13>=WT*100,"W","D")))) | W13: =SUM(W14:W15) -> 0 | X13: =SUM(X14:X15) -> 0 | Y13: =SUM(Y14:Y15) -> 0 | Z13: =SUM(Z14:Z15) -> 0
A14: 7.2.a | B14: Additional facilities beyond curriculum | C14: Additional facilities beyond curriculum | D14: Facility physically present with purchase record and usage log | E14: Facilities (count) | F14: 1 | G14: 3 | H14: Verify every claimed facility | I14: Meets benchmark, in use | J14: Slightly below | K14: Well below | L14: None | P14: No. | Q14: 10 | T14: =IF(OR(S14="",R14="",R14=0),"",ROUND(Q14*MIN(S14/R14,1),2)) | U14: =IF(T14="","",ROUND(T14/Q14*100,2)) | V14: =IF(U14="","",IF(U14>YT*100,"Y",IF(U14>=CT*100,"C",IF(U14>=WT*100,"W","D")))) | W14: =IF($V14="Y",1,"") | X14: =IF($V14="C",1,"") | Y14: =IF($V14="W",1,"") | Z14: =IF($V14="D",1,"")
A15: 7.2.b | B15: Use of additional facilities | C15: Use of additional facilities | D15: Usage log entries with names, dates and purpose | E15: Log entries | F15: 0.1 | G15: 10 | H15: Random log entries; cross-check with student lists | I15: High, genuine use | J15: Moderate use | K15: Low use | L15: No usage log | P15: % | Q15: 10 | T15: =IF(OR(S15="",R15="",R15=0),"",ROUND(Q15*MIN(S15/R15,1),2)) | U15: =IF(T15="","",ROUND(T15/Q15*100,2)) | V15: =IF(U15="","",IF(U15>YT*100,"Y",IF(U15>=CT*100,"C",IF(U15>=WT*100,"W","D")))) | W15: =IF($V15="Y",1,"") | X15: =IF($V15="C",1,"") | Y15: =IF($V15="W",1,"") | Z15: =IF($V15="D",1,"")
A16: 7.3 | B16: Laboratory maintenance and ambience | Q16: =SUM(Q17:Q18) -> 10 | T16: =SUM(T17:T18) -> 0 | U16: =IF(COUNT(T17:T18)=0,"",ROUND(T16/Q16*100,2)) | V16: =IF(U16="","",IF(U16>YT*100,"Y",IF(U16>=CT*100,"C",IF(U16>=WT*100,"W","D")))) | W16: =SUM(W17:W18) -> 0 | X16: =SUM(X17:X18) -> 0 | Y16: =SUM(Y17:Y18) -> 0 | Z16: =SUM(Z17:Z18) -> 0
A17: 7.3.a | B17: Maintenance and calibration up to date | C17: Maintenance and calibration | D17: Current maintenance/calibration record for the item | E17: Equipment items | F17: 0.05 | G17: 10 | H17: Random items; check AMC/calibration certificates | I17: All current | J17: Few overdue | K17: Many overdue | L17: No records | P17: % | Q17: 5 | T17: =IF(OR(S17="",R17="",R17=0),"",ROUND(Q17*MIN(S17/R17,1),2)) | U17: =IF(T17="","",ROUND(T17/Q17*100,2)) | V17: =IF(U17="","",IF(U17>YT*100,"Y",IF(U17>=CT*100,"C",IF(U17>=WT*100,"W","D")))) | W17: =IF($V17="Y",1,"") | X17: =IF($V17="C",1,"") | Y17: =IF($V17="W",1,"") | Z17: =IF($V17="D",1,"")
A18: 7.3.b | B18: Lab ambience | C18: Lab ambience | D18: Lab meets checklist (lighting, ventilation, seating, cleanliness, display) | E18: Labs | F18: 0.5 | G18: 3 | H18: Walk-through of random labs with checklist | I18: All meet checklist | J18: Minor gaps | K18: Several gaps | L18: Poor ambience | P18: % | Q18: 5 | T18: =IF(OR(S18="",R18="",R18=0),"",ROUND(Q18*MIN(S18/R18,1),2)) | U18: =IF(T18="","",ROUND(T18/Q18*100,2)) | V18: =IF(U18="","",IF(U18>YT*100,"Y",IF(U18>=CT*100,"C",IF(U18>=WT*100,"W","D")))) | W18: =IF($V18="Y",1,"") | X18: =IF($V18="C",1,"") | Y18: =IF($V18="W",1,"") | Z18: =IF($V18="D",1,"")
A19: 7.4 | B19: Safety measures in laboratories | Q19: =SUM(Q20) -> 10 | T19: =SUM(T20) -> 0 | U19: =IF(COUNT(T20)=0,"",ROUND(T19/Q19*100,2)) | V19: =IF(U19="","",IF(U19>YT*100,"Y",IF(U19>=CT*100,"C",IF(U19>=WT*100,"W","D")))) | W19: =SUM(W20) -> 0 | X19: =SUM(X20) -> 0 | Y19: =SUM(Y20) -> 0 | Z19: =SUM(Z20) -> 0
A20: 7.4.a | B20: Lab safety compliance | C20: Lab safety compliance | D20: Extinguisher (valid refill), first-aid, signage, SOP and emergency contact present | E20: Labs | F20: 0.5 | G20: 3 | H20: Walk-through of random labs with safety checklist | I20: All compliant | J20: Minor gaps | K20: Several gaps | L20: Unsafe | P20: % | Q20: 10 | T20: =IF(OR(S20="",R20="",R20=0),"",ROUND(Q20*MIN(S20/R20,1),2)) | U20: =IF(T20="","",ROUND(T20/Q20*100,2)) | V20: =IF(U20="","",IF(U20>YT*100,"Y",IF(U20>=CT*100,"C",IF(U20>=WT*100,"W","D")))) | W20: =IF($V20="Y",1,"") | X20: =IF($V20="C",1,"") | Y20: =IF($V20="W",1,"") | Z20: =IF($V20="D",1,"")
A21: 7.5 | B21: Project lab / research lab / Centre of Excellence | Q21: =SUM(Q22:Q24) -> 20 | T21: =SUM(T22:T24) -> 0 | U21: =IF(COUNT(T22:T24)=0,"",ROUND(T21/Q21*100,2)) | V21: =IF(U21="","",IF(U21>YT*100,"Y",IF(U21>=CT*100,"C",IF(U21>=WT*100,"W","D")))) | W21: =SUM(W22:W24) -> 0 | X21: =SUM(X22:X24) -> 0 | Y21: =SUM(Y22:Y24) -> 0 | Z21: =SUM(Z22:Z24) -> 0
A22: 7.5.a | B22: Project / research labs / CoE | C22: Project / research labs / CoE | D22: Lab/CoE physically present with MoU/approval and equipment list | E22: Labs (count) | F22: 1 | G22: 2 | H22: Visit every claimed lab/CoE | I22: Meets benchmark, active | J22: Slightly below | K22: Well below | L22: None | P22: No. | Q22: 8 | T22: =IF(OR(S22="",R22="",R22=0),"",ROUND(Q22*MIN(S22/R22,1),2)) | U22: =IF(T22="","",ROUND(T22/Q22*100,2)) | V22: =IF(U22="","",IF(U22>YT*100,"Y",IF(U22>=CT*100,"C",IF(U22>=WT*100,"W","D")))) | W22: =IF($V22="Y",1,"") | X22: =IF($V22="C",1,"") | Y22: =IF($V22="W",1,"") | Z22: =IF($V22="D",1,"")
A23: 7.5.b | B23: CoE utilisation | C23: CoE utilisation | D23: Usage log entries with names, dates and purpose | E23: Log entries | F23: 0.1 | G23: 10 | H23: Random log entries; cross-check with users | I23: High, genuine use | J23: Moderate use | K23: Low use | L23: No usage log | P23: % | Q23: 6 | T23: =IF(OR(S23="",R23="",R23=0),"",ROUND(Q23*MIN(S23/R23,1),2)) | U23: =IF(T23="","",ROUND(T23/Q23*100,2)) | V23: =IF(U23="","",IF(U23>YT*100,"Y",IF(U23>=CT*100,"C",IF(U23>=WT*100,"W","D")))) | W23: =IF($V23="Y",1,"") | X23: =IF($V23="C",1,"") | Y23: =IF($V23="W",1,"") | Z23: =IF($V23="D",1,"")
A24: 7.5.c | B24: CoE outputs | C24: CoE outputs | D24: Output (project/paper/certification) traceable to the CoE | E24: Outputs (count) | F24: 1 | G24: 5 | H24: Verify every claim (or at least 5) | I24: Meets benchmark, verified | J24: Slightly below | K24: Well below | L24: None verified | P24: No. | Q24: 6 | T24: =IF(OR(S24="",R24="",R24=0),"",ROUND(Q24*MIN(S24/R24,1),2)) | U24: =IF(T24="","",ROUND(T24/Q24*100,2)) | V24: =IF(U24="","",IF(U24>YT*100,"Y",IF(U24>=CT*100,"C",IF(U24>=WT*100,"W","D")))) | W24: =IF($V24="Y",1,"") | X24: =IF($V24="C",1,"") | Y24: =IF($V24="W",1,"") | Z24: =IF($V24="D",1,"")
A25: C7 | B25: CRITERION 7 TOTAL | Q25: =Q8+Q13+Q16+Q19+Q21 -> 100 | T25: =T8+T13+T16+T19+T21 -> 0 | U25: =IF(T25=0,"",ROUND(T25/Q25*100,2)) | V25: =IF(U25="","",IF(U25>YT*100,"Y",IF(U25>=CT*100,"C",IF(U25>=WT*100,"W","D")))) | W25: =W8+W13+W16+W19+W21 -> 0 | X25: =X8+X13+X16+X19+X21 -> 0 | Y25: =Y8+Y13+Y16+Y19+Y21 -> 0 | Z25: =Z8+Z13+Z16+Z19+Z21 -> 0

Sheet C8 Validation Rubrics
A1: CRITERION 8 - CONTINUOUS IMPROVEMENT - VALIDATION RUBRICS AND SAMPLE SIZES (physical audit)
A2: Sampling: check at least the Sample % of the population, but never fewer than the Minimum (check all items if the population is smaller). Sample % and Minimum are defaults - IQAC may change them.
A3: For % indicators: Validated value = Valid items / Items checked x 100. For count indicators: Validated value = number of claimed items found valid.
A4: Enter the Benchmark (col R) and Validated value (col S) here. Marks, Percentage and Grade (Y > 75, C 60-75, W 40-60, D < 40) are calculated automatically and flow to the C8 Quantitative and All Criteria tabs.
A5: Yellow/blue = input: Items checked, Valid items, Auditor remarks, Benchmark, Validated value (and Sample % / Minimum if IQAC changes them).
A7: Code | B7: Key aspect | C7: What the auditor verifies | D7: An item counts as valid only if | E7: Sampling unit | F7: Sample % | G7: Minimum sample | H7: How to sample | I7: Y (> 75%) | J7: C (60-75%) | K7: W (40-60%) | L7: D (< 40%) | M7: Items checked | N7: Valid items | O7: Auditor remarks | P7: Unit | Q7: Max marks | R7: Benchmark | S7: Validated value | T7: Marks obtained | U7: Percentage | V7: Grade | W7: Y | X7: C | Y7: W | Z7: D
A8: 8.1 | B8: Actions on CO, PO and PSO evaluation | Q8: =SUM(Q9:Q12) -> 40 | T8: =SUM(T9:T12) -> 0 | U8: =IF(COUNT(T9:T12)=0,"",ROUND(T8/Q8*100,2)) | V8: =IF(U8="","",IF(U8>YT*100,"Y",IF(U8>=CT*100,"C",IF(U8>=WT*100,"W","D")))) | W8: =SUM(W9:W12) -> 0 | X8: =SUM(X9:X12) -> 0 | Y8: =SUM(Y9:Y12) -> 0 | Z8: =SUM(Z9:Z12) -> 0
A9: 8.1.a | B9: Action plans for CO gaps (8.1.1) | C9: Action plans for CO gaps | D9: Course below target has dated action plan approved by course committee | E9: Courses below target | F9: 0.5 | G9: 3 | H9: Random courses below CO target | I9: All have action plans | J9: Most have plans | K9: Few have plans | L9: None | P9: % | Q9: 10 | T9: =IF(OR(S9="",R9="",R9=0),"",ROUND(Q9*MIN(S9/R9,1),2)) | U9: =IF(T9="","",ROUND(T9/Q9*100,2)) | V9: =IF(U9="","",IF(U9>YT*100,"Y",IF(U9>=CT*100,"C",IF(U9>=WT*100,"W","D")))) | W9: =IF($V9="Y",1,"") | X9: =IF($V9="C",1,"") | Y9: =IF($V9="W",1,"") | Z9: =IF($V9="D",1,"")
A10: 8.1.b | B10: CO actions implemented (8.1.1) | C10: CO actions implemented | D10: Evidence of the action (session record, revised material, re-test) | E10: Actions | F10: 0.25 | G10: 5 | H10: Random actions from action plans | I10: All implemented with evidence | J10: Most implemented | K10: About half | L10: Few or none | P10: % | Q10: 10 | T10: =IF(OR(S10="",R10="",R10=0),"",ROUND(Q10*MIN(S10/R10,1),2)) | U10: =IF(T10="","",ROUND(T10/Q10*100,2)) | V10: =IF(U10="","",IF(U10>YT*100,"Y",IF(U10>=CT*100,"C",IF(U10>=WT*100,"W","D")))) | W10: =IF($V10="Y",1,"") | X10: =IF($V10="C",1,"") | Y10: =IF($V10="W",1,"") | Z10: =IF($V10="D",1,"")
A11: 8.1.c | B11: Action plans for PO/PSO gaps (8.1.2) | C11: Action plans for PO/PSO gaps | D11: PO/PSO below target has dated action plan approved by DAB | E11: POs/PSOs below target | F11: 1 | G11: 3 | H11: Check every PO/PSO below target | I11: All have action plans | J11: Most | K11: Few | L11: None | P11: % | Q11: 10 | T11: =IF(OR(S11="",R11="",R11=0),"",ROUND(Q11*MIN(S11/R11,1),2)) | U11: =IF(T11="","",ROUND(T11/Q11*100,2)) | V11: =IF(U11="","",IF(U11>YT*100,"Y",IF(U11>=CT*100,"C",IF(U11>=WT*100,"W","D")))) | W11: =IF($V11="Y",1,"") | X11: =IF($V11="C",1,"") | Y11: =IF($V11="W",1,"") | Z11: =IF($V11="D",1,"")
A12: 8.1.d | B12: PO/PSO attainment improved (8.1.2) | C12: PO/PSO attainment improved | D12: Current attainment higher than previous year (sheets compared) | E12: POs/PSOs | F12: 1 | G12: 3 | H12: Check every PO/PSO below target last year | I12: Most improved | J12: Majority improved | K12: About half | L12: Few or none improved | P12: % | Q12: 10 | T12: =IF(OR(S12="",R12="",R12=0),"",ROUND(Q12*MIN(S12/R12,1),2)) | U12: =IF(T12="","",ROUND(T12/Q12*100,2)) | V12: =IF(U12="","",IF(U12>YT*100,"Y",IF(U12>=CT*100,"C",IF(U12>=WT*100,"W","D")))) | W12: =IF($V12="Y",1,"") | X12: =IF($V12="C",1,"") | Y12: =IF($V12="W",1,"") | Z12: =IF($V12="D",1,"")
A13: 8.2 | B13: Academic audit and actions taken | Q13: =SUM(Q14:Q15) -> 15 | T13: =SUM(T14:T15) -> 0 | U13: =IF(COUNT(T14:T15)=0,"",ROUND(T13/Q13*100,2)) | V13: =IF(U13="","",IF(U13>YT*100,"Y",IF(U13>=CT*100,"C",IF(U13>=WT*100,"W","D")))) | W13: =SUM(W14:W15) -> 0 | X13: =SUM(X14:X15) -> 0 | Y13: =SUM(Y14:Y15) -> 0 | Z13: =SUM(Z14:Z15) -> 0
A14: 8.2.a | B14: Audit observations closed | C14: Audit observations closed | D14: Observation has closure evidence accepted by IQAC (ATR) | E14: Observations | F14: 0.25 | G14: 5 | H14: Random observations from previous audit report | I14: All sampled closed with proof | J14: Most closed | K14: About half | L14: Few or none closed | P14: % | Q14: 10 | T14: =IF(OR(S14="",R14="",R14=0),"",ROUND(Q14*MIN(S14/R14,1),2)) | U14: =IF(T14="","",ROUND(T14/Q14*100,2)) | V14: =IF(U14="","",IF(U14>YT*100,"Y",IF(U14>=CT*100,"C",IF(U14>=WT*100,"W","D")))) | W14: =IF($V14="Y",1,"") | X14: =IF($V14="C",1,"") | Y14: =IF($V14="W",1,"") | Z14: =IF($V14="D",1,"")
A15: 8.2.b | B15: Audits conducted as scheduled | C15: Audits conducted as scheduled | D15: Audit report dated within scheduled window | E15: Audits | F15: 1 | G15: 2 | H15: Check every scheduled audit in the period | I15: All conducted on time | J15: One delayed | K15: One missed | L15: Most missed | P15: % | Q15: 5 | T15: =IF(OR(S15="",R15="",R15=0),"",ROUND(Q15*MIN(S15/R15,1),2)) | U15: =IF(T15="","",ROUND(T15/Q15*100,2)) | V15: =IF(U15="","",IF(U15>YT*100,"Y",IF(U15>=CT*100,"C",IF(U15>=WT*100,"W","D")))) | W15: =IF($V15="Y",1,"") | X15: =IF($V15="C",1,"") | Y15: =IF($V15="W",1,"") | Z15: =IF($V15="D",1,"")
A16: 8.3 | B16: Improvement in faculty qualification / contribution | Q16: =SUM(Q17:Q18) -> 15 | T16: =SUM(T17:T18) -> 0 | U16: =IF(COUNT(T17:T18)=0,"",ROUND(T16/Q16*100,2)) | V16: =IF(U16="","",IF(U16>YT*100,"Y",IF(U16>=CT*100,"C",IF(U16>=WT*100,"W","D")))) | W16: =SUM(W17:W18) -> 0 | X16: =SUM(X17:X18) -> 0 | Y16: =SUM(Y17:Y18) -> 0 | Z16: =SUM(Z17:Z18) -> 0
A17: 8.3.a | B17: Faculty qualification | C17: Faculty qualification improvement | D17: Ph.D. certificates verified for faculty counted in current % | E17: Faculty | F17: 0.25 | G17: 5 | H17: Random faculty counted in current %; compare with target | I17: Target met, verified | J17: Slightly below target | K17: Well below target | L17: No improvement | P17: No. | Q17: 8 | T17: =IF(OR(S17="",R17="",R17=0),"",ROUND(Q17*MIN(S17/R17,1),2)) | U17: =IF(T17="","",ROUND(T17/Q17*100,2)) | V17: =IF(U17="","",IF(U17>YT*100,"Y",IF(U17>=CT*100,"C",IF(U17>=WT*100,"W","D")))) | W17: =IF($V17="Y",1,"") | X17: =IF($V17="C",1,"") | Y17: =IF($V17="W",1,"") | Z17: =IF($V17="D",1,"")
A18: 8.3.b | B18: Faculty contribution | C18: Faculty contribution improvement | D18: Publications and FDPs verified for current count | E18: Items | F18: 0.25 | G18: 5 | H18: Random items from current count | I18: Target met, verified | J18: Slightly below target | K18: Well below target | L18: No improvement | P18: No. | Q18: 7 | T18: =IF(OR(S18="",R18="",R18=0),"",ROUND(Q18*MIN(S18/R18,1),2)) | U18: =IF(T18="","",ROUND(T18/Q18*100,2)) | V18: =IF(U18="","",IF(U18>YT*100,"Y",IF(U18>=CT*100,"C",IF(U18>=WT*100,"W","D")))) | W18: =IF($V18="Y",1,"") | X18: =IF($V18="C",1,"") | Y18: =IF($V18="W",1,"") | Z18: =IF($V18="D",1,"")
A19: 8.4 | B19: Improvement in academic performance | Q19: =SUM(Q20:Q21) -> 10 | T19: =SUM(T20:T21) -> 0 | U19: =IF(COUNT(T20:T21)=0,"",ROUND(T19/Q19*100,2)) | V19: =IF(U19="","",IF(U19>YT*100,"Y",IF(U19>=CT*100,"C",IF(U19>=WT*100,"W","D")))) | W19: =SUM(W20:W21) -> 0 | X19: =SUM(X20:X21) -> 0 | Y19: =SUM(Y20:Y21) -> 0 | Z19: =SUM(Z20:Z21) -> 0
